Workbook
Name clientes: [1]CLIENTES!$A$1:$A$3
Name clientes: [1]CLIENTES!$A$1:$A$3
Name clientes: [2]CLIENTES!$A$1:$A$3
Name clientes: [3]CLIENTES!$A$1:$A$3
Name codigos: 'DETALLE PRODUCTOSxPrecio'!$A$8:$A$99
Name codigos: 'DETALLE PRODUCTOSxPrecio (2)'!$A$8:$A$98
Name codigos: #REF!
Name datos: 'DETALLE PRODUCTOSxPrecio'!$A$7:$AJ$99
Name datos: 'DETALLE PRODUCTOSxPrecio (2)'!$A$7:$AE$98
Name datos: #REF!

Sheet DETALLE PRODUCTOSxPrecio (2)
J1: VALIDAR PRECIO
A2: PRECIOS ACTUALIZADOS ABRIL 2025 | J2: FALTA PRECIO PROD
J3: FALTA PRECIO PROD Y VALIDAR RECETA
J4: FALTA RECETA | P4: #1 ELAINE | T4: #2 CALICHE | X4: #3 VICTOR
D5: SAI OPEN | P5: INF PARA SAI OPEN | T5: INF PARA SAI OPEN | X5: INF PARA SAI OPEN | AC5: VALORES ACTUALES
AC6: A-0001 | AD6: B-0001 | AE6: C-0001
A7: CODIGO | B7: PRODUCTO | C7: PRESENTACION | D7: LINEA | E7: GRUPO | F7: SUB GRUPO | G7: MARCA | H7: CAMARAS DE COMERCIO DE DISTRIBUIDORES | I7: LUGAR DE ALMACENAMIENTO | J7: PRECIO DE PRODUCCIÓN POR UND | K7: TOTAL GASTOS VARIOS | L7: COSTO TOTAL UNIDAD | M7: COSTO UTILIDAD | N7: UTILIDAD | O7: PRECIO VENTA POR RECETA | P7: PRECIO DE VENTA 1 | Q7: % GANANCIA | R7: VALOR UTILIDAD | S7: DIF EN PRECIO | T7: PRECIO DE VENTA2 | U7: % GANANCIA2 | V7: VALOR UTILIDAD2 | W7: DIF EN PRECIO5 | X7: PRECIO DE VENTA 3 | Y7: % GANANCIA3 | Z7: VALOR UTILIDAD22 | AA7: DIF EN PRECIO55 | AB7: OBSERVACIONES | AC7: ELAINE GARZON | AD7: CALICHE-MANZ | AE7: VICTOR-CALI | AF7: VARIOS | AG7: OBSERVACION | AH7: ESTADO DE RECETAS
A8: 7T01 | B8: 7 TOROS | C8: 500 ML-Jarabe | D8: HOMEOPATICOS | E8: JARABES | F8: 500 ML | G8: NATURAL PALAGAR | I8: MARIA-IMPERIO NATURAL | J8: ='RECETAS JARABES'!G68 -> 2046.4421 | K8: ='Gtos Varios'!$B$22 -> 3070.5429 | L8: =+LISTPROD3[[#This Row],[PRECIO DE PRODUCCIÓN POR UND]]+LISTPROD3[[#This Row],[TOTAL GASTOS VARIOS]] -> 5116.985 | M8: ='RECETAS JARABES'!G73 -> 3088.4609 | N8: ='RECETAS JARABES'!H73 -> 0.54 | O8: ='RECETAS JARABES'!G74 -> 8807.8331 | P8: 8000 | Q8: =(LISTPROD3[[#This Row],[PRECIO DE VENTA 1]]-LISTPROD3[[#This Row],[COSTO TOTAL UNIDAD]])/LISTPROD3[[#This Row],[COSTO TOTAL UNIDAD]] -> 0.56342066 | R8: =LISTPROD3[[#This Row],[% GANANCIA]]*LISTPROD3[[#This Row],[COSTO TOTAL UNIDAD]] -> 2883.015 | S8: =+LISTPROD3[[#This Row],[PRECIO DE VENTA 1]]-LISTPROD3[[#This Row],[PRECIO VENTA POR RECETA]] -> -807.83305 | X8: 0 | AC8: 8000 | AD8: 0 | AE8: 0 | AF8: 0 | AH8: OK
A9: AM01 | B9: ALICITRIM LITRO | C9: 1000 ML-Jarabe | D9: HOMEOPATICOS | E9: JARABES | F9: LITRO 1000 ML | G9: CUBANO | I9: ANGIE-LHC | J9: ='RECETAS JARABES'!G98 -> 2074.0653 | K9: ='Gtos Varios'!$B$22 -> 3070.5429 | L9: =+LISTPROD3[[#This Row],[PRECIO DE PRODUCCIÓN POR UND]]+LISTPROD3[[#This Row],[TOTAL GASTOS VARIOS]] -> 5144.6082 | M9: ='RECETAS JARABES'!G103 -> 3390.7272 | N9: ='RECETAS JARABES'!$H$103 -> 0.59 | O9: ='RECETAS JARABES'!$G$104 -> 9137.7226 | P9: 7500 | Q9: =(LISTPROD3[[#This Row],[PRECIO DE VENTA 1]]-LISTPROD3[[#This Row],[COSTO TOTAL UNIDAD]])/LISTPROD3[[#This Row],[COSTO TOTAL UNIDAD]] -> 0.45783697 | R9: =LISTPROD3[[#This Row],[% GANANCIA]]*LISTPROD3[[#This Row],[COSTO TOTAL UNIDAD]] -> 2355.3918 | S9: =+LISTPROD3[[#This Row],[PRECIO DE VENTA 1]]-LISTPROD3[[#This Row],[PRECIO VENTA POR RECETA]] -> -1637.7226 | X9: 0 | AC9: 7500 | AD9: 0 | AE9: 0 | AF9: 0 | AH9: PREGUNTAR A LUIS POR PRECIOS Y FORMULA | AL9: CLIENTES
A10: AN01 | B10: ARBRON | C10: 500 ML-Jarabe | D10: HOMEOPATICOS | E10: JARABES | F10: 500 ML | G10: NATURAL PALAGAR | I10: MARIA-IMPERIO NATURAL | J10: ='RECETAS JARABES'!G132 -> 1088.0283 | K10: ='Gtos Varios'!$B$22 -> 3070.5429 | L10: =+LISTPROD3[[#This Row],[PRECIO DE PRODUCCIÓN POR UND]]+LISTPROD3[[#This Row],[TOTAL GASTOS VARIOS]] -> 4158.5711 | M10: ='RECETAS JARABES'!G137 -> 3475.4995 | N10: ='RECETAS JARABES'!$H$137 -> 0.73 | O10: ='RECETAS JARABES'!$G$138 -> 8236.4578 | P10: 7000 | Q10: =(LISTPROD3[[#This Row],[PRECIO DE VENTA 1]]-LISTPROD3[[#This Row],[COSTO TOTAL UNIDAD]])/LISTPROD3[[#This Row],[COSTO TOTAL UNIDAD]] -> 0.68327047 | R10: =LISTPROD3[[#This Row],[% GANANCIA]]*LISTPROD3[[#This Row],[COSTO TOTAL UNIDAD]] -> 2841.4289 | S10: =+LISTPROD3[[#This Row],[PRECIO DE VENTA 1]]-LISTPROD3[[#This Row],[PRECIO VENTA POR RECETA]] -> -1236.4578 | X10: 0 | AC10: 7000 | AD10: 0 | AE10: 0 | AF10: 0 | AH10: OK | AL10: PRECIO 1
A11: AV01 | B11: ARTERIO VENOSO | C11: 500 ML-Jarabe | D11: HOMEOPATICOS | E11: JARABES | F11: 500 ML | G11: PHARMA | I11: LUIS-FARMACIA NATIVA | J11: ='RECETAS JARABES'!G167 -> 2134.0639 | K11: ='Gtos Varios'!$B$22 -> 3070.5429 | L11: =+LISTPROD3[[#This Row],[PRECIO DE PRODUCCIÓN POR UND]]+LISTPROD3[[#This Row],[TOTAL GASTOS VARIOS]] -> 5204.6067 | M11: ='RECETAS JARABES'!G172 -> 3368.0565 | N11: ='RECETAS JARABES'!$H$172 -> 0.58 | O11: ='RECETAS JARABES'!$G$173 -> 9175.0503 | P11: 6000 | Q11: =(LISTPROD3[[#This Row],[PRECIO DE VENTA 1]]-LISTPROD3[[#This Row],[COSTO TOTAL UNIDAD]])/LISTPROD3[[#This Row],[COSTO TOTAL UNIDAD]] -> 0.15282485 | R11: =LISTPROD3[[#This Row],[% GANANCIA]]*LISTPROD3[[#This Row],[COSTO TOTAL UNIDAD]] -> 795.39326 | S11: =+LISTPROD3[[#This Row],[PRECIO DE VENTA 1]]-LISTPROD3[[#This Row],[PRECIO VENTA POR RECETA]] -> -3175.0503 | T11: 5000 | U11: =(LISTPROD3[[#This Row],[PRECIO DE VENTA2]]-LISTPROD3[[#This Row],[COSTO TOTAL UNIDAD]])/LISTPROD3[[#This Row],[COSTO TOTAL UNIDAD]] -> -0.039312622 | V11: =+LISTPROD3[[#This Row],[% GANANCIA2]]*LISTPROD3[[#This Row],[COSTO TOTAL UNIDAD]] -> -204.60674 | W11: =LISTPROD3[[#This Row],[PRECIO DE VENTA2]]-LISTPROD3[[#This Row],[PRECIO VENTA POR RECETA]] -> -4175.0503 | X11: 5000 | Y11: =(LISTPROD3[[#This Row],[PRECIO DE VENTA 3]]-LISTPROD3[[#This Row],[COSTO TOTAL UNIDAD]])/LISTPROD3[[#This Row],[COSTO TOTAL UNIDAD]] -> -0.039312622 | Z11: =LISTPROD3[[#This Row],[% GANANCIA3]]*LISTPROD3[[#This Row],[COSTO TOTAL UNIDAD]] -> -204.60674 | AC11: 6000 | AD11: 5000 | AE11: 5000 | AF11: 5000 | AH11: OK | AL11: PRECIO 2-MANZ
A12: A01 | B12: ARTRIN | C12: PASTILLAS 30 | D12: HOMEOPATICOS | E12: PASTILLAS | F12: PASTILLAS DE 30 UND | I12: LUIS-FARMACIA NATIVA | J12: ='RECETAS PASTILLAS'!G16 -> 2450 | K12: ='Gtos Varios'!$B$22 -> 3070.5429 | L12: =+LISTPROD3[[#This Row],[TOTAL GASTOS VARIOS]]+LISTPROD3[[#This Row],[PRECIO DE PRODUCCIÓN POR UND]] -> 5520.5429 | M12: ='RECETAS PASTILLAS'!G21 -> 3367.6115 | N12: ='RECETAS PASTILLAS'!H21 -> 0.55 | O12: ='RECETAS PASTILLAS'!G22 -> 9490.5415 | P12: 3200 | Q12: =(LISTPROD3[[#This Row],[PRECIO DE VENTA 1]]-LISTPROD3[[#This Row],[COSTO TOTAL UNIDAD]])/LISTPROD3[[#This Row],[COSTO TOTAL UNIDAD]] -> -0.42034686 | R12: =LISTPROD3[[#This Row],[% GANANCIA]]*LISTPROD3[[#This Row],[COSTO TOTAL UNIDAD]] -> -2320.5429 | T12: 3200 | U12: =(LISTPROD3[[#This Row],[PRECIO DE VENTA2]]-LISTPROD3[[#This Row],[COSTO TOTAL UNIDAD]])/LISTPROD3[[#This Row],[COSTO TOTAL UNIDAD]] -> -0.42034686 | V12: =LISTPROD3[[#This Row],[PRECIO DE VENTA2]]*LISTPROD3[[#This Row],[% GANANCIA2]] -> -1345.11 | X12: 3200 | Y12: =(LISTPROD3[[#This Row],[PRECIO DE VENTA 3]]-LISTPROD3[[#This Row],[COSTO TOTAL UNIDAD]])/LISTPROD3[[#This Row],[COSTO TOTAL UNIDAD]] -> -0.42034686 | Z12: =+LISTPROD3[[#This Row],[PRECIO DE VENTA 3]]*LISTPROD3[[#This Row],[% GANANCIA3]] -> -1345.11 | AB12: Se toma solo el costo de produccion no margen de utilidad | AC12: 3200 | AD12: 3200 | AE12: 3200 | AF12: 3200 | AH12: OK-26/3/2025 | AL12: PRECIO 3-Victor
A13: BP01 | B13: BIL PRO | C13: 500 ML-Jarabe | D13: HOMEOPATICOS | E13: JARABES | F13: 500 ML | G13: NATURAL PALAGAR | I13: MARIA-IMPERIO NATURAL | J13: ='RECETAS JARABES'!G200 -> 949.4736 | K13: ='Gtos Varios'!$B$22 -> 3070.5429 | L13: =+LISTPROD3[[#This Row],[PRECIO DE PRODUCCIÓN POR UND]]+LISTPROD3[[#This Row],[TOTAL GASTOS VARIOS]] -> 4020.0165 | M13: ='RECETAS JARABES'!G205 -> 3374.3546 | N13: ='RECETAS JARABES'!H205 -> 0.73 | O13: ='RECETAS JARABES'!G206 -> 7996.7582 | P13: 7000 | Q13: =(LISTPROD3[[#This Row],[PRECIO DE VENTA 1]]-LISTPROD3[[#This Row],[COSTO TOTAL UNIDAD]])/LISTPROD3[[#This Row],[COSTO TOTAL UNIDAD]] -> 0.7412864 | R13: =LISTPROD3[[#This Row],[% GANANCIA]]*LISTPROD3[[#This Row],[COSTO TOTAL UNIDAD]] -> 2979.9835 | S13: =+LISTPROD3[[#This Row],[PRECIO DE VENTA 1]]-LISTPROD3[[#This Row],[PRECIO VENTA POR RECETA]] -> -996.75823 | AC13: 7000 | AD13: 0 | AE13: 0 | AF13: 0 | AH13: OK
A14: B01 | B14: BIO 44 | C14: 500 ML-Jarabe | D14: HOMEOPATICOS | E14: JARABES | F14: 500 ML | G14: PHARMA | I14: LUIS-FARMACIA NATIVA | J14: ='RECETAS JARABES'!G232 -> 2388.8636 | K14: ='Gtos Varios'!$B$22 -> 3070.5429 | L14: =+LISTPROD3[[#This Row],[PRECIO DE PRODUCCIÓN POR UND]]+LISTPROD3[[#This Row],[TOTAL GASTOS VARIOS]] -> 5459.4064 | M14: ='RECETAS JARABES'!G237 -> 3333.9865 | N14: ='RECETAS JARABES'!H237 -> 0.55 | O14: ='RECETAS JARABES'!G238 -> 9395.78 | P14: 6000 | Q14: =(LISTPROD3[[#This Row],[PRECIO DE VENTA 1]]-LISTPROD3[[#This Row],[COSTO TOTAL UNIDAD]])/LISTPROD3[[#This Row],[COSTO TOTAL UNIDAD]] -> 0.099020578 | R14: =LISTPROD3[[#This Row],[% GANANCIA]]*LISTPROD3[[#This Row],[COSTO TOTAL UNIDAD]] -> 540.59358 | S14: =+LISTPROD3[[#This Row],[PRECIO DE VENTA 1]]-LISTPROD3[[#This Row],[PRECIO VENTA POR RECETA]] -> -3395.78 | T14: 5000 | U14: =(LISTPROD3[[#This Row],[PRECIO DE VENTA2]]-LISTPROD3[[#This Row],[COSTO TOTAL UNIDAD]])/LISTPROD3[[#This Row],[COSTO TOTAL UNIDAD]] -> -0.084149518 | V14: =+LISTPROD3[[#This Row],[% GANANCIA2]]*LISTPROD3[[#This Row],[COSTO TOTAL UNIDAD]] -> -459.40642 | W14: =LISTPROD3[[#This Row],[PRECIO DE VENTA2]]-LISTPROD3[[#This Row],[PRECIO VENTA POR RECETA]] -> -4395.78 | X14: 5000 | Y14: =(LISTPROD3[[#This Row],[PRECIO DE VENTA 3]]-LISTPROD3[[#This Row],[COSTO TOTAL UNIDAD]])/LISTPROD3[[#This Row],[COSTO TOTAL UNIDAD]] -> -0.084149518 | Z14: =LISTPROD3[[#This Row],[% GANANCIA3]]*LISTPROD3[[#This Row],[COSTO TOTAL UNIDAD]] -> -459.40642 | AC14: 6000 | AD14: 5000 | AE14: 5000 | AF14: 5000 | AH14: FALTA
A15: BO01 | B15: BOTANPROS | C15: 500 ML-Jarabe | D15: HOMEOPATICOS | E15: JARABES | F15: 500 ML | G15: N/A | I15: LUIS-FARMACIA NATIVA | J15: ='RECETAS JARABES'!G264 -> 984.66726 | K15: ='Gtos Varios'!$B$22 -> 3070.5429 | L15: =+LISTPROD3[[#This Row],[PRECIO DE PRODUCCIÓN POR UND]]+LISTPROD3[[#This Row],[TOTAL GASTOS VARIOS]] -> 4055.2101 | M15: ='RECETAS JARABES'!G269 -> 3353.47 | N15: ='RECETAS JARABES'!H269 -> 0.72 | O15: ='RECETAS JARABES'!G270 -> 8011.0673 | P15: 7000 | Q15: =(LISTPROD3[[#This Row],[PRECIO DE VENTA 1]]-LISTPROD3[[#This Row],[COSTO TOTAL UNIDAD]])/LISTPROD3[[#This Row],[COSTO TOTAL UNIDAD]] -> 0.72617443 | R15: =LISTPROD3[[#This Row],[% GANANCIA]]*LISTPROD3[[#This Row],[COSTO TOTAL UNIDAD]] -> 2944.7899 | S15: =+LISTPROD3[[#This Row],[PRECIO DE VENTA 1]]-LISTPROD3[[#This Row],[PRECIO VENTA POR RECETA]] -> -1011.0673 | T15: 5000 | U15: =(LISTPROD3[[#This Row],[PRECIO DE VENTA2]]-LISTPROD3[[#This Row],[COSTO TOTAL UNIDAD]])/LISTPROD3[[#This Row],[COSTO TOTAL UNIDAD]] -> 0.23298173 | V15: =+LISTPROD3[[#This Row],[% GANANCIA2]]*LISTPROD3[[#This Row],[COSTO TOTAL UNIDAD]] -> 944.78989 | W15: =LISTPROD3[[#This Row],[PRECIO DE VENTA2]]-LISTPROD3[[#This Row],[PRECIO VENTA POR RECETA]] -> -3011.0673 | X15: 5000 | Y15: =(LISTPROD3[[#This Row],[PRECIO DE VENTA 3]]-LISTPROD3[[#This Row],[COSTO TOTAL UNIDAD]])/LISTPROD3[[#This Row],[COSTO TOTAL UNIDAD]] -> 0.23298173 | Z15: =LISTPROD3[[#This Row],[% GANANCIA3]]*LISTPROD3[[#This Row],[COSTO TOTAL UNIDAD]] -> 944.78989 | AC15: 7000 | AD15: 5000 | AE15: 5000 | AF15: 5000 | AH15: OK
A16: CO01 | B16: CALCUBANO LITRO | C16: 1000 ML-Jarabe | D16: HOMEOPATICOS | E16: JARABES | F16: LITRO 1000 ML | G16: CUBANO | I16: ANGIE-LHC | J16: ='RECETAS JARABES'!G295 -> 2745.6159 | K16: ='Gtos Varios'!$B$22 -> 3070.5429 | L16: =+LISTPROD3[[#This Row],[PRECIO DE PRODUCCIÓN POR UND]]+LISTPROD3[[#This Row],[TOTAL GASTOS VARIOS]] -> 5816.1587 | M16: ='RECETAS JARABES'!$G$300 -> 3337.6439 | N16: ='RECETAS JARABES'!H300 -> 0.52 | O16: ='RECETAS JARABES'!G301 -> 9756.1897 | P16: 7500 | Q16: =(LISTPROD3[[#This Row],[PRECIO DE VENTA 1]]-LISTPROD3[[#This Row],[COSTO TOTAL UNIDAD]])/LISTPROD3[[#This Row],[COSTO TOTAL UNIDAD]] -> 0.28951089 | R16: =LISTPROD3[[#This Row],[% GANANCIA]]*LISTPROD3[[#This Row],[COSTO TOTAL UNIDAD]] -> 1683.8413 | S16: =+LISTPROD3[[#This Row],[PRECIO DE VENTA 1]]-LISTPROD3[[#This Row],[PRECIO VENTA POR RECETA]] -> -2256.1897 | T16: 0 | V16: =+LISTPROD3[[#This Row],[% GANANCIA2]]*LISTPROD3[[#This Row],[COSTO TOTAL UNIDAD]] -> 0 | W16: =LISTPROD3[[#This Row],[PRECIO DE VENTA2]]-LISTPROD3[[#This Row],[PRECIO VENTA POR RECETA]] -> -9756.1897 | AC16: 7500 | AD16: 0 | AE16: 0 | AF16: 0 | AH16: OK
A17: CM01 | B17: CARDO MARIANO (Capsulas) | C17: ENVASE TIENE 60 CAPSULAS | D17: HOMEOPATICOS | E17: CAPSULAS | F17: CAPSULAS 60 UND | I17: ANGIE-LHC | J17: ='RECETAS CAPS'!U19 -> 3943.7 | K17: ='Gtos Varios'!$B$22 -> 3070.5429 | L17: =+LISTPROD3[[#This Row],[TOTAL GASTOS VARIOS]]+LISTPROD3[[#This Row],[PRECIO DE PRODUCCIÓN POR UND]] -> 7014.2429 | M17: ='RECETAS CAPS'!U25 -> 3351.3172 | N17: ='RECETAS CAPS'!V25 -> 0.44 | O17: ='RECETAS CAPS'!U26 -> 10967.947 | P17: 10968 | Q17: =(LISTPROD3[[#This Row],[PRECIO DE VENTA 1]]-LISTPROD3[[#This Row],[COSTO TOTAL UNIDAD]])/LISTPROD3[[#This Row],[COSTO TOTAL UNIDAD]] -> 0.56367554 | R17: =LISTPROD3[[#This Row],[% GANANCIA]]*LISTPROD3[[#This Row],[COSTO TOTAL UNIDAD]] -> 3953.7571 | AC17: 9600 | AD17: 0 | AE17: 0 | AF17: 0 | AH17: OK
A18: CT01 | B18: CARTILAGO DE TIBURON | C18: 500 ML-Jarabe | D18: HOMEOPATICOS | E18: JARABES | F18: 500 ML | G18: PHARMA | I18: LUIS-FARMACIA NATIVA | J18: ='RECETAS JARABES'!G327 -> 2482.1171 | K18: ='Gtos Varios'!$B$22 -> 3070.5429 | L18: =+LISTPROD3[[#This Row],[PRECIO DE PRODUCCIÓN POR UND]]+LISTPROD3[[#This Row],[TOTAL GASTOS VARIOS]] -> 5552.6599 | M18: ='RECETAS JARABES'!$G$332 -> 3323.7254 | N18: ='RECETAS JARABES'!$H$332 -> 0.54 | O18: ='RECETAS JARABES'!$G$333 -> 9478.7725 | P18: 6000 | Q18: =(LISTPROD3[[#This Row],[PRECIO DE VENTA 1]]-LISTPROD3[[#This Row],[COSTO TOTAL UNIDAD]])/LISTPROD3[[#This Row],[COSTO TOTAL UNIDAD]] -> 0.080563205 | R18: =LISTPROD3[[#This Row],[% GANANCIA]]*LISTPROD3[[#This Row],[COSTO TOTAL UNIDAD]] -> 447.34008 | S18: =+LISTPROD3[[#This Row],[PRECIO DE VENTA 1]]-LISTPROD3[[#This Row],[PRECIO VENTA POR RECETA]] -> -3478.7725 | T18: 5000 | U18: =(LISTPROD3[[#This Row],[PRECIO DE VENTA2]]-LISTPROD3[[#This Row],[COSTO TOTAL UNIDAD]])/LISTPROD3[[#This Row],[COSTO TOTAL UNIDAD]] -> -0.099530663 | V18: =+LISTPROD3[[#This Row],[% GANANCIA2]]*LISTPROD3[[#This Row],[COSTO TOTAL UNIDAD]] -> -552.65992 | W18: =LISTPROD3[[#This Row],[PRECIO DE VENTA2]]-LISTPROD3[[#This Row],[PRECIO VENTA POR RECETA]] -> -4478.7725 | X18: 5000 | Y18: =(LISTPROD3[[#This Row],[PRECIO DE VENTA 3]]-LISTPROD3[[#This Row],[COSTO TOTAL UNIDAD]])/LISTPROD3[[#This Row],[COSTO TOTAL UNIDAD]] -> -0.099530663 | Z18: =LISTPROD3[[#This Row],[% GANANCIA3]]*LISTPROD3[[#This Row],[COSTO TOTAL UNIDAD]] -> -552.65992 | AC18: 6000 | AD18: 5000 | AE18: 5000 | AF18: 5000 | AH18: OK
A19: CHP01 | B19: CHANCA PIEDRA JARABE | C19: 500 ML-Jarabe | D19: HOMEOPATICOS | E19: JARABES | F19: 500 ML | G19: PHARMA | I19: LUIS-FARMACIA NATIVA | J19: ='RECETAS JARABES'!G364 -> 2112.0478 | K19: ='Gtos Varios'!$B$22 -> 3070.5429 | L19: =+LISTPROD3[[#This Row],[PRECIO DE PRODUCCIÓN POR UND]]+LISTPROD3[[#This Row],[TOTAL GASTOS VARIOS]] -> 5182.5907 | M19: ='RECETAS JARABES'!$G$369 -> 3355.2871 | N19: ='RECETAS JARABES'!H369 -> 0.58 | O19: ='RECETAS JARABES'!G370 -> 9140.265 | P19: 6000 | Q19: =(LISTPROD3[[#This Row],[PRECIO DE VENTA 1]]-LISTPROD3[[#This Row],[COSTO TOTAL UNIDAD]])/LISTPROD3[[#This Row],[COSTO TOTAL UNIDAD]] -> 0.15772215 | R19: =LISTPROD3[[#This Row],[% GANANCIA]]*LISTPROD3[[#This Row],[COSTO TOTAL UNIDAD]] -> 817.40932 | S19: =+LISTPROD3[[#This Row],[PRECIO DE VENTA 1]]-LISTPROD3[[#This Row],[PRECIO VENTA POR RECETA]] -> -3140.265 | T19: 5000 | U19: =(LISTPROD3[[#This Row],[PRECIO DE VENTA2]]-LISTPROD3[[#This Row],[COSTO TOTAL UNIDAD]])/LISTPROD3[[#This Row],[COSTO TOTAL UNIDAD]] -> -0.035231546 | V19: =+LISTPROD3[[#This Row],[% GANANCIA2]]*LISTPROD3[[#This Row],[COSTO TOTAL UNIDAD]] -> -182.59068 | W19: =LISTPROD3[[#This Row],[PRECIO DE VENTA2]]-LISTPROD3[[#This Row],[PRECIO VENTA POR RECETA]] -> -4140.265 | X19: 5000 | Y19: =(LISTPROD3[[#This Row],[PRECIO DE VENTA 3]]-LISTPROD3[[#This Row],[COSTO TOTAL UNIDAD]])/LISTPROD3[[#This Row],[COSTO TOTAL UNIDAD]] -> -0.035231546 | Z19: =LISTPROD3[[#This Row],[% GANANCIA3]]*LISTPROD3[[#This Row],[COSTO TOTAL UNIDAD]] -> -182.59068 | AC19: 6000 | AD19: 5000 | AE19: 5000 | AF19: 5000 | AH19: OK
A20: CL01 | B20: CIR LAN LITRO | C20: 1000 ML-Jarabe | D20: HOMEOPATICOS | E20: JARABES | F20: LITRO 1000 ML | G20: NATURAL PALAGAR | I20: MARIA-IMPERIO NATURAL | J20: ='RECETAS JARABES'!G396 -> 1054.3662 | K20: ='Gtos Varios'!$B$22 -> 3070.5429 | L20: =+LISTPROD3[[#This Row],[PRECIO DE PRODUCCIÓN POR UND]]+LISTPROD3[[#This Row],[TOTAL GASTOS VARIOS]] -> 4124.9091 | M20: ='RECETAS JARABES'!G401 -> 3450.9262 | N20: ='RECETAS JARABES'!H401 -> 0.73 | O20: ='RECETAS JARABES'!G402 -> 8178.2224 | P20: 7000 | Q20: =(LISTPROD3[[#This Row],[PRECIO DE VENTA 1]]-LISTPROD3[[#This Row],[COSTO TOTAL UNIDAD]])/LISTPROD3[[#This Row],[COSTO TOTAL UNIDAD]] -> 0.69700711 | R20: =LISTPROD3[[#This Row],[% GANANCIA]]*LISTPROD3[[#This Row],[COSTO TOTAL UNIDAD]] -> 2875.0909 | S20: =+LISTPROD3[[#This Row],[PRECIO DE VENTA 1]]-LISTPROD3[[#This Row],[PRECIO VENTA POR RECETA]] -> -1178.2224 | AC20: 7000 | AD20: 0 | AE20: 0 | AF20: 0 | AH20: OK
A21: CV01 | B21: CIRCULAV LITRO | C21: 1000 ML-Jarabe | D21: HOMEOPATICOS | E21: JARABES | F21: LITRO 1000 ML | G21: CUBANO | I21: ANGIE-LHC | J21: ='RECETAS JARABES'!G426 -> 2060.4127 | K21: ='Gtos Varios'!$B$22 -> 3070.5429 | L21: =+LISTPROD3[[#This Row],[PRECIO DE PRODUCCIÓN POR UND]]+LISTPROD3[[#This Row],[TOTAL GASTOS VARIOS]] -> 5130.9555 | M21: ='RECETAS JARABES'!G431 -> 3210.6719 | N21: ='RECETAS JARABES'!H431 -> 0.56 | O21: ='RECETAS JARABES'!G432 -> 8944.0146 | P21: 7500 | Q21: =(LISTPROD3[[#This Row],[PRECIO DE VENTA 1]]-LISTPROD3[[#This Row],[COSTO TOTAL UNIDAD]])/LISTPROD3[[#This Row],[COSTO TOTAL UNIDAD]] -> 0.46171604 | R21: =LISTPROD3[[#This Row],[% GANANCIA]]*LISTPROD3[[#This Row],[COSTO TOTAL UNIDAD]] -> 2369.0445 | S21: =+LISTPROD3[[#This Row],[PRECIO DE VENTA 1]]-LISTPROD3[[#This Row],[PRECIO VENTA POR RECETA]] -> -1444.0146 | AC21: 7500 | AD21: 0 | AE21: 0 | AF21: 0 | AH21: PREGUNTAR A LUIS POR PRECIOS Y FORMULA
A22: CG01 | B22: COLAGENO | C22: 500 ML-Jarabe | D22: HOMEOPATICOS | E22: JARABES | F22: 500 ML | G22: PHARMA | I22: LUIS-FARMACIA NATIVA | J22: ='RECETAS JARABES'!G460 -> 2662.4346 | K22: ='Gtos Varios'!$B$22 -> 3070.5429 | L22: =+LISTPROD3[[#This Row],[PRECIO DE PRODUCCIÓN POR UND]]+LISTPROD3[[#This Row],[TOTAL GASTOS VARIOS]] -> 5732.9774 | M22: ='RECETAS JARABES'!G465 -> 3357.7432 | N22: ='RECETAS JARABES'!H465 -> 0.53 | O22: ='RECETAS JARABES'!G466 -> 9693.1078 | P22: 6000 | Q22: =(LISTPROD3[[#This Row],[PRECIO DE VENTA 1]]-LISTPROD3[[#This Row],[COSTO TOTAL UNIDAD]])/LISTPROD3[[#This Row],[COSTO TOTAL UNIDAD]] -> 0.046576599 | R22: =LISTPROD3[[#This Row],[% GANANCIA]]*LISTPROD3[[#This Row],[COSTO TOTAL UNIDAD]] -> 267.02259 | S22: =+LISTPROD3[[#This Row],[PRECIO DE VENTA 1]]-LISTPROD3[[#This Row],[PRECIO VENTA POR RECETA]] -> -3693.1078 | T22: 5000 | U22: =(LISTPROD3[[#This Row],[PRECIO DE VENTA2]]-LISTPROD3[[#This Row],[COSTO TOTAL UNIDAD]])/LISTPROD3[[#This Row],[COSTO TOTAL UNIDAD]] -> -0.12785283 | V22: =+LISTPROD3[[#This Row],[% GANANCIA2]]*LISTPROD3[[#This Row],[COSTO TOTAL UNIDAD]] -> -732.97741 | W22: =LISTPROD3[[#This Row],[PRECIO DE VENTA2]]-LISTPROD3[[#This Row],[PRECIO VENTA POR RECETA]] -> -4693.1078 | X22: 5000 | Y22: =(LISTPROD3[[#This Row],[PRECIO DE VENTA 3]]-LISTPROD3[[#This Row],[COSTO TOTAL UNIDAD]])/LISTPROD3[[#This Row],[COSTO TOTAL UNIDAD]] -> -0.12785283 | Z22: =LISTPROD3[[#This Row],[% GANANCIA3]]*LISTPROD3[[#This Row],[COSTO TOTAL UNIDAD]] -> -732.97741 | AC22: 6000 | AD22: 5000 | AE22: 5000 | AF22: 5000 | AH22: OK
A23: CC01 | B23: COLIRIO CUBANO (Gotas) | C23: 25 ML | D23: HOMEOPATICOS | E23: GOTAS | F23: 25 ML | I23: LUIS-FARMACIA NATIVA | J23: FALTA RECETA | K23: ='Gtos Varios'!$B$22 -> 3070.5429 | M23: ='RECETAS GOTAS'!K156 -> 3391.0937 | N23: ='RECETAS GOTAS'!L156 -> 0.62 | O23: ='RECETAS GOTAS'!K157 -> 8860.5996 | P23: 3500 | Q23: =(LISTPROD3[[#This Row],[PRECIO DE VENTA 1]]-LISTPROD3[[#This Row],[COSTO TOTAL UNIDAD]])/LISTPROD3[[#This Row],[COSTO TOTAL UNIDAD]] -> #DIV/0! | R23: =LISTPROD3[[#This Row],[% GANANCIA]]*LISTPROD3[[#This Row],[COSTO TOTAL UNIDAD]] -> #DIV/0! | T23: 0 | U23: =(LISTPROD3[[#This Row],[PRECIO DE VENTA2]]-LISTPROD3[[#This Row],[COSTO TOTAL UNIDAD]])/LISTPROD3[[#This Row],[COSTO TOTAL UNIDAD]] -> #DIV/0! | V23: =LISTPROD3[[#This Row],[PRECIO DE VENTA2]]*LISTPROD3[[#This Row],[% GANANCIA2]] -> #DIV/0! | W23: =LISTPROD3[[#This Row],[PRECIO DE VENTA2]]-LISTPROD3[[#This Row],[PRECIO VENTA POR RECETA]] -> -8860.5996 | X23: 0 | AC23: 3500 | AD23: 0 | AE23: 0 | AF23: 0 | AH23: PREGUNTAR A LUIS POR PRECIOS Y FORMULA
A24: CSZ01 | B24: COLIRIO SABILA Y ZANAHORIA (Gotas) | C24: 25 ML | D24: HOMEOPATICOS | E24: GOTAS | F24: 25 ML | I24: LUIS-FARMACIA NATIVA | J24: FALTA RECETA | K24: ='Gtos Varios'!$B$22 -> 3070.5429 | P24: 2000 | Q24: =(LISTPROD3[[#This Row],[PRECIO DE VENTA 1]]-LISTPROD3[[#This Row],[COSTO TOTAL UNIDAD]])/LISTPROD3[[#This Row],[COSTO TOTAL UNIDAD]] -> #DIV/0! | R24: =LISTPROD3[[#This Row],[% GANANCIA]]*LISTPROD3[[#This Row],[COSTO TOTAL UNIDAD]] -> #DIV/0! | T24: 5000 | U24: =(LISTPROD3[[#This Row],[PRECIO DE VENTA2]]-LISTPROD3[[#This Row],[COSTO TOTAL UNIDAD]])/LISTPROD3[[#This Row],[COSTO TOTAL UNIDAD]] -> #DIV/0! | V24: =LISTPROD3[[#This Row],[PRECIO DE VENTA2]]*LISTPROD3[[#This Row],[% GANANCIA2]] -> #DIV/0! | W24: =LISTPROD3[[#This Row],[PRECIO DE VENTA2]]-LISTPROD3[[#This Row],[PRECIO VENTA POR RECETA]] -> 5000 | X24: 5000 | AC24: 2000 | AD24: 5000 | AE24: 5000 | AF24: 5000 | AH24: FALTA
A25: CCN01 | B25: COLON CLEARSEN | C25: 500 ML-Jarabe | D25: HOMEOPATICOS | E25: JARABES | F25: 500 ML | G25: PHARMA | I25: LUIS-FARMACIA NATIVA | J25: FALTA PRECIO PROD | K25: ='Gtos Varios'!$B$22 -> 3070.5429 | L25: =+LISTPROD3[[#This Row],[PRECIO DE PRODUCCIÓN POR UND]]+LISTPROD3[[#This Row],[TOTAL GASTOS VARIOS]] -> #VALUE! | M25: ='RECETAS JARABES'!G500 -> 3378.6696 | N25: ='RECETAS JARABES'!H500 -> 0.58 | O25: ='RECETAS JARABES'!G501 -> 9203.9619 | P25: 6000 | R25: =LISTPROD3[[#This Row],[% GANANCIA]]*LISTPROD3[[#This Row],[COSTO TOTAL UNIDAD]] -> #VALUE! | S25: =+LISTPROD3[[#This Row],[PRECIO DE VENTA 1]]-LISTPROD3[[#This Row],[PRECIO VENTA POR RECETA]] -> -3203.9619 | T25: 5000 | U25: =(LISTPROD3[[#This Row],[PRECIO DE VENTA2]]-LISTPROD3[[#This Row],[COSTO TOTAL UNIDAD]])/LISTPROD3[[#This Row],[COSTO TOTAL UNIDAD]] -> #VALUE! | V25: =+LISTPROD3[[#This Row],[% GANANCIA2]]*LISTPROD3[[#This Row],[COSTO TOTAL UNIDAD]] -> #VALUE! | W25: =LISTPROD3[[#This Row],[PRECIO DE VENTA2]]-LISTPROD3[[#This Row],[PRECIO VENTA POR RECETA]] -> -4203.9619 | X25: 5000 | Y25: =(LISTPROD3[[#This Row],[PRECIO DE VENTA 3]]-LISTPROD3[[#This Row],[COSTO TOTAL UNIDAD]])/LISTPROD3[[#This Row],[COSTO TOTAL UNIDAD]] -> #VALUE! | Z25: =LISTPROD3[[#This Row],[% GANANCIA3]]*LISTPROD3[[#This Row],[COSTO TOTAL UNIDAD]] -> #VALUE! | AC25: 6000 | AD25: 5000 | AE25: 5000 | AF25: 5000 | AH25: OK
A26: CB01 | B26: COMPLEJO B | C26: 500 ML-Jarabe | D26: HOMEOPATICOS | E26: JARABES | F26: 500 ML | G26: PHARMA | I26: LUIS-FARMACIA NATIVA | J26: ='RECETAS JARABES'!G529 -> 2179.2612 | K26: ='Gtos Varios'!$B$22 -> 3070.5429 | L26: =+LISTPROD3[[#This Row],[PRECIO DE PRODUCCIÓN POR UND]]+LISTPROD3[[#This Row],[TOTAL GASTOS VARIOS]] -> 5249.804 | M26: ='RECETAS JARABES'!$G$534 -> 3394.2709 | N26: ='RECETAS JARABES'!$H$534 -> 0.58 | O26: ='RECETAS JARABES'!$G$535 -> 9246.4621 | P26: 6000 | Q26: =(LISTPROD3[[#This Row],[PRECIO DE VENTA 1]]-LISTPROD3[[#This Row],[COSTO TOTAL UNIDAD]])/LISTPROD3[[#This Row],[COSTO TOTAL UNIDAD]] -> 0.1428998 | R26: =LISTPROD3[[#This Row],[% GANANCIA]]*LISTPROD3[[#This Row],[COSTO TOTAL UNIDAD]] -> 750.19596 | S26: =+LISTPROD3[[#This Row],[PRECIO DE VENTA 1]]-LISTPROD3[[#This Row],[PRECIO VENTA POR RECETA]] -> -3246.4621 | T26: 5000 | U26: =(LISTPROD3[[#This Row],[PRECIO DE VENTA2]]-LISTPROD3[[#This Row],[COSTO TOTAL UNIDAD]])/LISTPROD3[[#This Row],[COSTO TOTAL UNIDAD]] -> -0.047583498 | V26: =+LISTPROD3[[#This Row],[% GANANCIA2]]*LISTPROD3[[#This Row],[COSTO TOTAL UNIDAD]] -> -249.80404 | W26: =LISTPROD3[[#This Row],[PRECIO DE VENTA2]]-LISTPROD3[[#This Row],[PRECIO VENTA POR RECETA]] -> -4246.4621 | X26: 5000 | Y26: =(LISTPROD3[[#This Row],[PRECIO DE VENTA 3]]-LISTPROD3[[#This Row],[COSTO TOTAL UNIDAD]])/LISTPROD3[[#This Row],[COSTO TOTAL UNIDAD]] -> -0.047583498 | Z26: =LISTPROD3[[#This Row],[% GANANCIA3]]*LISTPROD3[[#This Row],[COSTO TOTAL UNIDAD]] -> -249.80404 | AC26: 6000 | AD26: 5000 | AE26: 5000 | AF26: 5000 | AH26: OK
A27: CPC01 | B27: CONCENTRADO DE PLANTAS CUBANA | C27: 500 ML-Jarabe | D27: HOMEOPATICOS | E27: JARABES | F27: 500 ML | G27: CUBANO | H27: TIENE CAMARA DE COMERCIO UN TERCERO COMO DISTRIBUIDOR | I27: ANGIE-LHC | J27: ='RECETAS JARABES'!G562 -> 2122.6344 | K27: ='Gtos Varios'!$B$22 -> 3070.5429 | L27: =+LISTPROD3[[#This Row],[PRECIO DE PRODUCCIÓN POR UND]]+LISTPROD3[[#This Row],[TOTAL GASTOS VARIOS]] -> 5193.1773 | M27: ='RECETAS JARABES'!$G$567 -> 3303.4717 | N27: ='RECETAS JARABES'!$H$567 -> 0.57 | O27: ='RECETAS JARABES'!$G$568 -> 9099.0361 | P27: 6000 | Q27: =(LISTPROD3[[#This Row],[PRECIO DE VENTA 1]]-LISTPROD3[[#This Row],[COSTO TOTAL UNIDAD]])/LISTPROD3[[#This Row],[COSTO TOTAL UNIDAD]] -> 0.15536206 | R27: =LISTPROD3[[#This Row],[% GANANCIA]]*LISTPROD3[[#This Row],[COSTO TOTAL UNIDAD]] -> 806.82273 | S27: =+LISTPROD3[[#This Row],[PRECIO DE VENTA 1]]-LISTPROD3[[#This Row],[PRECIO VENTA POR RECETA]] -> -3099.0361 | T27: 5000 | U27: =(LISTPROD3[[#This Row],[PRECIO DE VENTA2]]-LISTPROD3[[#This Row],[COSTO TOTAL UNIDAD]])/LISTPROD3[[#This Row],[COSTO TOTAL UNIDAD]] -> -0.037198281 | V27: =+LISTPROD3[[#This Row],[% GANANCIA2]]*LISTPROD3[[#This Row],[COSTO TOTAL UNIDAD]] -> -193.17727 | W27: =LISTPROD3[[#This Row],[PRECIO DE VENTA2]]-LISTPROD3[[#This Row],[PRECIO VENTA POR RECETA]] -> -4099.0361 | X27: 5000 | Y27: =(LISTPROD3[[#This Row],[PRECIO DE VENTA 3]]-LISTPROD3[[#This Row],[COSTO TOTAL UNIDAD]])/LISTPROD3[[#This Row],[COSTO TOTAL UNIDAD]] -> -0.037198281 | Z27: =LISTPROD3[[#This Row],[% GANANCIA3]]*LISTPROD3[[#This Row],[COSTO TOTAL UNIDAD]] -> -193.17727 | AC27: 6000 | AD27: 5000 | AE27: 5000 | AF27: 5000 | AH27: PREGUNTAR A LUIS POR PRECIOS Y FORMULA
A28: CI01 | B28: COPA DE INDIO | C28: 500 ML-Jarabe | D28: HOMEOPATICOS | E28: JARABES | F28: 500 ML | G28: PHARMA | I28: LUIS-FARMACIA NATIVA | J28: ='RECETAS JARABES'!G595 -> 2072.6344 | K28: ='Gtos Varios'!$B$22 -> 3070.5429 | L28: =+LISTPROD3[[#This Row],[PRECIO DE PRODUCCIÓN POR UND]]+LISTPROD3[[#This Row],[TOTAL GASTOS VARIOS]] -> 5143.1773 | M28: ='RECETAS JARABES'!G600 -> 3389.883 | N28: ='RECETAS JARABES'!H600 -> 0.59 | O28: ='RECETAS JARABES'!G601 -> 9135.4474 | P28: 6000 | Q28: =(LISTPROD3[[#This Row],[PRECIO DE VENTA 1]]-LISTPROD3[[#This Row],[COSTO TOTAL UNIDAD]])/LISTPROD3[[#This Row],[COSTO TOTAL UNIDAD]] -> 0.16659405 | R28: =LISTPROD3[[#This Row],[% GANANCIA]]*LISTPROD3[[#This Row],[COSTO TOTAL UNIDAD]] -> 856.82273 | S28: =+LISTPROD3[[#This Row],[PRECIO DE VENTA 1]]-LISTPROD3[[#This Row],[PRECIO VENTA POR RECETA]] -> -3135.4474 | T28: 5000 | U28: =(LISTPROD3[[#This Row],[PRECIO DE VENTA2]]-LISTPROD3[[#This Row],[COSTO TOTAL UNIDAD]])/LISTPROD3[[#This Row],[COSTO TOTAL UNIDAD]] -> -0.027838292 | V28: =+LISTPROD3[[#This Row],[% GANANCIA2]]*LISTPROD3[[#This Row],[COSTO TOTAL UNIDAD]] -> -143.17727 | W28: =LISTPROD3[[#This Row],[PRECIO DE VENTA2]]-LISTPROD3[[#This Row],[PRECIO VENTA POR RECETA]] -> -4135.4474 | X28: 5000 | Y28: =(LISTPROD3[[#This Row],[PRECIO DE VENTA 3]]-LISTPROD3[[#This Row],[COSTO TOTAL UNIDAD]])/LISTPROD3[[#This Row],[COSTO TOTAL UNIDAD]] -> -0.027838292 | Z28: =LISTPROD3[[#This Row],[% GANANCIA3]]*LISTPROD3[[#This Row],[COSTO TOTAL UNIDAD]] -> -143.17727 | AC28: 6000 | AD28: 5000 | AE28: 5000 | AF28: 5000 | AH28: OK
A29: DZ01 | B29: DIABETIZAN | C29: 500 ML-Jarabe | D29: HOMEOPATICOS | E29: JARABES | F29: 500 ML | G29: PHARMA | I29: LUIS-FARMACIA NATIVA | J29: FALTA PRECIO PROD | K29: ='Gtos Varios'!$B$22 -> 3070.5429 | L29: =+LISTPROD3[[#This Row],[PRECIO DE PRODUCCIÓN POR UND]]+LISTPROD3[[#This Row],[TOTAL GASTOS VARIOS]] -> #VALUE! | M29: ='RECETAS JARABES'!G634 -> 3357.1036 | N29: ='RECETAS JARABES'!H634 -> 0.58 | O29: ='RECETAS JARABES'!G635 -> 9145.2133 | P29: 6000 | Q29: =(LISTPROD3[[#This Row],[PRECIO DE VENTA 1]]-LISTPROD3[[#This Row],[COSTO TOTAL UNIDAD]])/LISTPROD3[[#This Row],[COSTO TOTAL UNIDAD]] -> #VALUE! | R29: =LISTPROD3[[#This Row],[% GANANCIA]]*LISTPROD3[[#This Row],[COSTO TOTAL UNIDAD]] -> #VALUE! | S29: =+LISTPROD3[[#This Row],[PRECIO DE VENTA 1]]-LISTPROD3[[#This Row],[PRECIO VENTA POR RECETA]] -> -3145.2133 | T29: 5000 | U29: =(LISTPROD3[[#This Row],[PRECIO DE VENTA2]]-LISTPROD3[[#This Row],[COSTO TOTAL UNIDAD]])/LISTPROD3[[#This Row],[COSTO TOTAL UNIDAD]] -> #VALUE! | V29: =+LISTPROD3[[#This Row],[% GANANCIA2]]*LISTPROD3[[#This Row],[COSTO TOTAL UNIDAD]] -> #VALUE! | W29: =LISTPROD3[[#This Row],[PRECIO DE VENTA2]]-LISTPROD3[[#This Row],[PRECIO VENTA POR RECETA]] -> -4145.2133 | X29: 5000 | Y29: =(LISTPROD3[[#This Row],[PRECIO DE VENTA 3]]-LISTPROD3[[#This Row],[COSTO TOTAL UNIDAD]])/LISTPROD3[[#This Row],[COSTO TOTAL UNIDAD]] -> #VALUE! | Z29: =LISTPROD3[[#This Row],[% GANANCIA3]]*LISTPROD3[[#This Row],[COSTO TOTAL UNIDAD]] -> #VALUE! | AC29: 6000 | AD29: 5000 | AE29: 5000 | AF29: 5000 | AH29: OK
A30: du01 | B30: DOLORAN ULTRA (lleva Spray) | C30: PASTILLAS 60 | D30: HOMEOPATICOS | E30: PASTILLAS | F30: PASTILLAS DE 60 UND | I30: LUIS-FARMACIA NATIVA | J30: ='RECETAS PASTILLAS'!R16 -> 4900 | K30: ='Gtos Varios'!$B$22 -> 3070.5429 | L30: =+LISTPROD3[[#This Row],[TOTAL GASTOS VARIOS]]+LISTPROD3[[#This Row],[PRECIO DE PRODUCCIÓN POR UND]] -> 7970.5429 | M30: ='RECETAS PASTILLAS'!R48 -> 3257.7134 | N30: ='RECETAS PASTILLAS'!S48 -> 0.38 | O30: ='RECETAS PASTILLAS'!R49 -> 11830.643 | P30: 10500 | Q30: =(LISTPROD3[[#This Row],[PRECIO DE VENTA 1]]-LISTPROD3[[#This Row],[COSTO TOTAL UNIDAD]])/LISTPROD3[[#This Row],[COSTO TOTAL UNIDAD]] -> 0.31735067 | R30: =LISTPROD3[[#This Row],[% GANANCIA]]*LISTPROD3[[#This Row],[COSTO TOTAL UNIDAD]] -> 2529.4571 | AB30: Se toma solo el costo de produccion no margen de utilidad | AC30: 10500 | AD30: 0 | AE30: 0 | AF30: 0 | AH30: FALTA
A31: E01 | B31: ELIXIR (Gotas) | C31: 25 ML | D31: HOMEOPATICOS | E31: GOTAS | F31: 25 ML | I31: LUIS-FARMACIA NATIVA | J31: ='RECETAS GOTAS'!K92 -> 2006 | K31: ='Gtos Varios'!$B$22 -> 3070.5429 | L31: =+LISTPROD3[[#This Row],[TOTAL GASTOS VARIOS]]+LISTPROD3[[#This Row],[PRECIO DE PRODUCCIÓN POR UND]] -> 5076.5429 | M31: ='RECETAS GOTAS'!K97 -> 3350.5687 | N31: ='RECETAS GOTAS'!L97 -> 0.59 | O31: ='RECETAS GOTAS'!K98 -> 9029.4987 | P31: 600 | Q31: =(LISTPROD3[[#This Row],[PRECIO DE VENTA 1]]-LISTPROD3[[#This Row],[COSTO TOTAL UNIDAD]])/LISTPROD3[[#This Row],[COSTO TOTAL UNIDAD]] -> -0.88180933 | R31: =LISTPROD3[[#This Row],[% GANANCIA]]*LISTPROD3[[#This Row],[COSTO TOTAL UNIDAD]] -> -4476.5429 | T31: 0 | U31: =(LISTPROD3[[#This Row],[PRECIO DE VENTA2]]-LISTPROD3[[#This Row],[COSTO TOTAL UNIDAD]])/LISTPROD3[[#This Row],[COSTO TOTAL UNIDAD]] -> -1 | V31: =LISTPROD3[[#This Row],[PRECIO DE VENTA2]]*LISTPROD3[[#This Row],[% GANANCIA2]] -> 0 | W31: =LISTPROD3[[#This Row],[PRECIO DE VENTA2]]-LISTPROD3[[#This Row],[PRECIO VENTA POR RECETA]] -> -9029.4987 | X31: 0 | AC31: 600 | AD31: 0 | AE31: 0 | AF31: 0 | AH31: FALTA
A32: EDM01 | B32: ENFERMEDADES DE LA MUJER | C32: 500 ML-Jarabe | D32: HOMEOPATICOS | E32: JARABES | F32: 500 ML | G32: PHARMA | I32: LUIS-FARMACIA NATIVA | J32: FALTA PRECIO PROD | K32: ='Gtos Varios'!$B$22 -> 3070.5429 | L32: =+LISTPROD3[[#This Row],[PRECIO DE PRODUCCIÓN POR UND]]+LISTPROD3[[#This Row],[TOTAL GASTOS VARIOS]] -> #VALUE! | M32: ='RECETAS JARABES'!G669 -> 3364.3853 | N32: ='RECETAS JARABES'!H669 -> 0.58 | O32: ='RECETAS JARABES'!G670 -> 9165.0497 | P32: 6000 | Q32: =(LISTPROD3[[#This Row],[PRECIO DE VENTA 1]]-LISTPROD3[[#This Row],[COSTO TOTAL UNIDAD]])/LISTPROD3[[#This Row],[COSTO TOTAL UNIDAD]] -> #VALUE! | R32: =LISTPROD3[[#This Row],[% GANANCIA]]*LISTPROD3[[#This Row],[COSTO TOTAL UNIDAD]] -> #VALUE! | S32: =+LISTPROD3[[#This Row],[PRECIO DE VENTA 1]]-LISTPROD3[[#This Row],[PRECIO VENTA POR RECETA]] -> -3165.0497 | T32: 5000 | U32: =(LISTPROD3[[#This Row],[PRECIO DE VENTA2]]-LISTPROD3[[#This Row],[COSTO TOTAL UNIDAD]])/LISTPROD3[[#This Row],[COSTO TOTAL UNIDAD]] -> #VALUE! | V32: =+LISTPROD3[[#This Row],[% GANANCIA2]]*LISTPROD3[[#This Row],[COSTO TOTAL UNIDAD]] -> #VALUE! | W32: =LISTPROD3[[#This Row],[PRECIO DE VENTA2]]-LISTPROD3[[#This Row],[PRECIO VENTA POR RECETA]] -> -4165.0497 | X32: 5000 | Y32: =(LISTPROD3[[#This Row],[PRECIO DE VENTA 3]]-LISTPROD3[[#This Row],[COSTO TOTAL UNIDAD]])/LISTPROD3[[#This Row],[COSTO TOTAL UNIDAD]] -> #VALUE! | Z32: =LISTPROD3[[#This Row],[% GANANCIA3]]*LISTPROD3[[#This Row],[COSTO TOTAL UNIDAD]] -> #VALUE! | AC32: 6000 | AD32: 5000 | AE32: 5000 | AF32: 5000 | AH32: OK
A33: EMX01 | B33: ERECMAX | C33: 500 ML-Jarabe | D33: HOMEOPATICOS | E33: JARABES | F33: 500 ML | G33: PHARMA | I33: LUIS-FARMACIA NATIVA | J33: ='RECETAS JARABES'!G699 -> 3065.3275 | K33: ='Gtos Varios'!$B$22 -> 3070.5429 | L33: =+LISTPROD3[[#This Row],[PRECIO DE PRODUCCIÓN POR UND]]+LISTPROD3[[#This Row],[TOTAL GASTOS VARIOS]] -> 6135.8704 | M33: ='RECETAS JARABES'!G704 -> 3006.5765 | N33: ='RECETAS JARABES'!H704 -> 0.49 | O33: ='RECETAS JARABES'!G705 -> 9142.4469 | P33: 6000 | Q33: =(LISTPROD3[[#This Row],[PRECIO DE VENTA 1]]-LISTPROD3[[#This Row],[COSTO TOTAL UNIDAD]])/LISTPROD3[[#This Row],[COSTO TOTAL UNIDAD]] -> -0.02214362 | R33: =LISTPROD3[[#This Row],[% GANANCIA]]*LISTPROD3[[#This Row],[COSTO TOTAL UNIDAD]] -> -135.87038 | S33: =+LISTPROD3[[#This Row],[PRECIO DE VENTA 1]]-LISTPROD3[[#This Row],[PRECIO VENTA POR RECETA]] -> -3142.4469 | T33: 5000 | U33: =(LISTPROD3[[#This Row],[PRECIO DE VENTA2]]-LISTPROD3[[#This Row],[COSTO TOTAL UNIDAD]])/LISTPROD3[[#This Row],[COSTO TOTAL UNIDAD]] -> -0.18511968 | V33: =+LISTPROD3[[#This Row],[% GANANCIA2]]*LISTPROD3[[#This Row],[COSTO TOTAL UNIDAD]] -> -1135.8704 | W33: =LISTPROD3[[#This Row],[PRECIO DE VENTA2]]-LISTPROD3[[#This Row],[PRECIO VENTA POR RECETA]] -> -4142.4469 | X33: 5000 | Y33: =(LISTPROD3[[#This Row],[PRECIO DE VENTA 3]]-LISTPROD3[[#This Row],[COSTO TOTAL UNIDAD]])/LISTPROD3[[#This Row],[COSTO TOTAL UNIDAD]] -> -0.18511968 | Z33: =LISTPROD3[[#This Row],[% GANANCIA3]]*LISTPROD3[[#This Row],[COSTO TOTAL UNIDAD]] -> -1135.8704 | AC33: 6000 | AD33: 5000 | AE33: 5000 | AF33: 5000 | AH33: OK
A34: FO01 | B34: FENOGRECO (Capsulas) | C34: ENVASE TIENE 60 CAPSULAS | D34: HOMEOPATICOS | E34: CAPSULAS | F34: CAPSULAS 60 UND | I34: ANGIE-LHC | J34: ='RECETAS CAPS'!AI19 -> 2926.25 | K34: ='Gtos Varios'!$B$22 -> 3070.5429 | L34: =+LISTPROD3[[#This Row],[TOTAL GASTOS VARIOS]]+LISTPROD3[[#This Row],[PRECIO DE PRODUCCIÓN POR UND]] -> 5996.7929 | M34: ='RECETAS CAPS'!AI25 -> 3365.5818 | N34: ='RECETAS CAPS'!AJ25 -> 0.51 | O34: ='RECETAS CAPS'!AI26 -> 9964.7618 | P34: 8700 | Q34: =(LISTPROD3[[#This Row],[PRECIO DE VENTA 1]]-LISTPROD3[[#This Row],[COSTO TOTAL UNIDAD]])/LISTPROD3[[#This Row],[COSTO TOTAL UNIDAD]] -> 0.45077547 | R34: =LISTPROD3[[#This Row],[% GANANCIA]]*LISTPROD3[[#This Row],[COSTO TOTAL UNIDAD]] -> 2703.2071 | AC34: 8700 | AD34: 0 | AE34: 0 | AF34: 0 | AH34: OK
A35: FT01 | B35: FERROVIT LT | C35: 1000 ML-Jarabe | D35: HOMEOPATICOS | E35: JARABES | F35: LITRO 1000 ML | G35: CUBANO | I35: ANGIE-LHC | J35: ='RECETAS JARABES'!G730 -> 2202.7729 | K35: ='Gtos Varios'!$B$22 -> 3070.5429 | L35: =+LISTPROD3[[#This Row],[PRECIO DE PRODUCCIÓN POR UND]]+LISTPROD3[[#This Row],[TOTAL GASTOS VARIOS]] -> 5273.3158 | M35: ='RECETAS JARABES'!G735 -> 3005.79 | N35: ='RECETAS JARABES'!H735 -> 0.57 | O35: ='RECETAS JARABES'!G736 -> 8279.1058 | P35: 7500 | Q35: =(LISTPROD3[[#This Row],[PRECIO DE VENTA 1]]-LISTPROD3[[#This Row],[COSTO TOTAL UNIDAD]])/LISTPROD3[[#This Row],[COSTO TOTAL UNIDAD]] -> 0.42225505 | R35: =LISTPROD3[[#This Row],[% GANANCIA]]*LISTPROD3[[#This Row],[COSTO TOTAL UNIDAD]] -> 2226.6842 | S35: =+LISTPROD3[[#This Row],[PRECIO DE VENTA 1]]-LISTPROD3[[#This Row],[PRECIO VENTA POR RECETA]] -> -779.1058 | T35: 5000 | U35: =(LISTPROD3[[#This Row],[PRECIO DE VENTA2]]-LISTPROD3[[#This Row],[COSTO TOTAL UNIDAD]])/LISTPROD3[[#This Row],[COSTO TOTAL UNIDAD]] -> -0.05182997 | V35: =+LISTPROD3[[#This Row],[% GANANCIA2]]*LISTPROD3[[#This Row],[COSTO TOTAL UNIDAD]] -> -273.3158 | W35: =LISTPROD3[[#This Row],[PRECIO DE VENTA2]]-LISTPROD3[[#This Row],[PRECIO VENTA POR RECETA]] -> -3279.1058 | X35: 2000 | Y35: =(LISTPROD3[[#This Row],[PRECIO DE VENTA 3]]-LISTPROD3[[#This Row],[COSTO TOTAL UNIDAD]])/LISTPROD3[[#This Row],[COSTO TOTAL UNIDAD]] -> -0.62073199 | Z35: =LISTPROD3[[#This Row],[% GANANCIA3]]*LISTPROD3[[#This Row],[COSTO TOTAL UNIDAD]] -> -3273.3158 | AC35: 7500 | AD35: 5000 | AE35: 2000 | AF35: 2000 | AH35: OK
A36: FM01 | B36: FERRUM LITRO | C36: 1000 ML-Jarabe | D36: HOMEOPATICOS | E36: JARABES | F36: LITRO 1000 ML | G36: CUBANO | I36: ANGIE-LHC | J36: ='RECETAS JARABES'!G761 -> 2202.7729 | K36: ='Gtos Varios'!$B$22 -> 3070.5429 | L36: =+LISTPROD3[[#This Row],[PRECIO DE PRODUCCIÓN POR UND]]+LISTPROD3[[#This Row],[TOTAL GASTOS VARIOS]] -> 5273.3158 | M36: ='RECETAS JARABES'!G766 -> 3005.79 | N36: ='RECETAS JARABES'!H766 -> 0.57 | O36: ='RECETAS JARABES'!G767 -> 8279.1058 | P36: 7500 | Q36: =(LISTPROD3[[#This Row],[PRECIO DE VENTA 1]]-LISTPROD3[[#This Row],[COSTO TOTAL UNIDAD]])/LISTPROD3[[#This Row],[COSTO TOTAL UNIDAD]] -> 0.42225505 | R36: =LISTPROD3[[#This Row],[% GANANCIA]]*LISTPROD3[[#This Row],[COSTO TOTAL UNIDAD]] -> 2226.6842 | S36: =+LISTPROD3[[#This Row],[PRECIO DE VENTA 1]]-LISTPROD3[[#This Row],[PRECIO VENTA POR RECETA]] -> -779.1058 | AC36: 7500 | AD36: 0 | AE36: 0 | AF36: 0 | AH36: PREGUNTAR A LUIS POR PRECIOS Y FORMULA
A37: FL01 | B37: FLEXDOL | C37: PASTILLAS 40 | D37: HOMEOPATICOS | E37: PASTILLAS | F37: PASTILLAS DE 40 UND | I37: LUIS-FARMACIA NATIVA | J37: ='RECETAS PASTILLAS'!G45 -> 4670 | K37: ='Gtos Varios'!$B$22 -> 3070.5429 | L37: =+LISTPROD3[[#This Row],[TOTAL GASTOS VARIOS]]+LISTPROD3[[#This Row],[PRECIO DE PRODUCCIÓN POR UND]] -> 7740.5429 | M37: ='RECETAS PASTILLAS'!G50 -> 3253.7427 | N37: ='RECETAS PASTILLAS'!H50 -> 0.39 | O37: ='RECETAS PASTILLAS'!G51 -> 11596.673 | P37: 7000 | Q37: =(LISTPROD3[[#This Row],[PRECIO DE VENTA 1]]-LISTPROD3[[#This Row],[COSTO TOTAL UNIDAD]])/LISTPROD3[[#This Row],[COSTO TOTAL UNIDAD]] -> -0.095670662 | R37: =LISTPROD3[[#This Row],[% GANANCIA]]*LISTPROD3[[#This Row],[COSTO TOTAL UNIDAD]] -> -740.54286 | T37: 7000 | U37: =(LISTPROD3[[#This Row],[PRECIO DE VENTA2]]-LISTPROD3[[#This Row],[COSTO TOTAL UNIDAD]])/LISTPROD3[[#This Row],[COSTO TOTAL UNIDAD]] -> -0.095670662 | V37: =LISTPROD3[[#This Row],[PRECIO DE VENTA2]]*LISTPROD3[[#This Row],[% GANANCIA2]] -> -669.69463 | X37: 7000 | Y37: =(LISTPROD3[[#This Row],[PRECIO DE VENTA 3]]-LISTPROD3[[#This Row],[COSTO TOTAL UNIDAD]])/LISTPROD3[[#This Row],[COSTO TOTAL UNIDAD]] -> -0.095670662 | Z37: =+LISTPROD3[[#This Row],[PRECIO DE VENTA 3]]*LISTPROD3[[#This Row],[% GANANCIA3]] -> -669.69463 | AB37: Se toma solo el costo de produccion no margen de utilidad | AC37: 7000 | AD37: 7000 | AE37: 7000 | AF37: 7000 | AH37: OK
A38: FC01 | B38: FLOR DE CENTELLA | C38: 500 ML-Jarabe | D38: HOMEOPATICOS | E38: JARABES | F38: 500 ML | G38: SALUD Y BELLEZA NATUTAL | I38: LUIS-FARMACIA NATIVA | J38: ='RECETAS JARABES'!G794 -> 2122.6344 | K38: ='Gtos Varios'!$B$22 -> 3070.5429 | L38: =+LISTPROD3[[#This Row],[PRECIO DE PRODUCCIÓN POR UND]]+LISTPROD3[[#This Row],[TOTAL GASTOS VARIOS]] -> 5193.1773 | M38: ='RECETAS JARABES'!G799 -> 2960.111 | N38: ='RECETAS JARABES'!H799 -> 0.57 | O38: ='RECETAS JARABES'!G800 -> 8153.2883 | P38: 7000 | Q38: =(LISTPROD3[[#This Row],[PRECIO DE VENTA 1]]-LISTPROD3[[#This Row],[COSTO TOTAL UNIDAD]])/LISTPROD3[[#This Row],[COSTO TOTAL UNIDAD]] -> 0.34792241 | R38: =LISTPROD3[[#This Row],[% GANANCIA]]*LISTPROD3[[#This Row],[COSTO TOTAL UNIDAD]] -> 1806.8227 | S38: =+LISTPROD3[[#This Row],[PRECIO DE VENTA 1]]-LISTPROD3[[#This Row],[PRECIO VENTA POR RECETA]] -> -1153.2883 | AC38: 7000 | AD38: 0 | AE38: 0 | AF38: 0 | AH38: OK
A39: FCN01 | B39: FLOR DE CENTELLA NUEVA | C39: 500 ML-Jarabe | D39: HOMEOPATICOS | E39: JARABES | F39: 500 ML | G39: SALUD Y BELLEZA NATUTAL | I39: LUIS-FARMACIA NATIVA | J39: ='RECETAS JARABES'!G826 -> 2016.5143 | K39: ='Gtos Varios'!$B$22 -> 3070.5429 | L39: =+LISTPROD3[[#This Row],[PRECIO DE PRODUCCIÓN POR UND]]+LISTPROD3[[#This Row],[TOTAL GASTOS VARIOS]] -> 5087.0572 | M39: ='RECETAS JARABES'!G831 -> 2899.6226 | N39: ='RECETAS JARABES'!H831 -> 0.57 | O39: ='RECETAS JARABES'!G832 -> 7986.6798 | P39: 7000 | Q39: =(LISTPROD3[[#This Row],[PRECIO DE VENTA 1]]-LISTPROD3[[#This Row],[COSTO TOTAL UNIDAD]])/LISTPROD3[[#This Row],[COSTO TOTAL UNIDAD]] -> 0.37604115 | R39: =LISTPROD3[[#This Row],[% GANANCIA]]*LISTPROD3[[#This Row],[COSTO TOTAL UNIDAD]] -> 1912.9428 | S39: =+LISTPROD3[[#This Row],[PRECIO DE VENTA 1]]-LISTPROD3[[#This Row],[PRECIO VENTA POR RECETA]] -> -986.67975 | AC39: 7000 | AD39: 0 | AE39: 0 | AF39: 0 | AH39: OK
A40: GT01 | B40: GASTRIUL | C40: 500 ML-Jarabe | D40: HOMEOPATICOS | E40: JARABES | F40: 500 ML | G40: PHARMA | I40: LUIS-FARMACIA NATIVA | J40: FALTA PRECIO PROD | K40: ='Gtos Varios'!$B$22 -> 3070.5429 | L40: =+LISTPROD3[[#This Row],[PRECIO DE PRODUCCIÓN POR UND]]+LISTPROD3[[#This Row],[TOTAL GASTOS VARIOS]] -> #VALUE! | M40: ='RECETAS JARABES'!$G$866 -> 3032.8279 | N40: ='RECETAS JARABES'!$H$866 -> 0.58 | O40: ='RECETAS JARABES'!$G$867 -> 8261.8415 | P40: 6000 | Q40: =(LISTPROD3[[#This Row],[PRECIO DE VENTA 1]]-LISTPROD3[[#This Row],[COSTO TOTAL UNIDAD]])/LISTPROD3[[#This Row],[COSTO TOTAL UNIDAD]] -> #VALUE! | R40: =LISTPROD3[[#This Row],[% GANANCIA]]*LISTPROD3[[#This Row],[COSTO TOTAL UNIDAD]] -> #VALUE! | S40: =+LISTPROD3[[#This Row],[PRECIO DE VENTA 1]]-LISTPROD3[[#This Row],[PRECIO VENTA POR RECETA]] -> -2261.8415 | T40: 6000 | U40: =(LISTPROD3[[#This Row],[PRECIO DE VENTA2]]-LISTPROD3[[#This Row],[COSTO TOTAL UNIDAD]])/LISTPROD3[[#This Row],[COSTO TOTAL UNIDAD]] -> #VALUE! | V40: =+LISTPROD3[[#This Row],[% GANANCIA2]]*LISTPROD3[[#This Row],[COSTO TOTAL UNIDAD]] -> #VALUE! | W40: =LISTPROD3[[#This Row],[PRECIO DE VENTA2]]-LISTPROD3[[#This Row],[PRECIO VENTA POR RECETA]] -> -2261.8415 | X40: 6000 | Y40: =(LISTPROD3[[#This Row],[PRECIO DE VENTA 3]]-LISTPROD3[[#This Row],[COSTO TOTAL UNIDAD]])/LISTPROD3[[#This Row],[COSTO TOTAL UNIDAD]] -> #VALUE! | Z40: =LISTPROD3[[#This Row],[% GANANCIA3]]*LISTPROD3[[#This Row],[COSTO TOTAL UNIDAD]] -> #VALUE! | AC40: 6000 | AD40: 6000 | AE40: 6000 | AF40: 6000 | AG40: Se ajusto precio el 17/03/2025 con Elaine | AH40: OK
A41: GL01 | B41: GASTROBELL | C41: 500 ML-Jarabe | D41: HOMEOPATICOS | E41: JARABES | F41: 500 ML | G41: CUBANO | I41: ANGIE-LHC | J41: FALTA PRECIO PROD | K41: ='Gtos Varios'!$B$22 -> 3070.5429 | L41: =+LISTPROD3[[#This Row],[PRECIO DE PRODUCCIÓN POR UND]]+LISTPROD3[[#This Row],[TOTAL GASTOS VARIOS]] -> #VALUE! | M41: ='RECETAS JARABES'!G901 -> 2975.6431 | N41: ='RECETAS JARABES'!H901 -> 0.57 | O41: ='RECETAS JARABES'!G902 -> 8196.0697 | P41: 6000 | Q41: =(LISTPROD3[[#This Row],[PRECIO DE VENTA 1]]-LISTPROD3[[#This Row],[COSTO TOTAL UNIDAD]])/LISTPROD3[[#This Row],[COSTO TOTAL UNIDAD]] -> #VALUE! | R41: =LISTPROD3[[#This Row],[% GANANCIA]]*LISTPROD3[[#This Row],[COSTO TOTAL UNIDAD]] -> #VALUE! | S41: =+LISTPROD3[[#This Row],[PRECIO DE VENTA 1]]-LISTPROD3[[#This Row],[PRECIO VENTA POR RECETA]] -> -2196.0697 | T41: 5000 | U41: =(LISTPROD3[[#This Row],[PRECIO DE VENTA2]]-LISTPROD3[[#This Row],[COSTO TOTAL UNIDAD]])/LISTPROD3[[#This Row],[COSTO TOTAL UNIDAD]] -> #VALUE! | V41: =+LISTPROD3[[#This Row],[% GANANCIA2]]*LISTPROD3[[#This Row],[COSTO TOTAL UNIDAD]] -> #VALUE! | W41: =LISTPROD3[[#This Row],[PRECIO DE VENTA2]]-LISTPROD3[[#This Row],[PRECIO VENTA POR RECETA]] -> -3196.0697 | X41: 5000 | Y41: =(LISTPROD3[[#This Row],[PRECIO DE VENTA 3]]-LISTPROD3[[#This Row],[COSTO TOTAL UNIDAD]])/LISTPROD3[[#This Row],[COSTO TOTAL UNIDAD]] -> #VALUE! | Z41: =LISTPROD3[[#This Row],[% GANANCIA3]]*LISTPROD3[[#This Row],[COSTO TOTAL UNIDAD]] -> #VALUE! | AC41: 6000 | AD41: 5000 | AE41: 5000 | AF41: 5000 | AH41: OK
A42: GP01 | B42: GOLDEN PLUS | C42: 500 ML-Jarabe | D42: HOMEOPATICOS | E42: JARABES | F42: 500 ML | I42: LUIS-FARMACIA NATIVA | J42: ='RECETAS JARABES'!G930 -> 3086.5143 | K42: ='Gtos Varios'!$B$22 -> 3070.5429 | L42: =+LISTPROD3[[#This Row],[PRECIO DE PRODUCCIÓN POR UND]]+LISTPROD3[[#This Row],[TOTAL GASTOS VARIOS]] -> 6157.0572 | M42: ='RECETAS JARABES'!G935 -> 2893.8169 | N42: ='RECETAS JARABES'!H935 -> 0.47 | O42: ='RECETAS JARABES'!G936 -> 9050.874 | P42: 7000 | Q42: =(LISTPROD3[[#This Row],[PRECIO DE VENTA 1]]-LISTPROD3[[#This Row],[COSTO TOTAL UNIDAD]])/LISTPROD3[[#This Row],[COSTO TOTAL UNIDAD]] -> 0.13690677 | R42: =LISTPROD3[[#This Row],[% GANANCIA]]*LISTPROD3[[#This Row],[COSTO TOTAL UNIDAD]] -> 842.94283 | S42: =+LISTPROD3[[#This Row],[PRECIO DE VENTA 1]]-LISTPROD3[[#This Row],[PRECIO VENTA POR RECETA]] -> -2050.874 | T42: 10000 | U42: =(LISTPROD3[[#This Row],[PRECIO DE VENTA2]]-LISTPROD3[[#This Row],[COSTO TOTAL UNIDAD]])/LISTPROD3[[#This Row],[COSTO TOTAL UNIDAD]] -> 0.62415253 | V42: =+LISTPROD3[[#This Row],[% GANANCIA2]]*LISTPROD3[[#This Row],[COSTO TOTAL UNIDAD]] -> 3842.9428 | W42: =LISTPROD3[[#This Row],[PRECIO DE VENTA2]]-LISTPROD3[[#This Row],[PRECIO VENTA POR RECETA]] -> 949.12597 | X42: 10000 | Y42: =(LISTPROD3[[#This Row],[PRECIO DE VENTA 3]]-LISTPROD3[[#This Row],[COSTO TOTAL UNIDAD]])/LISTPROD3[[#This Row],[COSTO TOTAL UNIDAD]] -> 0.62415253 | Z42: =LISTPROD3[[#This Row],[% GANANCIA3]]*LISTPROD3[[#This Row],[COSTO TOTAL UNIDAD]] -> 3842.9428 | AC42: 7000 | AD42: 10000 | AE42: 10000 | AF42: 10000 | AG42: Se ajusto precio el 11/03/2025 con Elaine | AH42: FALTA
A43: GMI | B43: GOTAS MILAGROSAS | C43: 25 ML | D43: HOMEOPATICOS | E43: GOTAS | F43: 25 ML | I43: LUIS-FARMACIA NATIVA | J43: FALTA RECETA | K43: ='Gtos Varios'!$B$22 -> 3070.5429 | L43: =+LISTPROD3[[#This Row],[TOTAL GASTOS VARIOS]]+LISTPROD3[[#This Row],[PRECIO DE PRODUCCIÓN POR UND]] -> #VALUE! | P43: 2000 | Q43: =(LISTPROD3[[#This Row],[PRECIO DE VENTA 1]]-LISTPROD3[[#This Row],[COSTO TOTAL UNIDAD]])/LISTPROD3[[#This Row],[COSTO TOTAL UNIDAD]] -> #VALUE! | R43: =LISTPROD3[[#This Row],[% GANANCIA]]*LISTPROD3[[#This Row],[COSTO TOTAL UNIDAD]] -> #VALUE! | T43: 2000 | U43: =(LISTPROD3[[#This Row],[PRECIO DE VENTA2]]-LISTPROD3[[#This Row],[COSTO TOTAL UNIDAD]])/LISTPROD3[[#This Row],[COSTO TOTAL UNIDAD]] -> #VALUE! | V43: =LISTPROD3[[#This Row],[PRECIO DE VENTA2]]*LISTPROD3[[#This Row],[% GANANCIA2]] -> #VALUE! | W43: =LISTPROD3[[#This Row],[PRECIO DE VENTA2]]-LISTPROD3[[#This Row],[PRECIO VENTA POR RECETA]] -> 2000 | X43: 2000 | AC43: 2000 | AD43: 2000 | AE43: 2000 | AF43: 2000 | AH43: FALTA
A44: GA01 | B44: GRAN TAMAKURA | C44: 500 ML-Jarabe | D44: HOMEOPATICOS | E44: JARABES | F44: 500 ML | G44: SALUD Y BELLEZA NATUTAL | I44: LUIS-FARMACIA NATIVA | J44: ='RECETAS JARABES'!G964 -> 2102.6258 | K44: ='Gtos Varios'!$B$22 -> 3070.5429 | L44: =+LISTPROD3[[#This Row],[PRECIO DE PRODUCCIÓN POR UND]]+LISTPROD3[[#This Row],[TOTAL GASTOS VARIOS]] -> 5173.1686 | M44: ='RECETAS JARABES'!G969 -> 3234.3112 | N44: ='RECETAS JARABES'!H969 -> 0.56 | O44: ='RECETAS JARABES'!G970 -> 9009.867 | P44: 7000 | Q44: =(LISTPROD3[[#This Row],[PRECIO DE VENTA 1]]-LISTPROD3[[#This Row],[COSTO TOTAL UNIDAD]])/LISTPROD3[[#This Row],[COSTO TOTAL UNIDAD]] -> 0.35313587 | R44: =LISTPROD3[[#This Row],[% GANANCIA]]*LISTPROD3[[#This Row],[COSTO TOTAL UNIDAD]] -> 1826.8314 | S44: =+LISTPROD3[[#This Row],[PRECIO DE VENTA 1]]-LISTPROD3[[#This Row],[PRECIO VENTA POR RECETA]] -> -2009.867 | AC44: 7000 | AD44: 0 | AE44: 0 | AF44: 0 | AH44: OK
A45: GM01 | B45: GREEN MARVIN (Ungüento) | C45: ungüento | D45: HOMEOPATICOS | I45: LUIS-FARMACIA NATIVA | N45: ='RECETAS UNGUENTOS'!H27 -> 0.63 | O45: ='RECETAS UNGUENTOS'!G28 -> 8775.5459 | P45: 6000 | Q45: =(LISTPROD3[[#This Row],[PRECIO DE VENTA 1]]-LISTPROD3[[#This Row],[COSTO TOTAL UNIDAD]])/LISTPROD3[[#This Row],[COSTO TOTAL UNIDAD]] -> #DIV/0! | R45: =LISTPROD3[[#This Row],[% GANANCIA]]*LISTPROD3[[#This Row],[COSTO TOTAL UNIDAD]] -> #DIV/0! | T45: 0 | U45: =(LISTPROD3[[#This Row],[PRECIO DE VENTA2]]-LISTPROD3[[#This Row],[COSTO TOTAL UNIDAD]])/LISTPROD3[[#This Row],[COSTO TOTAL UNIDAD]] -> #DIV/0! | V45: =LISTPROD3[[#This Row],[PRECIO DE VENTA2]]*LISTPROD3[[#This Row],[% GANANCIA2]] -> #DIV/0! | W45: =LISTPROD3[[#This Row],[PRECIO DE VENTA2]]-LISTPROD3[[#This Row],[PRECIO VENTA POR RECETA]] -> -8775.5459 | X45: 0 | AC45: 6000 | AD45: 0 | AE45: 0 | AF45: 0 | AH45: OK
A46: HX01 | B46: HEPATOX LITRO | C46: 1000 ML-Jarabe | D46: HOMEOPATICOS | E46: JARABES | F46: LITRO 1000 ML | G46: CUBANO | I46: ANGIE-LHC | J46: ='RECETAS JARABES'!G994 -> 2056.7813 | K46: ='Gtos Varios'!$B$22 -> 3070.5429 | L46: =+LISTPROD3[[#This Row],[PRECIO DE PRODUCCIÓN POR UND]]+LISTPROD3[[#This Row],[TOTAL GASTOS VARIOS]] -> 5127.3242 | M46: ='RECETAS JARABES'!G999 -> 3380.5297 | N46: ='RECETAS JARABES'!H999 -> 0.59 | O46: ='RECETAS JARABES'!G1000 -> 9110.241 | P46: 7500 | Q46: =(LISTPROD3[[#This Row],[PRECIO DE VENTA 1]]-LISTPROD3[[#This Row],[COSTO TOTAL UNIDAD]])/LISTPROD3[[#This Row],[COSTO TOTAL UNIDAD]] -> 0.46275127 | R46: =LISTPROD3[[#This Row],[% GANANCIA]]*LISTPROD3[[#This Row],[COSTO TOTAL UNIDAD]] -> 2372.6758 | S46: =+LISTPROD3[[#This Row],[PRECIO DE VENTA 1]]-LISTPROD3[[#This Row],[PRECIO VENTA POR RECETA]] -> -1610.241 | AC46: 7500 | AD46: 0 | AE46: 0 | AF46: 0 | AH46: OK
A47: IM01 | B47: INFAMOL-JARABE 500 ML | C47: 500 ML-Jarabe | D47: HOMEOPATICOS | E47: JARABES | F47: 500 ML | G47: S/M | I47: LUIS-FARMACIA NATIVA | J47: ='RECETAS JARABES'!G1025 -> 2302.3862 | K47: ='Gtos Varios'!$B$22 -> 3070.5429 | L47: =+LISTPROD3[[#This Row],[PRECIO DE PRODUCCIÓN POR UND]]+LISTPROD3[[#This Row],[TOTAL GASTOS VARIOS]] -> 5372.9291 | M47: ='RECETAS JARABES'!G1030 -> 3286.4239 | N47: ='RECETAS JARABES'!H1030 -> 0.55 | O47: ='RECETAS JARABES'!G1031 -> 9261.7402 | P47: 6000 | Q47: =(LISTPROD3[[#This Row],[PRECIO DE VENTA 1]]-LISTPROD3[[#This Row],[COSTO TOTAL UNIDAD]])/LISTPROD3[[#This Row],[COSTO TOTAL UNIDAD]] -> 0.11670932 | R47: =LISTPROD3[[#This Row],[% GANANCIA]]*LISTPROD3[[#This Row],[COSTO TOTAL UNIDAD]] -> 627.07091 | S47: =+LISTPROD3[[#This Row],[PRECIO DE VENTA 1]]-LISTPROD3[[#This Row],[PRECIO VENTA POR RECETA]] -> -3261.7402 | T47: 5000 | U47: =(LISTPROD3[[#This Row],[PRECIO DE VENTA2]]-LISTPROD3[[#This Row],[COSTO TOTAL UNIDAD]])/LISTPROD3[[#This Row],[COSTO TOTAL UNIDAD]] -> -0.069408898 | V47: =+LISTPROD3[[#This Row],[% GANANCIA2]]*LISTPROD3[[#This Row],[COSTO TOTAL UNIDAD]] -> -372.92909 | W47: =LISTPROD3[[#This Row],[PRECIO DE VENTA2]]-LISTPROD3[[#This Row],[PRECIO VENTA POR RECETA]] -> -4261.7402 | X47: 5000 | Y47: =(LISTPROD3[[#This Row],[PRECIO DE VENTA 3]]-LISTPROD3[[#This Row],[COSTO TOTAL UNIDAD]])/LISTPROD3[[#This Row],[COSTO TOTAL UNIDAD]] -> -0.069408898 | Z47: =LISTPROD3[[#This Row],[% GANANCIA3]]*LISTPROD3[[#This Row],[COSTO TOTAL UNIDAD]] -> -372.92909 | AC47: 6000 | AD47: 5000 | AE47: 5000 | AF47: 5000 | AH47: FALTA
A48: IP01 | B48: INFAMOL PASTAS (lleva Spray) | C48: PASTILLAS 60 | D48: HOMEOPATICOS | E48: PASTILLAS | F48: PASTILLAS DE 60 UND | I48: LUIS-FARMACIA NATIVA | J48: ='RECETAS PASTILLAS'!G70 -> 4950 | K48: ='Gtos Varios'!$B$22 -> 3070.5429 | L48: =+LISTPROD3[[#This Row],[TOTAL GASTOS VARIOS]]+LISTPROD3[[#This Row],[PRECIO DE PRODUCCIÓN POR UND]] -> 8020.5429 | M48: ='RECETAS PASTILLAS'!G75 -> 3276.7134 | N48: ='RECETAS PASTILLAS'!H75 -> 0.38 | O48: ='RECETAS PASTILLAS'!G76 -> 11899.643 | P48: 10500 | Q48: =(LISTPROD3[[#This Row],[PRECIO DE VENTA 1]]-LISTPROD3[[#This Row],[COSTO TOTAL UNIDAD]])/LISTPROD3[[#This Row],[COSTO TOTAL UNIDAD]] -> 0.30913832 | R48: =LISTPROD3[[#This Row],[% GANANCIA]]*LISTPROD3[[#This Row],[COSTO TOTAL UNIDAD]] -> 2479.4571 | X48: 0 | AC48: 10500 | AD48: 0 | AE48: 0 | AF48: 0 | AH48: PREGUNTAR A LUIS POR PRECIOS Y FORMULA
A49: KN01 | B49: KOLOSAN | C49: 500 ML-Jarabe | D49: HOMEOPATICOS | E49: JARABES | F49: 500 ML | G49: NATURAL PALAGAR | I49: MARIA-IMPERIO NATURAL | J49: ='RECETAS JARABES'!G1055 -> 944.32325 | K49: ='Gtos Varios'!$B$22 -> 3070.5429 | L49: =+LISTPROD3[[#This Row],[PRECIO DE PRODUCCIÓN POR UND]]+LISTPROD3[[#This Row],[TOTAL GASTOS VARIOS]] -> 4014.8661 | M49: ='RECETAS JARABES'!G1060 -> 3370.5949 | N49: ='RECETAS JARABES'!H1060 -> 0.73 | O49: ='RECETAS JARABES'!G1061 -> 7987.8481 | P49: 7000 | Q49: =(LISTPROD3[[#This Row],[PRECIO DE VENTA 1]]-LISTPROD3[[#This Row],[COSTO TOTAL UNIDAD]])/LISTPROD3[[#This Row],[COSTO TOTAL UNIDAD]] -> 0.74352016 | R49: =LISTPROD3[[#This Row],[% GANANCIA]]*LISTPROD3[[#This Row],[COSTO TOTAL UNIDAD]] -> 2985.1339 | S49: =+LISTPROD3[[#This Row],[PRECIO DE VENTA 1]]-LISTPROD3[[#This Row],[PRECIO VENTA POR RECETA]] -> -987.84813 | AC49: 7000 | AD49: 0 | AE49: 0 | AF49: 0 | AH49: FALTA
A50: LC01 | B50: LIMPIEZA CHINA | C50: 500 ML-Jarabe | D50: HOMEOPATICOS | E50: JARABES | F50: 500 ML | G50: PHARMA | I50: LUIS-FARMACIA NATIVA | J50: ='RECETAS JARABES'!G1088 -> 2103.0103 | K50: ='Gtos Varios'!$B$22 -> 3070.5429 | L50: =+LISTPROD3[[#This Row],[PRECIO DE PRODUCCIÓN POR UND]]+LISTPROD3[[#This Row],[TOTAL GASTOS VARIOS]] -> 5173.5532 | M50: ='RECETAS JARABES'!G1093 -> 3350.0454 | N50: ='RECETAS JARABES'!H1093 -> 0.58 | O50: ='RECETAS JARABES'!G1094 -> 9125.9857 | P50: 6000 | Q50: =(LISTPROD3[[#This Row],[PRECIO DE VENTA 1]]-LISTPROD3[[#This Row],[COSTO TOTAL UNIDAD]])/LISTPROD3[[#This Row],[COSTO TOTAL UNIDAD]] -> 0.15974453 | R50: =LISTPROD3[[#This Row],[% GANANCIA]]*LISTPROD3[[#This Row],[COSTO TOTAL UNIDAD]] -> 826.4468 | S50: =+LISTPROD3[[#This Row],[PRECIO DE VENTA 1]]-LISTPROD3[[#This Row],[PRECIO VENTA POR RECETA]] -> -3125.9857 | T50: 5000 | U50: =(LISTPROD3[[#This Row],[PRECIO DE VENTA2]]-LISTPROD3[[#This Row],[COSTO TOTAL UNIDAD]])/LISTPROD3[[#This Row],[COSTO TOTAL UNIDAD]] -> -0.033546228 | V50: =+LISTPROD3[[#This Row],[% GANANCIA2]]*LISTPROD3[[#This Row],[COSTO TOTAL UNIDAD]] -> -173.5532 | W50: =LISTPROD3[[#This Row],[PRECIO DE VENTA2]]-LISTPROD3[[#This Row],[PRECIO VENTA POR RECETA]] -> -4125.9857 | X50: 5000 | Y50: =(LISTPROD3[[#This Row],[PRECIO DE VENTA 3]]-LISTPROD3[[#This Row],[COSTO TOTAL UNIDAD]])/LISTPROD3[[#This Row],[COSTO TOTAL UNIDAD]] -> -0.033546228 | Z50: =LISTPROD3[[#This Row],[% GANANCIA3]]*LISTPROD3[[#This Row],[COSTO TOTAL UNIDAD]] -> -173.5532 | AC50: 6000 | AD50: 5000 | AE50: 5000 | AF50: 5000 | AH50: OK
A51: MS01 | B51: MATRI SEX | C51: 500 ML-Jarabe | D51: HOMEOPATICOS | E51: JARABES | F51: 500 ML | I51: LUIS-FARMACIA NATIVA | J51: FALTA PRECIO PROD | K51: ='Gtos Varios'!$B$22 -> 3070.5429 | L51: =+LISTPROD3[[#This Row],[PRECIO DE PRODUCCIÓN POR UND]]+LISTPROD3[[#This Row],[TOTAL GASTOS VARIOS]] -> #VALUE! | M51: ='RECETAS JARABES'!G1128 -> 3328.4318 | N51: ='RECETAS JARABES'!H1128 -> 0.65 | O51: ='RECETAS JARABES'!G1129 -> 8449.0962 | P51: 6000 | Q51: =(LISTPROD3[[#This Row],[PRECIO DE VENTA 1]]-LISTPROD3[[#This Row],[COSTO TOTAL UNIDAD]])/LISTPROD3[[#This Row],[COSTO TOTAL UNIDAD]] -> #VALUE! | R51: =LISTPROD3[[#This Row],[% GANANCIA]]*LISTPROD3[[#This Row],[COSTO TOTAL UNIDAD]] -> #VALUE! | S51: =+LISTPROD3[[#This Row],[PRECIO DE VENTA 1]]-LISTPROD3[[#This Row],[PRECIO VENTA POR RECETA]] -> -2449.0962 | T51: 0 | U51: =(LISTPROD3[[#This Row],[PRECIO DE VENTA2]]-LISTPROD3[[#This Row],[COSTO TOTAL UNIDAD]])/LISTPROD3[[#This Row],[COSTO TOTAL UNIDAD]] -> #VALUE! | V51: =+LISTPROD3[[#This Row],[% GANANCIA2]]*LISTPROD3[[#This Row],[COSTO TOTAL UNIDAD]] -> #VALUE! | W51: =LISTPROD3[[#This Row],[PRECIO DE VENTA2]]-LISTPROD3[[#This Row],[PRECIO VENTA POR RECETA]] -> -8449.0962 | X51: 0 | Y51: =(LISTPROD3[[#This Row],[PRECIO DE VENTA 3]]-LISTPROD3[[#This Row],[COSTO TOTAL UNIDAD]])/LISTPROD3[[#This Row],[COSTO TOTAL UNIDAD]] -> #VALUE! | Z51: =LISTPROD3[[#This Row],[% GANANCIA3]]*LISTPROD3[[#This Row],[COSTO TOTAL UNIDAD]] -> #VALUE! | AC51: 6000 | AD51: 0 | AE51: 0 | AF51: 0 | AH51: FALTA
A52: MR01 | B52: MEMOREX | C52: 500 ML-Jarabe | D52: HOMEOPATICOS | E52: JARABES | F52: 500 ML | G52: PHARMA | I52: LUIS-FARMACIA NATIVA | J52: ='RECETAS JARABES'!G1157 -> 2155.1837 | K52: ='Gtos Varios'!$B$22 -> 3070.5429 | L52: =+LISTPROD3[[#This Row],[PRECIO DE PRODUCCIÓN POR UND]]+LISTPROD3[[#This Row],[TOTAL GASTOS VARIOS]] -> 5225.7266 | M52: ='RECETAS JARABES'!$G$1162 -> 2855.7757 | N52: ='RECETAS JARABES'!$H$1162 -> 0.49 | O52: ='RECETAS JARABES'!$G$1163 -> 8683.8895 | P52: 6000 | Q52: =(LISTPROD3[[#This Row],[PRECIO DE VENTA 1]]-LISTPROD3[[#This Row],[COSTO TOTAL UNIDAD]])/LISTPROD3[[#This Row],[COSTO TOTAL UNIDAD]] -> 0.14816569 | R52: =LISTPROD3[[#This Row],[% GANANCIA]]*LISTPROD3[[#This Row],[COSTO TOTAL UNIDAD]] -> 774.2734 | S52: =+LISTPROD3[[#This Row],[PRECIO DE VENTA 1]]-LISTPROD3[[#This Row],[PRECIO VENTA POR RECETA]] -> -2683.8895 | T52: 5000 | U52: =(LISTPROD3[[#This Row],[PRECIO DE VENTA2]]-LISTPROD3[[#This Row],[COSTO TOTAL UNIDAD]])/LISTPROD3[[#This Row],[COSTO TOTAL UNIDAD]] -> -0.043195256 | V52: =+LISTPROD3[[#This Row],[% GANANCIA2]]*LISTPROD3[[#This Row],[COSTO TOTAL UNIDAD]] -> -225.7266 | W52: =LISTPROD3[[#This Row],[PRECIO DE VENTA2]]-LISTPROD3[[#This Row],[PRECIO VENTA POR RECETA]] -> -3683.8895 | X52: 5000 | Y52: =(LISTPROD3[[#This Row],[PRECIO DE VENTA 3]]-LISTPROD3[[#This Row],[COSTO TOTAL UNIDAD]])/LISTPROD3[[#This Row],[COSTO TOTAL UNIDAD]] -> -0.043195256 | Z52: =LISTPROD3[[#This Row],[% GANANCIA3]]*LISTPROD3[[#This Row],[COSTO TOTAL UNIDAD]] -> -225.7266 | AC52: 6000 | AD52: 5000 | AE52: 5000 | AF52: 5000 | AH52: OK
A53: MM01 | B53: MERO MACHO | C53: 550 ML-Jarabe | D53: HOMEOPATICOS | E53: JARABES | F53: 500 ML | G53: BOTICA NATURAL ESCULAPIO | I53: LUIS-FARMACIA NATIVA | J53: FALTA PRECIO PROD | K53: ='Gtos Varios'!$B$22 -> 3070.5429 | L53: =+LISTPROD3[[#This Row],[PRECIO DE PRODUCCIÓN POR UND]]+LISTPROD3[[#This Row],[TOTAL GASTOS VARIOS]] -> #VALUE! | M53: ='RECETAS JARABES'!G1201 -> 3403.9762 | N53: ='RECETAS JARABES'!H1201 -> 0.62 | O53: ='RECETAS JARABES'!G1202 -> 8894.2605 | P53: 8000 | Q53: =(LISTPROD3[[#This Row],[PRECIO DE VENTA 1]]-LISTPROD3[[#This Row],[COSTO TOTAL UNIDAD]])/LISTPROD3[[#This Row],[COSTO TOTAL UNIDAD]] -> #VALUE! | R53: =LISTPROD3[[#This Row],[% GANANCIA]]*LISTPROD3[[#This Row],[COSTO TOTAL UNIDAD]] -> #VALUE! | S53: =+LISTPROD3[[#This Row],[PRECIO DE VENTA 1]]-LISTPROD3[[#This Row],[PRECIO VENTA POR RECETA]] -> -894.26047 | T53: 5000 | U53: =(LISTPROD3[[#This Row],[PRECIO DE VENTA2]]-LISTPROD3[[#This Row],[COSTO TOTAL UNIDAD]])/LISTPROD3[[#This Row],[COSTO TOTAL UNIDAD]] -> #VALUE! | V53: =+LISTPROD3[[#This Row],[% GANANCIA2]]*LISTPROD3[[#This Row],[COSTO TOTAL UNIDAD]] -> #VALUE! | W53: =LISTPROD3[[#This Row],[PRECIO DE VENTA2]]-LISTPROD3[[#This Row],[PRECIO VENTA POR RECETA]] -> -3894.2605 | X53: 5000 | Y53: =(LISTPROD3[[#This Row],[PRECIO DE VENTA 3]]-LISTPROD3[[#This Row],[COSTO TOTAL UNIDAD]])/LISTPROD3[[#This Row],[COSTO TOTAL UNIDAD]] -> #VALUE! | Z53: =LISTPROD3[[#This Row],[% GANANCIA3]]*LISTPROD3[[#This Row],[COSTO TOTAL UNIDAD]] -> #VALUE! | AC53: 8000 | AD53: 5000 | AE53: 5000 | AF53: 5000 | AH53: PREGUNTAR A LUIS POR PRECIOS Y FORMULA
A54: MO01 | B54: MORINGA OLIFERA | C54: 500 ML-Jarabe | D54: HOMEOPATICOS | E54: JARABES | F54: 500 ML | G54: PHARMA | I54: LUIS-FARMACIA NATIVA | J54: ='RECETAS JARABES'!G1228 -> 2102.6344 | K54: ='Gtos Varios'!$B$22 -> 3070.5429 | L54: =+LISTPROD3[[#This Row],[PRECIO DE PRODUCCIÓN POR UND]]+LISTPROD3[[#This Row],[TOTAL GASTOS VARIOS]] -> 5173.1773 | M54: ='RECETAS JARABES'!G1233 -> 3349.8274 | N54: ='RECETAS JARABES'!H1233 -> 0.58 | O54: ='RECETAS JARABES'!G1234 -> 9125.3918 | P54: 6000 | Q54: =(LISTPROD3[[#This Row],[PRECIO DE VENTA 1]]-LISTPROD3[[#This Row],[COSTO TOTAL UNIDAD]])/LISTPROD3[[#This Row],[COSTO TOTAL UNIDAD]] -> 0.1598288 | R54: =LISTPROD3[[#This Row],[% GANANCIA]]*LISTPROD3[[#This Row],[COSTO TOTAL UNIDAD]] -> 826.82273 | S54: =+LISTPROD3[[#This Row],[PRECIO DE VENTA 1]]-LISTPROD3[[#This Row],[PRECIO VENTA POR RECETA]] -> -3125.3918 | T54: 5000 | U54: =(LISTPROD3[[#This Row],[PRECIO DE VENTA2]]-LISTPROD3[[#This Row],[COSTO TOTAL UNIDAD]])/LISTPROD3[[#This Row],[COSTO TOTAL UNIDAD]] -> -0.033475998 | V54: =+LISTPROD3[[#This Row],[% GANANCIA2]]*LISTPROD3[[#This Row],[COSTO TOTAL UNIDAD]] -> -173.17727 | W54: =LISTPROD3[[#This Row],[PRECIO DE VENTA2]]-LISTPROD3[[#This Row],[PRECIO VENTA POR RECETA]] -> -4125.3918 | X54: 5000 | Y54: =(LISTPROD3[[#This Row],[PRECIO DE VENTA 3]]-LISTPROD3[[#This Row],[COSTO TOTAL UNIDAD]])/LISTPROD3[[#This Row],[COSTO TOTAL UNIDAD]] -> -0.033475998 | Z54: =LISTPROD3[[#This Row],[% GANANCIA3]]*LISTPROD3[[#This Row],[COSTO TOTAL UNIDAD]] -> -173.17727 | AC54: 6000 | AD54: 5000 | AE54: 5000 | AF54: 5000 | AH54: OK
A55: NS01 | B55: NERVIO Y SUSTO | C55: 500 ML-Jarabe | D55: HOMEOPATICOS | E55: JARABES | F55: 500 ML | G55: PHARMA | I55: LUIS-FARMACIA NATIVA | J55: ='RECETAS JARABES'!G1264 -> 2129.0703 | K55: ='Gtos Varios'!$B$22 -> 3070.5429 | L55: =+LISTPROD3[[#This Row],[PRECIO DE PRODUCCIÓN POR UND]]+LISTPROD3[[#This Row],[TOTAL GASTOS VARIOS]] -> 5199.6131 | M55: ='RECETAS JARABES'!G1269 -> 3365.1602 | N55: ='RECETAS JARABES'!H1269 -> 0.58 | O55: ='RECETAS JARABES'!G1270 -> 9167.1604 | P55: 6000 | Q55: =(LISTPROD3[[#This Row],[PRECIO DE VENTA 1]]-LISTPROD3[[#This Row],[COSTO TOTAL UNIDAD]])/LISTPROD3[[#This Row],[COSTO TOTAL UNIDAD]] -> 0.15393201 | R55: =LISTPROD3[[#This Row],[% GANANCIA]]*LISTPROD3[[#This Row],[COSTO TOTAL UNIDAD]] -> 800.38688 | S55: =+LISTPROD3[[#This Row],[PRECIO DE VENTA 1]]-LISTPROD3[[#This Row],[PRECIO VENTA POR RECETA]] -> -3167.1604 | T55: 5000 | U55: =(LISTPROD3[[#This Row],[PRECIO DE VENTA2]]-LISTPROD3[[#This Row],[COSTO TOTAL UNIDAD]])/LISTPROD3[[#This Row],[COSTO TOTAL UNIDAD]] -> -0.038389995 | V55: =+LISTPROD3[[#This Row],[% GANANCIA2]]*LISTPROD3[[#This Row],[COSTO TOTAL UNIDAD]] -> -199.61312 | W55: =LISTPROD3[[#This Row],[PRECIO DE VENTA2]]-LISTPROD3[[#This Row],[PRECIO VENTA POR RECETA]] -> -4167.1604 | X55: 5000 | Y55: =(LISTPROD3[[#This Row],[PRECIO DE VENTA 3]]-LISTPROD3[[#This Row],[COSTO TOTAL UNIDAD]])/LISTPROD3[[#This Row],[COSTO TOTAL UNIDAD]] -> -0.038389995 | Z55: =LISTPROD3[[#This Row],[% GANANCIA3]]*LISTPROD3[[#This Row],[COSTO TOTAL UNIDAD]] -> -199.61312 | AC55: 6000 | AD55: 5000 | AE55: 5000 | AF55: 5000 | AH55: OK
A56: NP01 | B56: NEURO PLUS LITRO | C56: 1000 ML-Jarabe | D56: HOMEOPATICOS | E56: JARABES | F56: LITRO 1000 ML | G56: CUBANO | I56: ANGIE-LHC | J56: ='RECETAS JARABES'!G1296 -> 2274.0441 | K56: ='Gtos Varios'!$B$22 -> 3070.5429 | L56: =+LISTPROD3[[#This Row],[PRECIO DE PRODUCCIÓN POR UND]]+LISTPROD3[[#This Row],[TOTAL GASTOS VARIOS]] -> 5344.5869 | M56: ='RECETAS JARABES'!$G$1301 -> 3330.3055 | N56: ='RECETAS JARABES'!$H$1301 -> 0.56 | O56: ='RECETAS JARABES'!$G$1302 -> 9277.2796 | P56: 7500 | Q56: =(LISTPROD3[[#This Row],[PRECIO DE VENTA 1]]-LISTPROD3[[#This Row],[COSTO TOTAL UNIDAD]])/LISTPROD3[[#This Row],[COSTO TOTAL UNIDAD]] -> 0.40328899 | R56: =LISTPROD3[[#This Row],[% GANANCIA]]*LISTPROD3[[#This Row],[COSTO TOTAL UNIDAD]] -> 2155.4131 | S56: =+LISTPROD3[[#This Row],[PRECIO DE VENTA 1]]-LISTPROD3[[#This Row],[PRECIO VENTA POR RECETA]] -> -1777.2796 | T56: 5000 | U56: =(LISTPROD3[[#This Row],[PRECIO DE VENTA2]]-LISTPROD3[[#This Row],[COSTO TOTAL UNIDAD]])/LISTPROD3[[#This Row],[COSTO TOTAL UNIDAD]] -> -0.064474007 | V56: =+LISTPROD3[[#This Row],[% GANANCIA2]]*LISTPROD3[[#This Row],[COSTO TOTAL UNIDAD]] -> -344.58693 | W56: =LISTPROD3[[#This Row],[PRECIO DE VENTA2]]-LISTPROD3[[#This Row],[PRECIO VENTA POR RECETA]] -> -4277.2796 | X56: 5000 | Y56: =(LISTPROD3[[#This Row],[PRECIO DE VENTA 3]]-LISTPROD3[[#This Row],[COSTO TOTAL UNIDAD]])/LISTPROD3[[#This Row],[COSTO TOTAL UNIDAD]] -> -0.064474007 | Z56: =LISTPROD3[[#This Row],[% GANANCIA3]]*LISTPROD3[[#This Row],[COSTO TOTAL UNIDAD]] -> -344.58693 | AC56: 7500 | AD56: 5000 | AE56: 5000 | AF56: 5000 | AH56: OK
A57: NO01 | B57: NUTRI OCULAR GOTAS Y PASTAS | C57: pastillas y gotas | D57: HOMEOPATICOS | I57: LUIS-FARMACIA NATIVA | P57: 8000 | Q57: =(LISTPROD3[[#This Row],[PRECIO DE VENTA 1]]-LISTPROD3[[#This Row],[COSTO TOTAL UNIDAD]])/LISTPROD3[[#This Row],[COSTO TOTAL UNIDAD]] -> #DIV/0! | R57: =LISTPROD3[[#This Row],[% GANANCIA]]*LISTPROD3[[#This Row],[COSTO TOTAL UNIDAD]] -> #DIV/0! | T57: 0 | U57: =(LISTPROD3[[#This Row],[PRECIO DE VENTA2]]-LISTPROD3[[#This Row],[COSTO TOTAL UNIDAD]])/LISTPROD3[[#This Row],[COSTO TOTAL UNIDAD]] -> #DIV/0! | V57: =LISTPROD3[[#This Row],[PRECIO DE VENTA2]]*LISTPROD3[[#This Row],[% GANANCIA2]] -> #DIV/0! | W57: =LISTPROD3[[#This Row],[PRECIO DE VENTA2]]-LISTPROD3[[#This Row],[PRECIO VENTA POR RECETA]] -> 0 | X57: 0 | AC57: 8000 | AD57: 0 | AE57: 0 | AF57: 0 | AH57: FALTA
A58: OM01 | B58: OXTEOMAX | C58: 500 ML-Jarabe | D58: HOMEOPATICOS | E58: JARABES | F58: 500 ML | G58: NATURAL PALAGAR | I58: LUIS-FARMACIA NATIVA | J58: ='RECETAS JARABES'!G1328 -> 1331.1354 | K58: ='Gtos Varios'!$B$22 -> 3070.5429 | L58: =+LISTPROD3[[#This Row],[PRECIO DE PRODUCCIÓN POR UND]]+LISTPROD3[[#This Row],[TOTAL GASTOS VARIOS]] -> 4401.6782 | M58: ='RECETAS JARABES'!G1333 -> 3452.8051 | N58: ='RECETAS JARABES'!H1333 -> 0.69 | O58: ='RECETAS JARABES'!G1334 -> 8456.8705 | P58: 6000 | Q58: =(LISTPROD3[[#This Row],[PRECIO DE VENTA 1]]-LISTPROD3[[#This Row],[COSTO TOTAL UNIDAD]])/LISTPROD3[[#This Row],[COSTO TOTAL UNIDAD]] -> 0.36311645 | R58: =LISTPROD3[[#This Row],[% GANANCIA]]*LISTPROD3[[#This Row],[COSTO TOTAL UNIDAD]] -> 1598.3218 | S58: =+LISTPROD3[[#This Row],[PRECIO DE VENTA 1]]-LISTPROD3[[#This Row],[PRECIO VENTA POR RECETA]] -> -2456.8705 | AC58: 6000 | AD58: 0 | AE58: 0 | AF58: 0 | AH58: OK
A59: PJL01 | B59: PAP BRAZ JARABE LITRO | C59: 1000 ML-Jarabe | D59: HOMEOPATICOS | E59: JARABES | F59: LITRO 1000 ML | I59: MARIA-IMPERIO NATURAL | J59: ='RECETAS JARABES'!G1357 -> 1660.4127 | K59: ='Gtos Varios'!$B$22 -> 3070.5429 | L59: =+LISTPROD3[[#This Row],[PRECIO DE PRODUCCIÓN POR UND]]+LISTPROD3[[#This Row],[TOTAL GASTOS VARIOS]] -> 4730.9555 | M59: ='RECETAS JARABES'!G1362 -> 3413.3393 | N59: ='RECETAS JARABES'!H1362 -> 0.64 | O59: ='RECETAS JARABES'!G1363 -> 8746.682 | P59: 10000 | Q59: =(LISTPROD3[[#This Row],[PRECIO DE VENTA 1]]-LISTPROD3[[#This Row],[COSTO TOTAL UNIDAD]])/LISTPROD3[[#This Row],[COSTO TOTAL UNIDAD]] -> 1.1137379 | R59: =LISTPROD3[[#This Row],[% GANANCIA]]*LISTPROD3[[#This Row],[COSTO TOTAL UNIDAD]] -> 5269.0445 | S59: =+LISTPROD3[[#This Row],[PRECIO DE VENTA 1]]-LISTPROD3[[#This Row],[PRECIO VENTA POR RECETA]] -> 1253.318 | AC59: 10000 | AD59: 0 | AE59: 0 | AF59: 0 | AG59: OJO SE DESPACHAN JUNTOS PARA NEIVA | AH59: OK
A60: CA01 | B60: CATUAMA (Capsulas) | C60: ENVASE TIENE 30 CAPSULAS | D60: HOMEOPATICOS | E60: CAPSULAS | F60: CAPSULAS 30 UND | I60: ANGIE-LHC | J60: ='RECETAS CAPS'!AW19 -> 2237.75 | K60: ='Gtos Varios'!$B$22 -> 3070.5429 | L60: =+LISTPROD3[[#This Row],[TOTAL GASTOS VARIOS]]+LISTPROD3[[#This Row],[PRECIO DE PRODUCCIÓN POR UND]] -> 5308.2929 | M60: ='RECETAS CAPS'!AW25 -> 3428.1944 | N60: ='RECETAS CAPS'!AX25 -> 0.58 | O60: ='RECETAS CAPS'!AW26 -> 9338.8744 | P60: 5000 | Q60: =(LISTPROD3[[#This Row],[PRECIO DE VENTA 1]]-LISTPROD3[[#This Row],[COSTO TOTAL UNIDAD]])/LISTPROD3[[#This Row],[COSTO TOTAL UNIDAD]] -> -0.05807759 | R60: =LISTPROD3[[#This Row],[% GANANCIA]]*LISTPROD3[[#This Row],[COSTO TOTAL UNIDAD]] -> -308.29286 | AC60: 5000 | AD60: 0 | AE60: 0 | AF60: 0 | AG60: OJO SE DESPACHAN JUNTOS PARA NEIVA | AH60: OK
A61: PJ01 | B61: PAPA JARABE | C61: 500 ML-Jarabe | D61: HOMEOPATICOS | E61: JARABES | F61: 500 ML | G61: S/M | I61: LUIS-FARMACIA NATIVA | J61: FALTA PRECIO PROD | K61: ='Gtos Varios'!$B$22 -> 3070.5429 | L61: =+LISTPROD3[[#This Row],[PRECIO DE PRODUCCIÓN POR UND]]+LISTPROD3[[#This Row],[TOTAL GASTOS VARIOS]] -> #VALUE! | M61: ='RECETAS JARABES'!G1394 -> 3516.2866 | N61: ='RECETAS JARABES'!H1394 -> 0.83 | O61: ='RECETAS JARABES'!G1395 -> 7752.7764 | P61: 2000 | Q61: =(LISTPROD3[[#This Row],[PRECIO DE VENTA 1]]-LISTPROD3[[#This Row],[COSTO TOTAL UNIDAD]])/LISTPROD3[[#This Row],[COSTO TOTAL UNIDAD]] -> #VALUE! | R61: =LISTPROD3[[#This Row],[% GANANCIA]]*LISTPROD3[[#This Row],[COSTO TOTAL UNIDAD]] -> #VALUE! | S61: =+LISTPROD3[[#This Row],[PRECIO DE VENTA 1]]-LISTPROD3[[#This Row],[PRECIO VENTA POR RECETA]] -> -5752.7764 | T61: 5000 | U61: =(LISTPROD3[[#This Row],[PRECIO DE VENTA2]]-LISTPROD3[[#This Row],[COSTO TOTAL UNIDAD]])/LISTPROD3[[#This Row],[COSTO TOTAL UNIDAD]] -> #VALUE! | V61: =+LISTPROD3[[#This Row],[% GANANCIA2]]*LISTPROD3[[#This Row],[COSTO TOTAL UNIDAD]] -> #VALUE! | W61: =LISTPROD3[[#This Row],[PRECIO DE VENTA2]]-LISTPROD3[[#This Row],[PRECIO VENTA POR RECETA]] -> -2752.7764 | X61: 5000 | Y61: =(LISTPROD3[[#This Row],[PRECIO DE VENTA 3]]-LISTPROD3[[#This Row],[COSTO TOTAL UNIDAD]])/LISTPROD3[[#This Row],[COSTO TOTAL UNIDAD]] -> #VALUE! | Z61: =LISTPROD3[[#This Row],[% GANANCIA3]]*LISTPROD3[[#This Row],[COSTO TOTAL UNIDAD]] -> #VALUE! | AC61: 2000 | AD61: 5000 | AE61: 5000 | AF61: 5000 | AH61: OK
A62: PS01 | B62: PAPA SILVESTRE (500 gr) | C62: POLVO | D62: HOMEOPATICOS | I62: LUIS-FARMACIA NATIVA | P62: 7000 | Q62: =(LISTPROD3[[#This Row],[PRECIO DE VENTA 1]]-LISTPROD3[[#This Row],[COSTO TOTAL UNIDAD]])/LISTPROD3[[#This Row],[COSTO TOTAL UNIDAD]] -> #DIV/0! | R62: =LISTPROD3[[#This Row],[% GANANCIA]]*LISTPROD3[[#This Row],[COSTO TOTAL UNIDAD]] -> #DIV/0! | T62: 5000 | U62: =(LISTPROD3[[#This Row],[PRECIO DE VENTA2]]-LISTPROD3[[#This Row],[COSTO TOTAL UNIDAD]])/LISTPROD3[[#This Row],[COSTO TOTAL UNIDAD]] -> #DIV/0! | V62: =LISTPROD3[[#This Row],[PRECIO DE VENTA2]]*LISTPROD3[[#This Row],[% GANANCIA2]] -> #DIV/0! | W62: =LISTPROD3[[#This Row],[PRECIO DE VENTA2]]-LISTPROD3[[#This Row],[PRECIO VENTA POR RECETA]] -> 5000 | X62: 5000 | AC62: 7000 | AD62: 5000 | AE62: 5000 | AF62: 5000 | AH62: FALTA
A63: PF01 | B63: POTENFULL | C63: 500 ML-Jarabe | D63: HOMEOPATICOS | E63: JARABES | F63: 500 ML | G63: SALUD Y BELLEZA NATUTAL | I63: LUIS-FARMACIA NATIVA | J63: ='RECETAS JARABES'!G33 -> 3672.93 | K63: ='Gtos Varios'!$B$22 -> 3070.5429 | L63: =+LISTPROD3[[#This Row],[PRECIO DE PRODUCCIÓN POR UND]]+LISTPROD3[[#This Row],[TOTAL GASTOS VARIOS]] -> 6743.4729 | M63: ='RECETAS JARABES'!G38 -> 3526.0128 | N63: ='RECETAS JARABES'!H38 -> 0.48 | O63: ='RECETAS JARABES'!G39 -> 10871.873 | P63: 8000 | Q63: =(LISTPROD3[[#This Row],[PRECIO DE VENTA 1]]-LISTPROD3[[#This Row],[COSTO TOTAL UNIDAD]])/LISTPROD3[[#This Row],[COSTO TOTAL UNIDAD]] -> 0.18633235 | R63: =LISTPROD3[[#This Row],[% GANANCIA]]*LISTPROD3[[#This Row],[COSTO TOTAL UNIDAD]] -> 1256.5271 | S63: =+LISTPROD3[[#This Row],[PRECIO DE VENTA 1]]-LISTPROD3[[#This Row],[PRECIO VENTA POR RECETA]] -> -2871.8728 | AC63: 8000 | AD63: 0 | AE63: 0 | AF63: 0 | AH63: OK
A64: PG01 | B64: PPG | C64: 750 ML-Jarabe | D64: HOMEOPATICOS | E64: JARABES | F64: 750 ML | I64: LUIS-FARMACIA NATIVA | J64: ='RECETAS JARABES'!G1480 -> 3428.9001 | K64: ='Gtos Varios'!$B$22 -> 3070.5429 | L64: =+LISTPROD3[[#This Row],[PRECIO DE PRODUCCIÓN POR UND]]+LISTPROD3[[#This Row],[TOTAL GASTOS VARIOS]] -> 6499.4429 | M64: ='RECETAS JARABES'!G1485 -> 3763.9699 | N64: ='RECETAS JARABES'!H1485 -> 0.53 | O64: ='RECETAS JARABES'!G1486 -> 10865.8 | P64: 8000 | Q64: =(LISTPROD3[[#This Row],[PRECIO DE VENTA 1]]-LISTPROD3[[#This Row],[COSTO TOTAL UNIDAD]])/LISTPROD3[[#This Row],[COSTO TOTAL UNIDAD]] -> 0.23087472 | R64: =LISTPROD3[[#This Row],[% GANANCIA]]*LISTPROD3[[#This Row],[COSTO TOTAL UNIDAD]] -> 1500.5571 | S64: =+LISTPROD3[[#This Row],[PRECIO DE VENTA 1]]-LISTPROD3[[#This Row],[PRECIO VENTA POR RECETA]] -> -2865.8 | AC64: 8000 | AD64: 0 | AE64: 0 | AF64: 0 | AH64: OK
A65: PP01 | B65: PROSTA PHARMA | C65: 500 ML-Jarabe | D65: HOMEOPATICOS | E65: JARABES | F65: 500 ML | G65: PHARMA | I65: LUIS-FARMACIA NATIVA | J65: ='RECETAS JARABES'!G1513 -> 2129.0703 | K65: ='Gtos Varios'!$B$22 -> 3070.5429 | L65: =+LISTPROD3[[#This Row],[PRECIO DE PRODUCCIÓN POR UND]]+LISTPROD3[[#This Row],[TOTAL GASTOS VARIOS]] -> 5199.6131 | M65: ='RECETAS JARABES'!G1518 -> 3365.1602 | N65: ='RECETAS JARABES'!H1518 -> 0.58 | O65: ='RECETAS JARABES'!G1519 -> 9167.1604 | P65: 6000 | Q65: =(LISTPROD3[[#This Row],[PRECIO DE VENTA 1]]-LISTPROD3[[#This Row],[COSTO TOTAL UNIDAD]])/LISTPROD3[[#This Row],[COSTO TOTAL UNIDAD]] -> 0.15393201 | R65: =LISTPROD3[[#This Row],[% GANANCIA]]*LISTPROD3[[#This Row],[COSTO TOTAL UNIDAD]] -> 800.38688 | S65: =+LISTPROD3[[#This Row],[PRECIO DE VENTA 1]]-LISTPROD3[[#This Row],[PRECIO VENTA POR RECETA]] -> -3167.1604 | T65: 5000 | U65: =(LISTPROD3[[#This Row],[PRECIO DE VENTA2]]-LISTPROD3[[#This Row],[COSTO TOTAL UNIDAD]])/LISTPROD3[[#This Row],[COSTO TOTAL UNIDAD]] -> -0.038389995 | V65: =+LISTPROD3[[#This Row],[% GANANCIA2]]*LISTPROD3[[#This Row],[COSTO TOTAL UNIDAD]] -> -199.61312 | W65: =LISTPROD3[[#This Row],[PRECIO DE VENTA2]]-LISTPROD3[[#This Row],[PRECIO VENTA POR RECETA]] -> -4167.1604 | X65: 5000 | Y65: =(LISTPROD3[[#This Row],[PRECIO DE VENTA 3]]-LISTPROD3[[#This Row],[COSTO TOTAL UNIDAD]])/LISTPROD3[[#This Row],[COSTO TOTAL UNIDAD]] -> -0.038389995 | Z65: =LISTPROD3[[#This Row],[% GANANCIA3]]*LISTPROD3[[#This Row],[COSTO TOTAL UNIDAD]] -> -199.61312 | AC65: 6000 | AD65: 5000 | AE65: 5000 | AF65: 5000 | AH65: OK
A66: PB01 | B66: PROSTABELL | C66: 500 ML-Jarabe | D66: HOMEOPATICOS | E66: JARABES | F66: 500 ML | G66: CUBANO | H66: TIENE CAMARA DE COMERCIO UN TERCERO COMO DISTRIBUIDOR | I66: ANGIE-LHC | J66: ='RECETAS JARABES'!G1547 -> 2149.0703 | K66: ='Gtos Varios'!$B$22 -> 3070.5429 | L66: =+LISTPROD3[[#This Row],[PRECIO DE PRODUCCIÓN POR UND]]+LISTPROD3[[#This Row],[TOTAL GASTOS VARIOS]] -> 5219.6131 | M66: ='RECETAS JARABES'!G1552 -> 3260.3201 | N66: ='RECETAS JARABES'!H1552 -> 0.56 | O66: ='RECETAS JARABES'!G1553 -> 9082.3204 | P66: 6000 | Q66: =(LISTPROD3[[#This Row],[PRECIO DE VENTA 1]]-LISTPROD3[[#This Row],[COSTO TOTAL UNIDAD]])/LISTPROD3[[#This Row],[COSTO TOTAL UNIDAD]] -> 0.14951048 | R66: =LISTPROD3[[#This Row],[% GANANCIA]]*LISTPROD3[[#This Row],[COSTO TOTAL UNIDAD]] -> 780.38688 | S66: =+LISTPROD3[[#This Row],[PRECIO DE VENTA 1]]-LISTPROD3[[#This Row],[PRECIO VENTA POR RECETA]] -> -3082.3204 | T66: 5000 | U66: =(LISTPROD3[[#This Row],[PRECIO DE VENTA2]]-LISTPROD3[[#This Row],[COSTO TOTAL UNIDAD]])/LISTPROD3[[#This Row],[COSTO TOTAL UNIDAD]] -> -0.042074597 | V66: =+LISTPROD3[[#This Row],[% GANANCIA2]]*LISTPROD3[[#This Row],[COSTO TOTAL UNIDAD]] -> -219.61312 | W66: =LISTPROD3[[#This Row],[PRECIO DE VENTA2]]-LISTPROD3[[#This Row],[PRECIO VENTA POR RECETA]] -> -4082.3204 | X66: 5000 | Y66: =(LISTPROD3[[#This Row],[PRECIO DE VENTA 3]]-LISTPROD3[[#This Row],[COSTO TOTAL UNIDAD]])/LISTPROD3[[#This Row],[COSTO TOTAL UNIDAD]] -> -0.042074597 | Z66: =LISTPROD3[[#This Row],[% GANANCIA3]]*LISTPROD3[[#This Row],[COSTO TOTAL UNIDAD]] -> -219.61312 | AC66: 6000 | AD66: 5000 | AE66: 5000 | AF66: 5000 | AH66: PREGUNTAR A LUIS POR PRECIOS Y FORMULA
A67: PT01 | B67: PROX TAP LITRO | C67: 1000 ML-Jarabe | D67: HOMEOPATICOS | E67: JARABES | F67: LITRO 1000 ML | G67: CUBANO | I67: ANGIE-LHC | J67: ='RECETAS JARABES'!G1579 -> 2108.225 | K67: ='Gtos Varios'!$B$22 -> 3070.5429 | L67: =+LISTPROD3[[#This Row],[PRECIO DE PRODUCCIÓN POR UND]]+LISTPROD3[[#This Row],[TOTAL GASTOS VARIOS]] -> 5178.7679 | M67: ='RECETAS JARABES'!G1584 -> 3353.0699 | N67: ='RECETAS JARABES'!H1584 -> 0.58 | O67: ='RECETAS JARABES'!G1585 -> 9134.225 | P67: 7500 | Q67: =(LISTPROD3[[#This Row],[PRECIO DE VENTA 1]]-LISTPROD3[[#This Row],[COSTO TOTAL UNIDAD]])/LISTPROD3[[#This Row],[COSTO TOTAL UNIDAD]] -> 0.44822092 | R67: =LISTPROD3[[#This Row],[% GANANCIA]]*LISTPROD3[[#This Row],[COSTO TOTAL UNIDAD]] -> 2321.2321 | S67: =+LISTPROD3[[#This Row],[PRECIO DE VENTA 1]]-LISTPROD3[[#This Row],[PRECIO VENTA POR RECETA]] -> -1634.225 | AC67: 7500 | AD67: 0 | AE67: 0 | AF67: 0 | AH67: OK
A68: RP01 | B68: RENAL PLUS | C68: 500 ML-Jarabe | D68: HOMEOPATICOS | E68: JARABES | F68: 500 ML | G68: PHARMA | I68: LUIS-FARMACIA NATIVA | J68: ='RECETAS JARABES'!G1613 -> 2129.0703 | K68: ='Gtos Varios'!$B$22 -> 3070.5429 | L68: =+LISTPROD3[[#This Row],[PRECIO DE PRODUCCIÓN POR UND]]+LISTPROD3[[#This Row],[TOTAL GASTOS VARIOS]] -> 5199.6131 | M68: ='RECETAS JARABES'!G1618 -> 3365.1602 | N68: ='RECETAS JARABES'!H1618 -> 0.58 | O68: ='RECETAS JARABES'!G1619 -> 9167.1604 | P68: 6000 | Q68: =(LISTPROD3[[#This Row],[PRECIO DE VENTA 1]]-LISTPROD3[[#This Row],[COSTO TOTAL UNIDAD]])/LISTPROD3[[#This Row],[COSTO TOTAL UNIDAD]] -> 0.15393201 | R68: =LISTPROD3[[#This Row],[% GANANCIA]]*LISTPROD3[[#This Row],[COSTO TOTAL UNIDAD]] -> 800.38688 | S68: =+LISTPROD3[[#This Row],[PRECIO DE VENTA 1]]-LISTPROD3[[#This Row],[PRECIO VENTA POR RECETA]] -> -3167.1604 | T68: 5000 | U68: =(LISTPROD3[[#This Row],[PRECIO DE VENTA2]]-LISTPROD3[[#This Row],[COSTO TOTAL UNIDAD]])/LISTPROD3[[#This Row],[COSTO TOTAL UNIDAD]] -> -0.038389995 | V68: =+LISTPROD3[[#This Row],[% GANANCIA2]]*LISTPROD3[[#This Row],[COSTO TOTAL UNIDAD]] -> -199.61312 | W68: =LISTPROD3[[#This Row],[PRECIO DE VENTA2]]-LISTPROD3[[#This Row],[PRECIO VENTA POR RECETA]] -> -4167.1604 | X68: 5000 | Y68: =(LISTPROD3[[#This Row],[PRECIO DE VENTA 3]]-LISTPROD3[[#This Row],[COSTO TOTAL UNIDAD]])/LISTPROD3[[#This Row],[COSTO TOTAL UNIDAD]] -> -0.038389995 | Z68: =LISTPROD3[[#This Row],[% GANANCIA3]]*LISTPROD3[[#This Row],[COSTO TOTAL UNIDAD]] -> -199.61312 | AC68: 6000 | AD68: 5000 | AE68: 5000 | AF68: 5000 | AH68: OK
A69: RO01 | B69: REUMAT OFF LITRO | C69: 1000 ML-Jarabe | D69: HOMEOPATICOS | E69: JARABES | F69: LITRO 1000 ML | G69: CUBANO | I69: ANGIE-LHC | J69: ='RECETAS JARABES'!G1644 -> 2745.6159 | K69: ='Gtos Varios'!$B$22 -> 3070.5429 | L69: =+LISTPROD3[[#This Row],[PRECIO DE PRODUCCIÓN POR UND]]+LISTPROD3[[#This Row],[TOTAL GASTOS VARIOS]] -> 5816.1587 | M69: ='RECETAS JARABES'!G1649 -> 3337.6439 | N69: ='RECETAS JARABES'!H1649 -> 0.52 | O69: ='RECETAS JARABES'!G1650 -> 9756.1897 | P69: 7500 | Q69: =(LISTPROD3[[#This Row],[PRECIO DE VENTA 1]]-LISTPROD3[[#This Row],[COSTO TOTAL UNIDAD]])/LISTPROD3[[#This Row],[COSTO TOTAL UNIDAD]] -> 0.28951089 | R69: =LISTPROD3[[#This Row],[% GANANCIA]]*LISTPROD3[[#This Row],[COSTO TOTAL UNIDAD]] -> 1683.8413 | S69: =+LISTPROD3[[#This Row],[PRECIO DE VENTA 1]]-LISTPROD3[[#This Row],[PRECIO VENTA POR RECETA]] -> -2256.1897 | AC69: 7500 | AD69: 0 | AE69: 0 | AF69: 0 | AH69: OK
A70: RC01 | B70: ROMPE CALCULOS | C70: 500 ML-Jarabe | D70: HOMEOPATICOS | E70: JARABES | F70: 500 ML | G70: PHARMA | I70: LUIS-FARMACIA NATIVA | J70: ='RECETAS JARABES'!G1680 -> 2129.0703 | K70: ='Gtos Varios'!$B$22 -> 3070.5429 | L70: =+LISTPROD3[[#This Row],[PRECIO DE PRODUCCIÓN POR UND]]+LISTPROD3[[#This Row],[TOTAL GASTOS VARIOS]] -> 5199.6131 | M70: ='RECETAS JARABES'!G1685 -> 3365.1602 | N70: ='RECETAS JARABES'!H1685 -> 0.58 | O70: ='RECETAS JARABES'!G1686 -> 9167.1604 | P70: 6000 | Q70: =(LISTPROD3[[#This Row],[PRECIO DE VENTA 1]]-LISTPROD3[[#This Row],[COSTO TOTAL UNIDAD]])/LISTPROD3[[#This Row],[COSTO TOTAL UNIDAD]] -> 0.15393201 | R70: =LISTPROD3[[#This Row],[% GANANCIA]]*LISTPROD3[[#This Row],[COSTO TOTAL UNIDAD]] -> 800.38688 | S70: =+LISTPROD3[[#This Row],[PRECIO DE VENTA 1]]-LISTPROD3[[#This Row],[PRECIO VENTA POR RECETA]] -> -3167.1604 | T70: 5000 | U70: =(LISTPROD3[[#This Row],[PRECIO DE VENTA2]]-LISTPROD3[[#This Row],[COSTO TOTAL UNIDAD]])/LISTPROD3[[#This Row],[COSTO TOTAL UNIDAD]] -> -0.038389995 | V70: =+LISTPROD3[[#This Row],[% GANANCIA2]]*LISTPROD3[[#This Row],[COSTO TOTAL UNIDAD]] -> -199.61312 | W70: =LISTPROD3[[#This Row],[PRECIO DE VENTA2]]-LISTPROD3[[#This Row],[PRECIO VENTA POR RECETA]] -> -4167.1604 | X70: 5000 | Y70: =(LISTPROD3[[#This Row],[PRECIO DE VENTA 3]]-LISTPROD3[[#This Row],[COSTO TOTAL UNIDAD]])/LISTPROD3[[#This Row],[COSTO TOTAL UNIDAD]] -> -0.038389995 | Z70: =LISTPROD3[[#This Row],[% GANANCIA3]]*LISTPROD3[[#This Row],[COSTO TOTAL UNIDAD]] -> -199.61312 | AC70: 6000 | AD70: 5000 | AE70: 5000 | AF70: 5000 | AH70: OK
A71: RQ01 | B71: ROMPE QUISTES | C71: 500 ML-Jarabe | D71: HOMEOPATICOS | E71: JARABES | F71: 500 ML | G71: PHARMA | I71: LUIS-FARMACIA NATIVA | J71: FALTA PRECIO PROD | K71: ='Gtos Varios'!$B$22 -> 3070.5429 | L71: =+LISTPROD3[[#This Row],[PRECIO DE PRODUCCIÓN POR UND]]+LISTPROD3[[#This Row],[TOTAL GASTOS VARIOS]] -> #VALUE! | M71: ='RECETAS JARABES'!G1720 -> 3364.3853 | N71: ='RECETAS JARABES'!H1720 -> 0.58 | O71: ='RECETAS JARABES'!G1721 -> 9165.0497 | P71: 6000 | Q71: =(LISTPROD3[[#This Row],[PRECIO DE VENTA 1]]-LISTPROD3[[#This Row],[COSTO TOTAL UNIDAD]])/LISTPROD3[[#This Row],[COSTO TOTAL UNIDAD]] -> #VALUE! | R71: =LISTPROD3[[#This Row],[% GANANCIA]]*LISTPROD3[[#This Row],[COSTO TOTAL UNIDAD]] -> #VALUE! | S71: =+LISTPROD3[[#This Row],[PRECIO DE VENTA 1]]-LISTPROD3[[#This Row],[PRECIO VENTA POR RECETA]] -> -3165.0497 | T71: 5000 | U71: =(LISTPROD3[[#This Row],[PRECIO DE VENTA2]]-LISTPROD3[[#This Row],[COSTO TOTAL UNIDAD]])/LISTPROD3[[#This Row],[COSTO TOTAL UNIDAD]] -> #VALUE! | V71: =+LISTPROD3[[#This Row],[% GANANCIA2]]*LISTPROD3[[#This Row],[COSTO TOTAL UNIDAD]] -> #VALUE! | W71: =LISTPROD3[[#This Row],[PRECIO DE VENTA2]]-LISTPROD3[[#This Row],[PRECIO VENTA POR RECETA]] -> -4165.0497 | X71: 5000 | Y71: =(LISTPROD3[[#This Row],[PRECIO DE VENTA 3]]-LISTPROD3[[#This Row],[COSTO TOTAL UNIDAD]])/LISTPROD3[[#This Row],[COSTO TOTAL UNIDAD]] -> #VALUE! | Z71: =LISTPROD3[[#This Row],[% GANANCIA3]]*LISTPROD3[[#This Row],[COSTO TOTAL UNIDAD]] -> #VALUE! | AC71: 6000 | AD71: 5000 | AE71: 5000 | AF71: 5000 | AH71: OK
A72: ST01 | B72: SALTO DEL TIGRE | C72: 500 ML-Jarabe | D72: HOMEOPATICOS | E72: JARABES | F72: 500 ML | G72: S/M | I72: LUIS-FARMACIA NATIVA | J72: ='RECETAS JARABES'!G1751 -> 3036.5143 | K72: ='Gtos Varios'!$B$22 -> 3070.5429 | L72: =+LISTPROD3[[#This Row],[PRECIO DE PRODUCCIÓN POR UND]]+LISTPROD3[[#This Row],[TOTAL GASTOS VARIOS]] -> 6107.0572 | M72: ='RECETAS JARABES'!G1756 -> 3220.5333 | N72: ='RECETAS JARABES'!H1756 -> 0.48 | O72: ='RECETAS JARABES'!G1757 -> 9929.9776 | P72: 8000 | Q72: =(LISTPROD3[[#This Row],[PRECIO DE VENTA 1]]-LISTPROD3[[#This Row],[COSTO TOTAL UNIDAD]])/LISTPROD3[[#This Row],[COSTO TOTAL UNIDAD]] -> 0.3099599 | R72: =LISTPROD3[[#This Row],[% GANANCIA]]*LISTPROD3[[#This Row],[COSTO TOTAL UNIDAD]] -> 1892.9428 | S72: =+LISTPROD3[[#This Row],[PRECIO DE VENTA 1]]-LISTPROD3[[#This Row],[PRECIO VENTA POR RECETA]] -> -1929.9776 | T72: 10000 | U72: =(LISTPROD3[[#This Row],[PRECIO DE VENTA2]]-LISTPROD3[[#This Row],[COSTO TOTAL UNIDAD]])/LISTPROD3[[#This Row],[COSTO TOTAL UNIDAD]] -> 0.63744988 | V72: =+LISTPROD3[[#This Row],[% GANANCIA2]]*LISTPROD3[[#This Row],[COSTO TOTAL UNIDAD]] -> 3892.9428 | W72: =LISTPROD3[[#This Row],[PRECIO DE VENTA2]]-LISTPROD3[[#This Row],[PRECIO VENTA POR RECETA]] -> 70.022423 | X72: 10000 | Y72: =(LISTPROD3[[#This Row],[PRECIO DE VENTA 3]]-LISTPROD3[[#This Row],[COSTO TOTAL UNIDAD]])/LISTPROD3[[#This Row],[COSTO TOTAL UNIDAD]] -> 0.63744988 | Z72: =LISTPROD3[[#This Row],[% GANANCIA3]]*LISTPROD3[[#This Row],[COSTO TOTAL UNIDAD]] -> 3892.9428 | AC72: 8000 | AD72: 10000 | AE72: 10000 | AF72: 10000 | AH72: OK
A73: SP01 | B73: SAW PALMETO (Capsulas) | C73: ENVASE TIENE 60 CAPSULAS | D73: HOMEOPATICOS | E73: CAPSULAS | F73: CAPSULAS 60 UND | I73: ANGIE-LHC | J73: ='RECETAS CAPS'!BK19 -> 6756.86 | K73: ='Gtos Varios'!$B$22 -> 3070.5429 | L73: =+LISTPROD3[[#This Row],[TOTAL GASTOS VARIOS]]+LISTPROD3[[#This Row],[PRECIO DE PRODUCCIÓN POR UND]] -> 9827.4029 | M73: ='RECETAS CAPS'!BK25 -> 3128.937 | N73: ='RECETAS CAPS'!BL25 -> 0.3 | O73: ='RECETAS CAPS'!BK26 -> 13558.727 | P73: 13559 | Q73: =(LISTPROD3[[#This Row],[PRECIO DE VENTA 1]]-LISTPROD3[[#This Row],[COSTO TOTAL UNIDAD]])/LISTPROD3[[#This Row],[COSTO TOTAL UNIDAD]] -> 0.37971346 | R73: =LISTPROD3[[#This Row],[% GANANCIA]]*LISTPROD3[[#This Row],[COSTO TOTAL UNIDAD]] -> 3731.5971 | AC73: 12800 | AD73: 0 | AE73: 0 | AF73: 0 | AG73: Se ajusto precio el 28/03/2025 con Luis | AH73: OK
A74: SC01 | B74: SUPER CALCIO | C74: 500 ML-Jarabe | D74: HOMEOPATICOS | E74: JARABES | F74: 500 ML | G74: CUBANO | H74: TIENE CAMARA DE COMERCIO UN TERCERO COMO DISTRIBUIDOR | I74: ANGIE-LHC | J74: ='RECETAS JARABES'!G1784 -> 2502.3862 | K74: ='Gtos Varios'!$B$22 -> 3070.5429 | L74: =+LISTPROD3[[#This Row],[PRECIO DE PRODUCCIÓN POR UND]]+LISTPROD3[[#This Row],[TOTAL GASTOS VARIOS]] -> 5572.9291 | M74: ='RECETAS JARABES'!$G$1787 -> 3272.9176 | N74: ='RECETAS JARABES'!$H$1787 -> 0.53 | O74: ='RECETAS JARABES'!$G$1788 -> 9448.2338 | P74: 7000 | Q74: =(LISTPROD3[[#This Row],[PRECIO DE VENTA 1]]-LISTPROD3[[#This Row],[COSTO TOTAL UNIDAD]])/LISTPROD3[[#This Row],[COSTO TOTAL UNIDAD]] -> 0.25607197 | R74: =LISTPROD3[[#This Row],[% GANANCIA]]*LISTPROD3[[#This Row],[COSTO TOTAL UNIDAD]] -> 1427.0709 | S74: =+LISTPROD3[[#This Row],[PRECIO DE VENTA 1]]-LISTPROD3[[#This Row],[PRECIO VENTA POR RECETA]] -> -2448.2338 | T74: 5000 | U74: =(LISTPROD3[[#This Row],[PRECIO DE VENTA2]]-LISTPROD3[[#This Row],[COSTO TOTAL UNIDAD]])/LISTPROD3[[#This Row],[COSTO TOTAL UNIDAD]] -> -0.10280574 | V74: =+LISTPROD3[[#This Row],[% GANANCIA2]]*LISTPROD3[[#This Row],[COSTO TOTAL UNIDAD]] -> -572.92909 | W74: =LISTPROD3[[#This Row],[PRECIO DE VENTA2]]-LISTPROD3[[#This Row],[PRECIO VENTA POR RECETA]] -> -4448.2338 | X74: 5000 | Y74: =(LISTPROD3[[#This Row],[PRECIO DE VENTA 3]]-LISTPROD3[[#This Row],[COSTO TOTAL UNIDAD]])/LISTPROD3[[#This Row],[COSTO TOTAL UNIDAD]] -> -0.10280574 | Z74: =LISTPROD3[[#This Row],[% GANANCIA3]]*LISTPROD3[[#This Row],[COSTO TOTAL UNIDAD]] -> -572.92909 | AC74: 6000 | AD74: 5000 | AE74: 5000 | AF74: 5000 | AH74: OK
A75: TC01 | B75: TONICO CEREBRAL | C75: 500 ML-Jarabe | D75: HOMEOPATICOS | E75: JARABES | F75: 500 ML | G75: CUBANO | H75: TIENE CAMARA DE COMERCIO UN TERCERO COMO DISTRIBUIDOR | I75: ANGIE-LHC | J75: ='RECETAS JARABES'!G1816 -> 1875.1837 | K75: ='Gtos Varios'!$B$22 -> 3070.5429 | L75: =+LISTPROD3[[#This Row],[PRECIO DE PRODUCCIÓN POR UND]]+LISTPROD3[[#This Row],[TOTAL GASTOS VARIOS]] -> 4945.7266 | M75: ='RECETAS JARABES'!$G$1821 -> 3273.3871 | N75: ='RECETAS JARABES'!$H$1821 -> 0.59 | O75: ='RECETAS JARABES'!$G$1822 -> 8821.5009 | P75: 6000 | Q75: =(LISTPROD3[[#This Row],[PRECIO DE VENTA 1]]-LISTPROD3[[#This Row],[COSTO TOTAL UNIDAD]])/LISTPROD3[[#This Row],[COSTO TOTAL UNIDAD]] -> 0.21316856 | R75: =LISTPROD3[[#This Row],[% GANANCIA]]*LISTPROD3[[#This Row],[COSTO TOTAL UNIDAD]] -> 1054.2734 | S75: =+LISTPROD3[[#This Row],[PRECIO DE VENTA 1]]-LISTPROD3[[#This Row],[PRECIO VENTA POR RECETA]] -> -2821.5009 | T75: 5000 | U75: =(LISTPROD3[[#This Row],[PRECIO DE VENTA2]]-LISTPROD3[[#This Row],[COSTO TOTAL UNIDAD]])/LISTPROD3[[#This Row],[COSTO TOTAL UNIDAD]] -> 0.010973797 | V75: =+LISTPROD3[[#This Row],[% GANANCIA2]]*LISTPROD3[[#This Row],[COSTO TOTAL UNIDAD]] -> 54.2734 | W75: =LISTPROD3[[#This Row],[PRECIO DE VENTA2]]-LISTPROD3[[#This Row],[PRECIO VENTA POR RECETA]] -> -3821.5009 | X75: 5000 | Y75: =(LISTPROD3[[#This Row],[PRECIO DE VENTA 3]]-LISTPROD3[[#This Row],[COSTO TOTAL UNIDAD]])/LISTPROD3[[#This Row],[COSTO TOTAL UNIDAD]] -> 0.010973797 | Z75: =LISTPROD3[[#This Row],[% GANANCIA3]]*LISTPROD3[[#This Row],[COSTO TOTAL UNIDAD]] -> 54.2734 | AC75: 6000 | AD75: 5000 | AE75: 5000 | AF75: 5000 | AH75: OK
A76: TV01 | B76: TORO VITAL | C76: 500 ML-Jarabe | D76: HOMEOPATICOS | E76: JARABES | F76: 500 ML | G76: PHARMA | I76: LUIS-FARMACIA NATIVA | J76: FALTA PRECIO PROD | K76: ='Gtos Varios'!$B$22 -> 3070.5429 | L76: =+LISTPROD3[[#This Row],[PRECIO DE PRODUCCIÓN POR UND]]+LISTPROD3[[#This Row],[TOTAL GASTOS VARIOS]] -> #VALUE! | M76: ='RECETAS JARABES'!G1857 -> 3386.6192 | N76: ='RECETAS JARABES'!H1857 -> 0.58 | O76: ='RECETAS JARABES'!G1858 -> 9225.6179 | P76: 6000 | Q76: =(LISTPROD3[[#This Row],[PRECIO DE VENTA 1]]-LISTPROD3[[#This Row],[COSTO TOTAL UNIDAD]])/LISTPROD3[[#This Row],[COSTO TOTAL UNIDAD]] -> #VALUE! | R76: =LISTPROD3[[#This Row],[% GANANCIA]]*LISTPROD3[[#This Row],[COSTO TOTAL UNIDAD]] -> #VALUE! | S76: =+LISTPROD3[[#This Row],[PRECIO DE VENTA 1]]-LISTPROD3[[#This Row],[PRECIO VENTA POR RECETA]] -> -3225.6179 | T76: 5000 | U76: =(LISTPROD3[[#This Row],[PRECIO DE VENTA2]]-LISTPROD3[[#This Row],[COSTO TOTAL UNIDAD]])/LISTPROD3[[#This Row],[COSTO TOTAL UNIDAD]] -> #VALUE! | V76: =+LISTPROD3[[#This Row],[% GANANCIA2]]*LISTPROD3[[#This Row],[COSTO TOTAL UNIDAD]] -> #VALUE! | W76: =LISTPROD3[[#This Row],[PRECIO DE VENTA2]]-LISTPROD3[[#This Row],[PRECIO VENTA POR RECETA]] -> -4225.6179 | X76: 5000 | Y76: =(LISTPROD3[[#This Row],[PRECIO DE VENTA 3]]-LISTPROD3[[#This Row],[COSTO TOTAL UNIDAD]])/LISTPROD3[[#This Row],[COSTO TOTAL UNIDAD]] -> #VALUE! | Z76: =LISTPROD3[[#This Row],[% GANANCIA3]]*LISTPROD3[[#This Row],[COSTO TOTAL UNIDAD]] -> #VALUE! | AC76: 6000 | AD76: 5000 | AE76: 5000 | AF76: 5000 | AH76: OK
A77: TB01 | B77: TOS BRONQUIOS | C77: 500 ML-Jarabe | D77: HOMEOPATICOS | E77: JARABES | F77: 500 ML | G77: PHARMA | I77: LUIS-FARMACIA NATIVA | J77: ='RECETAS JARABES'!G1887 -> 2085.0596 | K77: ='Gtos Varios'!$B$22 -> 3070.5429 | L77: =+LISTPROD3[[#This Row],[PRECIO DE PRODUCCIÓN POR UND]]+LISTPROD3[[#This Row],[TOTAL GASTOS VARIOS]] -> 5155.6024 | M77: ='RECETAS JARABES'!G1892 -> 3397.2139 | N77: ='RECETAS JARABES'!H1892 -> 0.59 | O77: ='RECETAS JARABES'!G1893 -> 9155.2034 | P77: 6000 | Q77: =(LISTPROD3[[#This Row],[PRECIO DE VENTA 1]]-LISTPROD3[[#This Row],[COSTO TOTAL UNIDAD]])/LISTPROD3[[#This Row],[COSTO TOTAL UNIDAD]] -> 0.16378252 | R77: =LISTPROD3[[#This Row],[% GANANCIA]]*LISTPROD3[[#This Row],[COSTO TOTAL UNIDAD]] -> 844.39756 | S77: =+LISTPROD3[[#This Row],[PRECIO DE VENTA 1]]-LISTPROD3[[#This Row],[PRECIO VENTA POR RECETA]] -> -3155.2034 | T77: 5000 | U77: =(LISTPROD3[[#This Row],[PRECIO DE VENTA2]]-LISTPROD3[[#This Row],[COSTO TOTAL UNIDAD]])/LISTPROD3[[#This Row],[COSTO TOTAL UNIDAD]] -> -0.030181233 | V77: =+LISTPROD3[[#This Row],[% GANANCIA2]]*LISTPROD3[[#This Row],[COSTO TOTAL UNIDAD]] -> -155.60244 | W77: =LISTPROD3[[#This Row],[PRECIO DE VENTA2]]-LISTPROD3[[#This Row],[PRECIO VENTA POR RECETA]] -> -4155.2034 | X77: 5000 | Y77: =(LISTPROD3[[#This Row],[PRECIO DE VENTA 3]]-LISTPROD3[[#This Row],[COSTO TOTAL UNIDAD]])/LISTPROD3[[#This Row],[COSTO TOTAL UNIDAD]] -> -0.030181233 | Z77: =LISTPROD3[[#This Row],[% GANANCIA3]]*LISTPROD3[[#This Row],[COSTO TOTAL UNIDAD]] -> -155.60244 | AC77: 6000 | AD77: 5000 | AE77: 5000 | AF77: 5000 | AH77: OK
A78: TP01 | B78: TOTUMO PULMONARIA | C78: 500 ML-Jarabe | D78: HOMEOPATICOS | E78: JARABES | F78: 500 ML | G78: PHARMA | I78: LUIS-FARMACIA NATIVA | J78: ='RECETAS JARABES'!G1922 -> 2085.0596 | K78: ='Gtos Varios'!$B$22 -> 3070.5429 | L78: =+LISTPROD3[[#This Row],[PRECIO DE PRODUCCIÓN POR UND]]+LISTPROD3[[#This Row],[TOTAL GASTOS VARIOS]] -> 5155.6024 | M78: ='RECETAS JARABES'!G1927 -> 3397.2139 | N78: ='RECETAS JARABES'!H1927 -> 0.59 | O78: ='RECETAS JARABES'!G1928 -> 9155.2034 | P78: 6000 | Q78: =(LISTPROD3[[#This Row],[PRECIO DE VENTA 1]]-LISTPROD3[[#This Row],[COSTO TOTAL UNIDAD]])/LISTPROD3[[#This Row],[COSTO TOTAL UNIDAD]] -> 0.16378252 | R78: =LISTPROD3[[#This Row],[% GANANCIA]]*LISTPROD3[[#This Row],[COSTO TOTAL UNIDAD]] -> 844.39756 | S78: =+LISTPROD3[[#This Row],[PRECIO DE VENTA 1]]-LISTPROD3[[#This Row],[PRECIO VENTA POR RECETA]] -> -3155.2034 | T78: 5000 | U78: =(LISTPROD3[[#This Row],[PRECIO DE VENTA2]]-LISTPROD3[[#This Row],[COSTO TOTAL UNIDAD]])/LISTPROD3[[#This Row],[COSTO TOTAL UNIDAD]] -> -0.030181233 | V78: =+LISTPROD3[[#This Row],[% GANANCIA2]]*LISTPROD3[[#This Row],[COSTO TOTAL UNIDAD]] -> -155.60244 | W78: =LISTPROD3[[#This Row],[PRECIO DE VENTA2]]-LISTPROD3[[#This Row],[PRECIO VENTA POR RECETA]] -> -4155.2034 | X78: 5000 | Y78: =(LISTPROD3[[#This Row],[PRECIO DE VENTA 3]]-LISTPROD3[[#This Row],[COSTO TOTAL UNIDAD]])/LISTPROD3[[#This Row],[COSTO TOTAL UNIDAD]] -> -0.030181233 | Z78: =LISTPROD3[[#This Row],[% GANANCIA3]]*LISTPROD3[[#This Row],[COSTO TOTAL UNIDAD]] -> -155.60244 | AC78: 6000 | AD78: 5000 | AE78: 5000 | AF78: 5000 | AH78: OK
A79: UL01 | B79: ULTRADOLL | C79: PASTILLAS 60 | D79: HOMEOPATICOS | E79: PASTILLAS | F79: PASTILLAS DE 60 UND | I79: LUIS-FARMACIA NATIVA | J79: ='RECETAS PASTILLAS'!AC16 -> 4900 | K79: ='Gtos Varios'!$B$22 -> 3070.5429 | L79: =+LISTPROD3[[#This Row],[TOTAL GASTOS VARIOS]]+LISTPROD3[[#This Row],[PRECIO DE PRODUCCIÓN POR UND]] -> 7970.5429 | M79: ='RECETAS PASTILLAS'!AC21 -> 3257.7134 | N79: ='RECETAS PASTILLAS'!AD21 -> 0.38 | O79: ='RECETAS PASTILLAS'!AC22 -> 11830.643 | T79: 6000 | U79: =(LISTPROD3[[#This Row],[PRECIO DE VENTA2]]-LISTPROD3[[#This Row],[COSTO TOTAL UNIDAD]])/LISTPROD3[[#This Row],[COSTO TOTAL UNIDAD]] -> -0.24722819 | V79: =LISTPROD3[[#This Row],[PRECIO DE VENTA2]]*LISTPROD3[[#This Row],[% GANANCIA2]] -> -1483.3691 | X79: 8000 | Y79: =(LISTPROD3[[#This Row],[PRECIO DE VENTA 3]]-LISTPROD3[[#This Row],[COSTO TOTAL UNIDAD]])/LISTPROD3[[#This Row],[COSTO TOTAL UNIDAD]] -> 0.0036957511 | Z79: =+LISTPROD3[[#This Row],[PRECIO DE VENTA 3]]*LISTPROD3[[#This Row],[% GANANCIA3]] -> 29.566009 | AC79: 0 | AD79: 6000 | AE79: 8000 | AF79: 8000 | AH79: FALTA
A80: UC01 | B80: UNGÜENTO CUBANO | C80: ungüento | D80: HOMEOPATICOS | I80: ANGIE-LHC | P80: 6000 | Q80: =(LISTPROD3[[#This Row],[PRECIO DE VENTA 1]]-LISTPROD3[[#This Row],[COSTO TOTAL UNIDAD]])/LISTPROD3[[#This Row],[COSTO TOTAL UNIDAD]] -> #DIV/0! | R80: =LISTPROD3[[#This Row],[% GANANCIA]]*LISTPROD3[[#This Row],[COSTO TOTAL UNIDAD]] -> #DIV/0! | T80: 5000 | U80: =(LISTPROD3[[#This Row],[PRECIO DE VENTA2]]-LISTPROD3[[#This Row],[COSTO TOTAL UNIDAD]])/LISTPROD3[[#This Row],[COSTO TOTAL UNIDAD]] -> #DIV/0! | V80: =LISTPROD3[[#This Row],[PRECIO DE VENTA2]]*LISTPROD3[[#This Row],[% GANANCIA2]] -> #DIV/0! | W80: =LISTPROD3[[#This Row],[PRECIO DE VENTA2]]-LISTPROD3[[#This Row],[PRECIO VENTA POR RECETA]] -> 5000 | X80: 5000 | Y80: =(LISTPROD3[[#This Row],[PRECIO DE VENTA 3]]-LISTPROD3[[#This Row],[COSTO TOTAL UNIDAD]])/LISTPROD3[[#This Row],[COSTO TOTAL UNIDAD]] -> #DIV/0! | Z80: =LISTPROD3[[#This Row],[% GANANCIA3]]*LISTPROD3[[#This Row],[COSTO TOTAL UNIDAD]] -> #DIV/0! | AC80: 6000 | AD80: 5000 | AE80: 5000 | AF80: 5000 | AH80: FALTA PRECIO INSUMOS
A81: UO01 | B81: URODATIVO LITRO | C81: 1000 ML-Jarabe | D81: HOMEOPATICOS | E81: JARABES | F81: LITRO 1000 ML | G81: CUBANO | I81: ANGIE-LHC | J81: ='RECETAS JARABES'!G1953 -> 2108.225 | K81: ='Gtos Varios'!$B$22 -> 3070.5429 | L81: =+LISTPROD3[[#This Row],[PRECIO DE PRODUCCIÓN POR UND]]+LISTPROD3[[#This Row],[TOTAL GASTOS VARIOS]] -> 5178.7679 | M81: ='RECETAS JARABES'!G1958 -> 3353.0699 | N81: ='RECETAS JARABES'!H1958 -> 0.58 | O81: ='RECETAS JARABES'!G1959 -> 9134.225 | P81: 7500 | Q81: =(LISTPROD3[[#This Row],[PRECIO DE VENTA 1]]-LISTPROD3[[#This Row],[COSTO TOTAL UNIDAD]])/LISTPROD3[[#This Row],[COSTO TOTAL UNIDAD]] -> 0.44822092 | R81: =LISTPROD3[[#This Row],[% GANANCIA]]*LISTPROD3[[#This Row],[COSTO TOTAL UNIDAD]] -> 2321.2321 | S81: =+LISTPROD3[[#This Row],[PRECIO DE VENTA 1]]-LISTPROD3[[#This Row],[PRECIO VENTA POR RECETA]] -> -1634.225 | AC81: 7500 | AD81: 0 | AE81: 0 | AF81: 0 | AH81: OK
A82: VX01 | B82: VENOFLEX LITRO | C82: 1000 ML-Jarabe | D82: HOMEOPATICOS | E82: JARABES | F82: LITRO 1000 ML | G82: CUBANO | I82: ANGIE-LHC | J82: ='RECETAS JARABES'!G1982 -> 2056.7813 | K82: ='Gtos Varios'!$B$22 -> 3070.5429 | L82: =+LISTPROD3[[#This Row],[PRECIO DE PRODUCCIÓN POR UND]]+LISTPROD3[[#This Row],[TOTAL GASTOS VARIOS]] -> 5127.3242 | M82: ='RECETAS JARABES'!$G$1985 -> 3380.5297 | N82: ='RECETAS JARABES'!$H$1985 -> 0.59 | O82: ='RECETAS JARABES'!$G$1986 -> 9110.241 | P82: 7500 | Q82: =(LISTPROD3[[#This Row],[PRECIO DE VENTA 1]]-LISTPROD3[[#This Row],[COSTO TOTAL UNIDAD]])/LISTPROD3[[#This Row],[COSTO TOTAL UNIDAD]] -> 0.46275127 | R82: =LISTPROD3[[#This Row],[% GANANCIA]]*LISTPROD3[[#This Row],[COSTO TOTAL UNIDAD]] -> 2372.6758 | S82: =+LISTPROD3[[#This Row],[PRECIO DE VENTA 1]]-LISTPROD3[[#This Row],[PRECIO VENTA POR RECETA]] -> -1610.241 | AC82: 7500 | AD82: 0 | AE82: 0 | AF82: 0 | AH82: OK
A83: VC01 | B83: VINO CEREBRAL | C83: 500 ML-Jarabe | D83: HOMEOPATICOS | E83: JARABES | F83: 500 ML | G83: PHARMA | I83: LUIS-FARMACIA NATIVA | J83: ='RECETAS JARABES'!G2016 -> 2155.1837 | K83: ='Gtos Varios'!$B$22 -> 3070.5429 | L83: =+LISTPROD3[[#This Row],[PRECIO DE PRODUCCIÓN POR UND]]+LISTPROD3[[#This Row],[TOTAL GASTOS VARIOS]] -> 5225.7266 | M83: ='RECETAS JARABES'!$G$2021 -> 3380.306 | N83: ='RECETAS JARABES'!$H$2021 -> 0.58 | O83: ='RECETAS JARABES'!$G$2022 -> 9208.4197 | P83: 6000 | Q83: =(LISTPROD3[[#This Row],[PRECIO DE VENTA 1]]-LISTPROD3[[#This Row],[COSTO TOTAL UNIDAD]])/LISTPROD3[[#This Row],[COSTO TOTAL UNIDAD]] -> 0.14816569 | R83: =LISTPROD3[[#This Row],[% GANANCIA]]*LISTPROD3[[#This Row],[COSTO TOTAL UNIDAD]] -> 774.2734 | S83: =+LISTPROD3[[#This Row],[PRECIO DE VENTA 1]]-LISTPROD3[[#This Row],[PRECIO VENTA POR RECETA]] -> -3208.4197 | T83: 5000 | U83: =(LISTPROD3[[#This Row],[PRECIO DE VENTA2]]-LISTPROD3[[#This Row],[COSTO TOTAL UNIDAD]])/LISTPROD3[[#This Row],[COSTO TOTAL UNIDAD]] -> -0.043195256 | V83: =+LISTPROD3[[#This Row],[% GANANCIA2]]*LISTPROD3[[#This Row],[COSTO TOTAL UNIDAD]] -> -225.7266 | W83: =LISTPROD3[[#This Row],[PRECIO DE VENTA2]]-LISTPROD3[[#This Row],[PRECIO VENTA POR RECETA]] -> -4208.4197 | X83: 5000 | Y83: =(LISTPROD3[[#This Row],[PRECIO DE VENTA 3]]-LISTPROD3[[#This Row],[COSTO TOTAL UNIDAD]])/LISTPROD3[[#This Row],[COSTO TOTAL UNIDAD]] -> -0.043195256 | Z83: =LISTPROD3[[#This Row],[% GANANCIA3]]*LISTPROD3[[#This Row],[COSTO TOTAL UNIDAD]] -> -225.7266 | AC83: 6000 | AD83: 5000 | AE83: 5000 | AF83: 5000 | AH83: OK
A84: VP01 | B84: VISION PLUS (Gotas) | C84: 25 ML | D84: HOMEOPATICOS | E84: GOTAS | F84: 25 ML | I84: LUIS-FARMACIA NATIVA | J84: FALTA PRECIO PROD | K84: ='Gtos Varios'!$B$22 -> 3070.5429 | L84: =+LISTPROD3[[#This Row],[TOTAL GASTOS VARIOS]]+LISTPROD3[[#This Row],[PRECIO DE PRODUCCIÓN POR UND]] -> #VALUE! | M84: ='RECETAS GOTAS'!K125 -> 3238.3158 | N84: ='RECETAS GOTAS'!L125 -> 0.59 | O84: ='RECETAS GOTAS'!K126 -> 8726.9868 | P84: 3500 | Q84: =(LISTPROD3[[#This Row],[PRECIO DE VENTA 1]]-LISTPROD3[[#This Row],[COSTO TOTAL UNIDAD]])/LISTPROD3[[#This Row],[COSTO TOTAL UNIDAD]] -> #VALUE! | R84: =LISTPROD3[[#This Row],[% GANANCIA]]*LISTPROD3[[#This Row],[COSTO TOTAL UNIDAD]] -> #VALUE! | T84: 0 | U84: =(LISTPROD3[[#This Row],[PRECIO DE VENTA2]]-LISTPROD3[[#This Row],[COSTO TOTAL UNIDAD]])/LISTPROD3[[#This Row],[COSTO TOTAL UNIDAD]] -> #VALUE! | V84: =LISTPROD3[[#This Row],[PRECIO DE VENTA2]]*LISTPROD3[[#This Row],[% GANANCIA2]] -> #VALUE! | W84: =LISTPROD3[[#This Row],[PRECIO DE VENTA2]]-LISTPROD3[[#This Row],[PRECIO VENTA POR RECETA]] -> -8726.9868 | X84: 0 | AC84: 3500 | AD84: 0 | AE84: 0 | AF84: 0 | AH84: PREGUNTAR A LUIS POR PRECIOS Y FORMULA
A85: VCF01 | B85: VITA CEREBRINA FRANCESA | C85: 500 ML-Jarabe | D85: HOMEOPATICOS | E85: JARABES | F85: 500 ML | G85: PHARMA | I85: LUIS-FARMACIA NATIVA | J85: FALTA PRECIO PROD | K85: ='Gtos Varios'!$B$22 -> 3070.5429 | L85: =+LISTPROD3[[#This Row],[PRECIO DE PRODUCCIÓN POR UND]]+LISTPROD3[[#This Row],[TOTAL GASTOS VARIOS]] -> #VALUE! | M85: ='RECETAS JARABES'!G2058 -> 3385.0181 | N85: ='RECETAS JARABES'!H2058 -> 0.58 | O85: ='RECETAS JARABES'!G2059 -> 9221.2562 | P85: 6000 | Q85: =(LISTPROD3[[#This Row],[PRECIO DE VENTA 1]]-LISTPROD3[[#This Row],[COSTO TOTAL UNIDAD]])/LISTPROD3[[#This Row],[COSTO TOTAL UNIDAD]] -> #VALUE! | R85: =LISTPROD3[[#This Row],[% GANANCIA]]*LISTPROD3[[#This Row],[COSTO TOTAL UNIDAD]] -> #VALUE! | S85: =+LISTPROD3[[#This Row],[PRECIO DE VENTA 1]]-LISTPROD3[[#This Row],[PRECIO VENTA POR RECETA]] -> -3221.2562 | T85: 5000 | U85: =(LISTPROD3[[#This Row],[PRECIO DE VENTA2]]-LISTPROD3[[#This Row],[COSTO TOTAL UNIDAD]])/LISTPROD3[[#This Row],[COSTO TOTAL UNIDAD]] -> #VALUE! | V85: =+LISTPROD3[[#This Row],[% GANANCIA2]]*LISTPROD3[[#This Row],[COSTO TOTAL UNIDAD]] -> #VALUE! | W85: =LISTPROD3[[#This Row],[PRECIO DE VENTA2]]-LISTPROD3[[#This Row],[PRECIO VENTA POR RECETA]] -> -4221.2562 | X85: 5000 | Y85: =(LISTPROD3[[#This Row],[PRECIO DE VENTA 3]]-LISTPROD3[[#This Row],[COSTO TOTAL UNIDAD]])/LISTPROD3[[#This Row],[COSTO TOTAL UNIDAD]] -> #VALUE! | Z85: =LISTPROD3[[#This Row],[% GANANCIA3]]*LISTPROD3[[#This Row],[COSTO TOTAL UNIDAD]] -> #VALUE! | AC85: 6000 | AD85: 5000 | AE85: 5000 | AF85: 5000 | AH85: OK
A86: WN01 | B86: WILTRON | C86: 500 ML-Jarabe | D86: HOMEOPATICOS | E86: JARABES | F86: 500 ML | G86: S/M | I86: LUIS-FARMACIA NATIVA | J86: ='RECETAS JARABES'!G2087 -> 1611.9902 | K86: ='Gtos Varios'!$B$22 -> 3070.5429 | L86: =+LISTPROD3[[#This Row],[PRECIO DE PRODUCCIÓN POR UND]]+LISTPROD3[[#This Row],[TOTAL GASTOS VARIOS]] -> 4682.533 | M86: ='RECETAS JARABES'!G2092 -> 3382.3489 | N86: ='RECETAS JARABES'!H2092 -> 0.69 | O86: ='RECETAS JARABES'!G2093 -> 8667.2691 | P86: 8000 | Q86: =(LISTPROD3[[#This Row],[PRECIO DE VENTA 1]]-LISTPROD3[[#This Row],[COSTO TOTAL UNIDAD]])/LISTPROD3[[#This Row],[COSTO TOTAL UNIDAD]] -> 0.70847701 | R86: =LISTPROD3[[#This Row],[% GANANCIA]]*LISTPROD3[[#This Row],[COSTO TOTAL UNIDAD]] -> 3317.467 | S86: =+LISTPROD3[[#This Row],[PRECIO DE VENTA 1]]-LISTPROD3[[#This Row],[PRECIO VENTA POR RECETA]] -> -667.26906 | T86: 0 | U86: =(LISTPROD3[[#This Row],[PRECIO DE VENTA2]]-LISTPROD3[[#This Row],[COSTO TOTAL UNIDAD]])/LISTPROD3[[#This Row],[COSTO TOTAL UNIDAD]] -> -1 | V86: =+LISTPROD3[[#This Row],[% GANANCIA2]]*LISTPROD3[[#This Row],[COSTO TOTAL UNIDAD]] -> -4682.533 | W86: =LISTPROD3[[#This Row],[PRECIO DE VENTA2]]-LISTPROD3[[#This Row],[PRECIO VENTA POR RECETA]] -> -8667.2691 | AC86: 8000 | AD86: 0 | AE86: 0 | AF86: 0 | AH86: OK
A87: FN01 | B87: ZARZAPARILLA | C87: 500 ML-Jarabe | D87: HOMEOPATICOS | E87: JARABES | F87: 500 ML | I87: LUIS-FARMACIA NATIVA | J87: ='RECETAS JARABES'!G2120 -> 1404.867 | K87: ='Gtos Varios'!$B$22 -> 3070.5429 | L87: =+LISTPROD3[[#This Row],[PRECIO DE PRODUCCIÓN POR UND]]+LISTPROD3[[#This Row],[TOTAL GASTOS VARIOS]] -> 4475.4098 | M87: ='RECETAS JARABES'!G2125 -> 3351.346 | N87: ='RECETAS JARABES'!H2125 -> 0.66 | O87: ='RECETAS JARABES'!G2126 -> 8429.143 | P87: 6000 | Q87: =(LISTPROD3[[#This Row],[PRECIO DE VENTA 1]]-LISTPROD3[[#This Row],[COSTO TOTAL UNIDAD]])/LISTPROD3[[#This Row],[COSTO TOTAL UNIDAD]] -> 0.34065934 | R87: =LISTPROD3[[#This Row],[% GANANCIA]]*LISTPROD3[[#This Row],[COSTO TOTAL UNIDAD]] -> 1524.5902 | S87: =+LISTPROD3[[#This Row],[PRECIO DE VENTA 1]]-LISTPROD3[[#This Row],[PRECIO VENTA POR RECETA]] -> -2429.143 | T87: 5000 | U87: =(LISTPROD3[[#This Row],[PRECIO DE VENTA2]]-LISTPROD3[[#This Row],[COSTO TOTAL UNIDAD]])/LISTPROD3[[#This Row],[COSTO TOTAL UNIDAD]] -> 0.11721612 | V87: =+LISTPROD3[[#This Row],[% GANANCIA2]]*LISTPROD3[[#This Row],[COSTO TOTAL UNIDAD]] -> 524.59017 | W87: =LISTPROD3[[#This Row],[PRECIO DE VENTA2]]-LISTPROD3[[#This Row],[PRECIO VENTA POR RECETA]] -> -3429.143 | X87: 5000 | Y87: =(LISTPROD3[[#This Row],[PRECIO DE VENTA 3]]-LISTPROD3[[#This Row],[COSTO TOTAL UNIDAD]])/LISTPROD3[[#This Row],[COSTO TOTAL UNIDAD]] -> 0.11721612 | Z87: =LISTPROD3[[#This Row],[% GANANCIA3]]*LISTPROD3[[#This Row],[COSTO TOTAL UNIDAD]] -> 524.59017 | AC87: 6000 | AD87: 5000 | AE87: 5000 | AF87: 5000 | AH87: FALTA
A88: CDM01 | B88: CITRATO DE MAGNESIO (Capsulas) | C88: ENVASE TIENE 60 CAPSULAS | D88: HOMEOPATICOS | E88: CAPSULAS | F88: CAPSULAS 60 UND | I88: ANGIE-LHC | J88: ='RECETAS CAPS'!BY19 -> 2751.32 | K88: ='Gtos Varios'!$B$22 -> 3070.5429 | L88: =+LISTPROD3[[#This Row],[TOTAL GASTOS VARIOS]]+LISTPROD3[[#This Row],[PRECIO DE PRODUCCIÓN POR UND]] -> 5821.8629 | M88: ='RECETAS CAPS'!BY25 -> 3404.8525 | N88: ='RECETAS CAPS'!BZ25 -> 0.53 | O88: ='RECETAS CAPS'!BY26 -> 9829.1025 | P88: 8500 | Q88: =(LISTPROD3[[#This Row],[PRECIO DE VENTA 1]]-LISTPROD3[[#This Row],[COSTO TOTAL UNIDAD]])/LISTPROD3[[#This Row],[COSTO TOTAL UNIDAD]] -> 0.46001378 | R88: =LISTPROD3[[#This Row],[% GANANCIA]]*LISTPROD3[[#This Row],[COSTO TOTAL UNIDAD]] -> 2678.1371 | T88: 7000 | U88: =(LISTPROD3[[#This Row],[PRECIO DE VENTA2]]-LISTPROD3[[#This Row],[COSTO TOTAL UNIDAD]])/LISTPROD3[[#This Row],[COSTO TOTAL UNIDAD]] -> 0.20236429 | V88: =LISTPROD3[[#This Row],[PRECIO DE VENTA2]]*LISTPROD3[[#This Row],[% GANANCIA2]] -> 1416.55 | W88: =LISTPROD3[[#This Row],[PRECIO DE VENTA2]]-LISTPROD3[[#This Row],[PRECIO VENTA POR RECETA]] -> -2829.1025 | X88: 7000 | Y88: =(LISTPROD3[[#This Row],[PRECIO DE VENTA 3]]-LISTPROD3[[#This Row],[COSTO TOTAL UNIDAD]])/LISTPROD3[[#This Row],[COSTO TOTAL UNIDAD]] -> 0.20236429 | Z88: =LISTPROD3[[#This Row],[% GANANCIA3]]*LISTPROD3[[#This Row],[COSTO TOTAL UNIDAD]] -> 1178.1371 | AC88: 8500 | AD88: 7000 | AE88: 7000 | AF88: 7000 | AG88: Se ajusto precio el 28/03/2025 con Luis | AH88: OK
A89: AE01 | B89: AGUAJE (Capsulas) | C89: ENVASE TIENE 60 CAPSULAS | D89: HOMEOPATICOS | E89: CAPSULAS | F89: CAPSULAS 60 UND | I89: ANGIE-LHC | J89: ='RECETAS CAPS'!G51 -> 3158.3 | K89: ='Gtos Varios'!$B$22 -> 3070.5429 | L89: =+LISTPROD3[[#This Row],[TOTAL GASTOS VARIOS]]+LISTPROD3[[#This Row],[PRECIO DE PRODUCCIÓN POR UND]] -> 6228.8429 | M89: ='RECETAS CAPS'!G57 -> 3347.3027 | N89: ='RECETAS CAPS'!H57 -> 0.49 | O89: ='RECETAS CAPS'!G58 -> 10178.533 | P89: 9500 | Q89: =(LISTPROD3[[#This Row],[PRECIO DE VENTA 1]]-LISTPROD3[[#This Row],[COSTO TOTAL UNIDAD]])/LISTPROD3[[#This Row],[COSTO TOTAL UNIDAD]] -> 0.52516289 | R89: =LISTPROD3[[#This Row],[% GANANCIA]]*LISTPROD3[[#This Row],[COSTO TOTAL UNIDAD]] -> 3271.1571 | T89: 7000 | U89: =(LISTPROD3[[#This Row],[PRECIO DE VENTA2]]-LISTPROD3[[#This Row],[COSTO TOTAL UNIDAD]])/LISTPROD3[[#This Row],[COSTO TOTAL UNIDAD]] -> 0.12380424 | V89: =LISTPROD3[[#This Row],[PRECIO DE VENTA2]]*LISTPROD3[[#This Row],[% GANANCIA2]] -> 866.62967 | W89: =LISTPROD3[[#This Row],[PRECIO DE VENTA2]]-LISTPROD3[[#This Row],[PRECIO VENTA POR RECETA]] -> -3178.5327 | X89: 7000 | Y89: =(LISTPROD3[[#This Row],[PRECIO DE VENTA 3]]-LISTPROD3[[#This Row],[COSTO TOTAL UNIDAD]])/LISTPROD3[[#This Row],[COSTO TOTAL UNIDAD]] -> 0.12380424 | Z89: =LISTPROD3[[#This Row],[% GANANCIA3]]*LISTPROD3[[#This Row],[COSTO TOTAL UNIDAD]] -> 771.15714 | AC89: 9500 | AD89: 7000 | AE89: 7000 | AF89: 7000 | AG89: Se ajusto precio el 28/03/2025 con Luis | AH89: OK
A90: GSA01 | B90: GLUCOSAMINA (Capsulas) | C90: ENVASE TIENE 60 CAPSULAS | D90: HOMEOPATICOS | E90: CAPSULAS | F90: CAPSULAS 60 UND | I90: ANGIE-LHC | J90: ='RECETAS CAPS'!U51 -> 3765.2 | K90: ='Gtos Varios'!$B$22 -> 3070.5429 | L90: =+LISTPROD3[[#This Row],[TOTAL GASTOS VARIOS]]+LISTPROD3[[#This Row],[PRECIO DE PRODUCCIÓN POR UND]] -> 6835.7429 | M90: ='RECETAS CAPS'!U57 -> 3347.1585 | N90: ='RECETAS CAPS'!V57 -> 0.45 | O90: ='RECETAS CAPS'!U58 -> 10785.289 | P90: 9600 | Q90: =(LISTPROD3[[#This Row],[PRECIO DE VENTA 1]]-LISTPROD3[[#This Row],[COSTO TOTAL UNIDAD]])/LISTPROD3[[#This Row],[COSTO TOTAL UNIDAD]] -> 0.40438284 | R90: =LISTPROD3[[#This Row],[% GANANCIA]]*LISTPROD3[[#This Row],[COSTO TOTAL UNIDAD]] -> 2764.2571 | T90: 7000 | U90: =(LISTPROD3[[#This Row],[PRECIO DE VENTA2]]-LISTPROD3[[#This Row],[COSTO TOTAL UNIDAD]])/LISTPROD3[[#This Row],[COSTO TOTAL UNIDAD]] -> 0.024029158 | V90: =LISTPROD3[[#This Row],[PRECIO DE VENTA2]]*LISTPROD3[[#This Row],[% GANANCIA2]] -> 168.2041 | W90: =LISTPROD3[[#This Row],[PRECIO DE VENTA2]]-LISTPROD3[[#This Row],[PRECIO VENTA POR RECETA]] -> -3785.2885 | X90: 7000 | Y90: =(LISTPROD3[[#This Row],[PRECIO DE VENTA 3]]-LISTPROD3[[#This Row],[COSTO TOTAL UNIDAD]])/LISTPROD3[[#This Row],[COSTO TOTAL UNIDAD]] -> 0.024029158 | Z90: =LISTPROD3[[#This Row],[% GANANCIA3]]*LISTPROD3[[#This Row],[COSTO TOTAL UNIDAD]] -> 164.25714 | AC90: 9600 | AD90: 7000 | AE90: 7000 | AF90: 7000 | AG90: Se ajusto precio el 28/03/2025 con Luis | AH90: OK
A91: ULD01 | B91: ULTRA DOLOR | C91: PASTILLAS 60 | D91: HOMEOPATICOS | E91: PASTILLAS | F91: PASTILLAS DE 60 UND | I91: LUIS-FARMACIA NATIVA | J91: ='RECETAS PASTILLAS'!R16 -> 4900 | K91: ='Gtos Varios'!$B$22 -> 3070.5429 | L91: =+LISTPROD3[[#This Row],[TOTAL GASTOS VARIOS]]+LISTPROD3[[#This Row],[PRECIO DE PRODUCCIÓN POR UND]] -> 7970.5429 | M91: ='RECETAS PASTILLAS'!R21 -> 3257.7134 | N91: ='RECETAS PASTILLAS'!S21 -> 0.38 | O91: ='RECETAS PASTILLAS'!R22 -> 11830.643 | T91: 6000 | U91: =(LISTPROD3[[#This Row],[PRECIO DE VENTA2]]-LISTPROD3[[#This Row],[COSTO TOTAL UNIDAD]])/LISTPROD3[[#This Row],[COSTO TOTAL UNIDAD]] -> -0.24722819 | V91: =LISTPROD3[[#This Row],[PRECIO DE VENTA2]]*LISTPROD3[[#This Row],[% GANANCIA2]] -> -1483.3691 | X91: 8000 | Y91: =(LISTPROD3[[#This Row],[PRECIO DE VENTA 3]]-LISTPROD3[[#This Row],[COSTO TOTAL UNIDAD]])/LISTPROD3[[#This Row],[COSTO TOTAL UNIDAD]] -> 0.0036957511 | Z91: =+LISTPROD3[[#This Row],[PRECIO DE VENTA 3]]*LISTPROD3[[#This Row],[% GANANCIA3]] -> 29.566009 | AC91: 0 | AD91: 6000 | AE91: 8000 | AF91: 8000 | AG91: VALIDAR PRECIO CON LUIS | AH91: FALTA
A92: EM01 | B92: EMPERADOR | C92: 500 ML-Jarabe | D92: HOMEOPATICOS | E92: JARABES | F92: 500 ML | G92: S/M | I92: LUIS-FARMACIA NATIVA | J92: ='RECETAS JARABES'!G2153 -> 3086.5143 | K92: ='Gtos Varios'!$B$22 -> 3070.5429 | L92: =+LISTPROD3[[#This Row],[PRECIO DE PRODUCCIÓN POR UND]]+LISTPROD3[[#This Row],[TOTAL GASTOS VARIOS]] -> 6157.0572 | M92: ='RECETAS JARABES'!G2158 -> 3176.9388 | N92: ='RECETAS JARABES'!H2158 -> 0.47 | O92: ='RECETAS JARABES'!G2159 -> 9936.3831 | T92: 7000 | U92: =(LISTPROD3[[#This Row],[PRECIO DE VENTA2]]-LISTPROD3[[#This Row],[COSTO TOTAL UNIDAD]])/LISTPROD3[[#This Row],[COSTO TOTAL UNIDAD]] -> 0.13690677 | V92: =+LISTPROD3[[#This Row],[% GANANCIA2]]*LISTPROD3[[#This Row],[COSTO TOTAL UNIDAD]] -> 842.94283 | W92: =LISTPROD3[[#This Row],[PRECIO DE VENTA2]]-LISTPROD3[[#This Row],[PRECIO VENTA POR RECETA]] -> -2936.3831 | X92: 7000 | Y92: =(LISTPROD3[[#This Row],[PRECIO DE VENTA 3]]-LISTPROD3[[#This Row],[COSTO TOTAL UNIDAD]])/LISTPROD3[[#This Row],[COSTO TOTAL UNIDAD]] -> 0.13690677 | Z92: =LISTPROD3[[#This Row],[% GANANCIA3]]*LISTPROD3[[#This Row],[COSTO TOTAL UNIDAD]] -> 842.94283 | AC92: 0 | AD92: 7000 | AE92: 7000 | AF92: 7000 | AH92: FALTA
A93: FD7 | B93: FACTOR D7 | C93: 500 ML-Jarabe | D93: HOMEOPATICOS | E93: JARABES | F93: 500 ML | G93: S/M | I93: LUIS-FARMACIA NATIVA | J93: ='RECETAS JARABES'!G2231 -> 1852.8522 | K93: ='Gtos Varios'!$B$22 -> 3070.5429 | L93: =+LISTPROD3[[#This Row],[PRECIO DE PRODUCCIÓN POR UND]]+LISTPROD3[[#This Row],[TOTAL GASTOS VARIOS]] -> 4923.3951 | M93: ='RECETAS JARABES'!G2236 -> 3315.4693 | N93: ='RECETAS JARABES'!H2236 -> 0.6 | O93: ='RECETAS JARABES'!G2237 -> 8841.2515 | P93: 7000 | Q93: =(LISTPROD3[[#This Row],[PRECIO DE VENTA 1]]-LISTPROD3[[#This Row],[COSTO TOTAL UNIDAD]])/LISTPROD3[[#This Row],[COSTO TOTAL UNIDAD]] -> 0.42178312 | R93: =LISTPROD3[[#This Row],[% GANANCIA]]*LISTPROD3[[#This Row],[COSTO TOTAL UNIDAD]] -> 2076.6049 | S93: =+LISTPROD3[[#This Row],[PRECIO DE VENTA 1]]-LISTPROD3[[#This Row],[PRECIO VENTA POR RECETA]] -> -1841.2515 | T93: 7000 | U93: =(LISTPROD3[[#This Row],[PRECIO DE VENTA2]]-LISTPROD3[[#This Row],[COSTO TOTAL UNIDAD]])/LISTPROD3[[#This Row],[COSTO TOTAL UNIDAD]] -> 0.42178312 | V93: =+LISTPROD3[[#This Row],[% GANANCIA2]]*LISTPROD3[[#This Row],[COSTO TOTAL UNIDAD]] -> 2076.6049 | W93: =LISTPROD3[[#This Row],[PRECIO DE VENTA2]]-LISTPROD3[[#This Row],[PRECIO VENTA POR RECETA]] -> -1841.2515 | X93: 7000 | Y93: =(LISTPROD3[[#This Row],[PRECIO DE VENTA 3]]-LISTPROD3[[#This Row],[COSTO TOTAL UNIDAD]])/LISTPROD3[[#This Row],[COSTO TOTAL UNIDAD]] -> 0.42178312 | Z93: =LISTPROD3[[#This Row],[% GANANCIA3]]*LISTPROD3[[#This Row],[COSTO TOTAL UNIDAD]] -> 2076.6049 | AC93: 7000 | AD93: 7000 | AE93: 7000 | AF93: 7000 | AH93: FALTA
A94: OP01 | B94: ORTIGA PHARMA | C94: 500 ML-Jarabe | D94: HOMEOPATICOS | E94: JARABES | F94: 500 ML | G94: PHARMA | I94: LUIS-FARMACIA NATIVA | J94: ='RECETAS JARABES'!G2264 -> 2102.6344 | K94: ='Gtos Varios'!$B$22 -> 3070.5429 | L94: =+LISTPROD3[[#This Row],[PRECIO DE PRODUCCIÓN POR UND]]+LISTPROD3[[#This Row],[TOTAL GASTOS VARIOS]] -> 5173.1773 | M94: ='RECETAS JARABES'!$G$2269 -> 3349.8274 | N94: ='RECETAS JARABES'!$H$2269 -> 0.58 | O94: ='RECETAS JARABES'!$G$2270 -> 9125.3918 | P94: 6000 | Q94: =(LISTPROD3[[#This Row],[PRECIO DE VENTA 1]]-LISTPROD3[[#This Row],[COSTO TOTAL UNIDAD]])/LISTPROD3[[#This Row],[COSTO TOTAL UNIDAD]] -> 0.1598288 | R94: =LISTPROD3[[#This Row],[% GANANCIA]]*LISTPROD3[[#This Row],[COSTO TOTAL UNIDAD]] -> 826.82273 | S94: =+LISTPROD3[[#This Row],[PRECIO DE VENTA 1]]-LISTPROD3[[#This Row],[PRECIO VENTA POR RECETA]] -> -3125.3918 | T94: 7000 | U94: =(LISTPROD3[[#This Row],[PRECIO DE VENTA2]]-LISTPROD3[[#This Row],[COSTO TOTAL UNIDAD]])/LISTPROD3[[#This Row],[COSTO TOTAL UNIDAD]] -> 0.3531336 | V94: =+LISTPROD3[[#This Row],[% GANANCIA2]]*LISTPROD3[[#This Row],[COSTO TOTAL UNIDAD]] -> 1826.8227 | W94: =LISTPROD3[[#This Row],[PRECIO DE VENTA2]]-LISTPROD3[[#This Row],[PRECIO VENTA POR RECETA]] -> -2125.3918 | X94: 7000 | Y94: =(LISTPROD3[[#This Row],[PRECIO DE VENTA 3]]-LISTPROD3[[#This Row],[COSTO TOTAL UNIDAD]])/LISTPROD3[[#This Row],[COSTO TOTAL UNIDAD]] -> 0.3531336 | Z94: =LISTPROD3[[#This Row],[% GANANCIA3]]*LISTPROD3[[#This Row],[COSTO TOTAL UNIDAD]] -> 1826.8227 | AC94: 6000 | AD94: 7000 | AE94: 7000 | AF94: 7000 | AH94: OK
A95: MMT01 | B95: MEMOTRON | C95: 500 ML-Jarabe | D95: HOMEOPATICOS | E95: JARABES | F95: 500 ML | G95: NATURAL PALAGAR | I95: MARIA-IMPERIO NATURAL | J95: FALTA PRECIO PROD | K95: ='Gtos Varios'!$B$22 -> 3070.5429 | L95: =+LISTPROD3[[#This Row],[PRECIO DE PRODUCCIÓN POR UND]]+LISTPROD3[[#This Row],[TOTAL GASTOS VARIOS]] -> #VALUE! | M95: ='RECETAS JARABES'!G2303 -> 3429.2904 | N95: ='RECETAS JARABES'!H2303 -> 0.72 | O95: ='RECETAS JARABES'!G2304 -> 8192.1938 | P95: 7000 | Q95: =(LISTPROD3[[#This Row],[PRECIO DE VENTA 1]]-LISTPROD3[[#This Row],[COSTO TOTAL UNIDAD]])/LISTPROD3[[#This Row],[COSTO TOTAL UNIDAD]] -> #VALUE! | R95: =LISTPROD3[[#This Row],[% GANANCIA]]*LISTPROD3[[#This Row],[COSTO TOTAL UNIDAD]] -> #VALUE! | S95: =+LISTPROD3[[#This Row],[PRECIO DE VENTA 1]]-LISTPROD3[[#This Row],[PRECIO VENTA POR RECETA]] -> -1192.1938 | T95: 7000 | U95: =(LISTPROD3[[#This Row],[PRECIO DE VENTA2]]-LISTPROD3[[#This Row],[COSTO TOTAL UNIDAD]])/LISTPROD3[[#This Row],[COSTO TOTAL UNIDAD]] -> #VALUE! | V95: =+LISTPROD3[[#This Row],[% GANANCIA2]]*LISTPROD3[[#This Row],[COSTO TOTAL UNIDAD]] -> #VALUE! | W95: =LISTPROD3[[#This Row],[PRECIO DE VENTA2]]-LISTPROD3[[#This Row],[PRECIO VENTA POR RECETA]] -> -1192.1938 | X95: 7000 | Y95: =(LISTPROD3[[#This Row],[PRECIO DE VENTA 3]]-LISTPROD3[[#This Row],[COSTO TOTAL UNIDAD]])/LISTPROD3[[#This Row],[COSTO TOTAL UNIDAD]] -> #VALUE! | Z95: =LISTPROD3[[#This Row],[% GANANCIA3]]*LISTPROD3[[#This Row],[COSTO TOTAL UNIDAD]] -> #VALUE! | AC95: 7000 | AD95: 7000 | AE95: 7000 | AF95: 7000 | AG95: nuevos productos 07/03/2025 | AH95: OK
A96: RE01 | B96: RESCATE (Gotas) | C96: 25 ML | D96: HOMEOPATICOS | E96: GOTAS | F96: 25 ML | I96: ANGIE-LHC | J96: ='RECETAS GOTAS'!K26 -> 3672.93 | K96: ='Gtos Varios'!$B$22 -> 3070.5429 | L96: =+LISTPROD3[[#This Row],[TOTAL GASTOS VARIOS]]+LISTPROD3[[#This Row],[PRECIO DE PRODUCCIÓN POR UND]] -> 6743.4729 | M96: ='RECETAS GOTAS'!K29 -> 3421.2277 | N96: ='RECETAS GOTAS'!L29 -> 0.61 | O96: ='RECETAS GOTAS'!K30 -> 9029.7977 | P96: 8000 | Q96: =(LISTPROD3[[#This Row],[PRECIO DE VENTA 1]]-LISTPROD3[[#This Row],[COSTO TOTAL UNIDAD]])/LISTPROD3[[#This Row],[COSTO TOTAL UNIDAD]] -> 0.18633235 | R96: =LISTPROD3[[#This Row],[% GANANCIA]]*LISTPROD3[[#This Row],[COSTO TOTAL UNIDAD]] -> 1256.5271 | T96: 7000 | U96: =(LISTPROD3[[#This Row],[PRECIO DE VENTA2]]-LISTPROD3[[#This Row],[COSTO TOTAL UNIDAD]])/LISTPROD3[[#This Row],[COSTO TOTAL UNIDAD]] -> 0.038040806 | V96: =LISTPROD3[[#This Row],[PRECIO DE VENTA2]]*LISTPROD3[[#This Row],[% GANANCIA2]] -> 266.28564 | W96: =LISTPROD3[[#This Row],[PRECIO DE VENTA2]]-LISTPROD3[[#This Row],[PRECIO VENTA POR RECETA]] -> -2029.7977 | X96: 7000 | Y96: =(LISTPROD3[[#This Row],[PRECIO DE VENTA 3]]-LISTPROD3[[#This Row],[COSTO TOTAL UNIDAD]])/LISTPROD3[[#This Row],[COSTO TOTAL UNIDAD]] -> 0.038040806 | Z96: =LISTPROD3[[#This Row],[% GANANCIA3]]*LISTPROD3[[#This Row],[COSTO TOTAL UNIDAD]] -> 256.52714 | AC96: 8000 | AD96: 7000 | AE96: 7000 | AF96: 7000 | AG96: nuevos productos 28/03/2025 | AH96: OK
A97: SS01 | B97: STRESS (Gotas) | C97: 25 ML | D97: HOMEOPATICOS | E97: GOTAS | F97: 25 ML | I97: ANGIE-LHC | J97: ='RECETAS GOTAS'!Z24 -> 1932.535 | K97: ='Gtos Varios'!$B$22 -> 3070.5429 | L97: =+LISTPROD3[[#This Row],[TOTAL GASTOS VARIOS]]+LISTPROD3[[#This Row],[PRECIO DE PRODUCCIÓN POR UND]] -> 5003.0779 | M97: ='RECETAS GOTAS'!Z29 -> 3363.279 | N97: ='RECETAS GOTAS'!AA29 -> 0.6 | O97: ='RECETAS GOTAS'!Z30 -> 8968.744 | P97: 8000 | Q97: =(LISTPROD3[[#This Row],[PRECIO DE VENTA 1]]-LISTPROD3[[#This Row],[COSTO TOTAL UNIDAD]])/LISTPROD3[[#This Row],[COSTO TOTAL UNIDAD]] -> 0.59901569 | R97: =LISTPROD3[[#This Row],[% GANANCIA]]*LISTPROD3[[#This Row],[COSTO TOTAL UNIDAD]] -> 2996.9221 | T97: 7000 | U97: =(LISTPROD3[[#This Row],[PRECIO DE VENTA2]]-LISTPROD3[[#This Row],[COSTO TOTAL UNIDAD]])/LISTPROD3[[#This Row],[COSTO TOTAL UNIDAD]] -> 0.39913873 | V97: =LISTPROD3[[#This Row],[PRECIO DE VENTA2]]*LISTPROD3[[#This Row],[% GANANCIA2]] -> 2793.9711 | W97: =LISTPROD3[[#This Row],[PRECIO DE VENTA2]]-LISTPROD3[[#This Row],[PRECIO VENTA POR RECETA]] -> -1968.744 | X97: 7000 | Y97: =(LISTPROD3[[#This Row],[PRECIO DE VENTA 3]]-LISTPROD3[[#This Row],[COSTO TOTAL UNIDAD]])/LISTPROD3[[#This Row],[COSTO TOTAL UNIDAD]] -> 0.39913873 | Z97: =LISTPROD3[[#This Row],[% GANANCIA3]]*LISTPROD3[[#This Row],[COSTO TOTAL UNIDAD]] -> 1996.9221 | AC97: 8000 | AD97: 7000 | AE97: 7000 | AF97: 7000 | AG97: nuevos productos 28/03/2025 | AH97: OK
A98: VS01 | B98: VICIOS (Gotas) | C98: 25 ML | D98: HOMEOPATICOS | E98: GOTAS | F98: 25 ML | I98: ANGIE-LHC | J98: ='RECETAS GOTAS'!AO24 -> 1932.535 | K98: ='Gtos Varios'!$B$22 -> 3070.5429 | L98: =+LISTPROD3[[#This Row],[TOTAL GASTOS VARIOS]]+LISTPROD3[[#This Row],[PRECIO DE PRODUCCIÓN POR UND]] -> 5003.0779 | M98: ='RECETAS GOTAS'!AO29 -> 3001.8467 | N98: ='RECETAS GOTAS'!AP29 -> 0.6 | O98: ='RECETAS GOTAS'!AO30 -> 8004.9246 | P98: 8000 | Q98: =(LISTPROD3[[#This Row],[PRECIO DE VENTA 1]]-LISTPROD3[[#This Row],[COSTO TOTAL UNIDAD]])/LISTPROD3[[#This Row],[COSTO TOTAL UNIDAD]] -> 0.59901569 | R98: =LISTPROD3[[#This Row],[% GANANCIA]]*LISTPROD3[[#This Row],[COSTO TOTAL UNIDAD]] -> 2996.9221 | T98: 7000 | U98: =(LISTPROD3[[#This Row],[PRECIO DE VENTA2]]-LISTPROD3[[#This Row],[COSTO TOTAL UNIDAD]])/LISTPROD3[[#This Row],[COSTO TOTAL UNIDAD]] -> 0.39913873 | V98: =LISTPROD3[[#This Row],[PRECIO DE VENTA2]]*LISTPROD3[[#This Row],[% GANANCIA2]] -> 2793.9711 | W98: =LISTPROD3[[#This Row],[PRECIO DE VENTA2]]-LISTPROD3[[#This Row],[PRECIO VENTA POR RECETA]] -> -1004.9246 | X98: 7000 | Y98: =(LISTPROD3[[#This Row],[PRECIO DE VENTA 3]]-LISTPROD3[[#This Row],[COSTO TOTAL UNIDAD]])/LISTPROD3[[#This Row],[COSTO TOTAL UNIDAD]] -> 0.39913873 | Z98: =LISTPROD3[[#This Row],[% GANANCIA3]]*LISTPROD3[[#This Row],[COSTO TOTAL UNIDAD]] -> 1996.9221 | AC98: 8000 | AD98: 7000 | AE98: 7000 | AF98: 7000 | AG98: nuevos productos 28/03/2025 | AH98: OK
A99: AA01 | B99: ALCACHOFA (Capsulas) | C99: ENVASE TIENE 60 CAPSULAS | D99: HOMEOPATICOS | E99: CAPSULAS | F99: CAPSULAS 60 UND | I99: ANGIE-LHC | J99: ='RECETAS CAPS'!AI51 -> 3265.4 | K99: ='Gtos Varios'!$B$22 -> 3070.5429 | L99: =+LISTPROD3[[#This Row],[TOTAL GASTOS VARIOS]]+LISTPROD3[[#This Row],[PRECIO DE PRODUCCIÓN POR UND]] -> 6335.9429 | M99: ='RECETAS CAPS'!AI57 -> 3330.3984 | N99: ='RECETAS CAPS'!AJ57 -> 0.48 | O99: ='RECETAS CAPS'!AI58 -> 10268.728 | P99: 9000 | Q99: =(LISTPROD3[[#This Row],[PRECIO DE VENTA 1]]-LISTPROD3[[#This Row],[COSTO TOTAL UNIDAD]])/LISTPROD3[[#This Row],[COSTO TOTAL UNIDAD]] -> 0.42046736 | R99: =LISTPROD3[[#This Row],[% GANANCIA]]*LISTPROD3[[#This Row],[COSTO TOTAL UNIDAD]] -> 2664.0571 | T99: 7000 | U99: =(LISTPROD3[[#This Row],[PRECIO DE VENTA2]]-LISTPROD3[[#This Row],[COSTO TOTAL UNIDAD]])/LISTPROD3[[#This Row],[COSTO TOTAL UNIDAD]] -> 0.10480794 | V99: =LISTPROD3[[#This Row],[PRECIO DE VENTA2]]*LISTPROD3[[#This Row],[% GANANCIA2]] -> 733.65561 | W99: =LISTPROD3[[#This Row],[PRECIO DE VENTA2]]-LISTPROD3[[#This Row],[PRECIO VENTA POR RECETA]] -> -3268.7284 | X99: 7000 | Y99: =(LISTPROD3[[#This Row],[PRECIO DE VENTA 3]]-LISTPROD3[[#This Row],[COSTO TOTAL UNIDAD]])/LISTPROD3[[#This Row],[COSTO TOTAL UNIDAD]] -> 0.10480794 | Z99: =LISTPROD3[[#This Row],[% GANANCIA3]]*LISTPROD3[[#This Row],[COSTO TOTAL UNIDAD]] -> 664.05714 | AC99: 9000 | AD99: 7000 | AE99: 7000 | AF99: 7000 | AG99: nuevos productos 28/03/2025 | AH99: OK
A100: GG01 | B100: GINGOBILOBA (Capsulas) | C100: ENVASE TIENE 60 CAPSULAS | D100: HOMEOPATICOS | E100: CAPSULAS | F100: CAPSULAS 60 UND | I100: ANGIE-LHC | J100: ='RECETAS CAPS'!AW51 -> 3622.4 | K100: ='Gtos Varios'!$B$22 -> 3070.5429 | L100: =+LISTPROD3[[#This Row],[TOTAL GASTOS VARIOS]]+LISTPROD3[[#This Row],[PRECIO DE PRODUCCIÓN POR UND]] -> 6692.9429 | M100: ='RECETAS CAPS'!AW57 -> 3355.8518 | N100: ='RECETAS CAPS'!AX57 -> 0.46 | O100: ='RECETAS CAPS'!AW58 -> 10651.182 | P100: 9500 | Q100: =(LISTPROD3[[#This Row],[PRECIO DE VENTA 1]]-LISTPROD3[[#This Row],[COSTO TOTAL UNIDAD]])/LISTPROD3[[#This Row],[COSTO TOTAL UNIDAD]] -> 0.41940551 | R100: =LISTPROD3[[#This Row],[% GANANCIA]]*LISTPROD3[[#This Row],[COSTO TOTAL UNIDAD]] -> 2807.0571 | T100: 7000 | U100: =(LISTPROD3[[#This Row],[PRECIO DE VENTA2]]-LISTPROD3[[#This Row],[COSTO TOTAL UNIDAD]])/LISTPROD3[[#This Row],[COSTO TOTAL UNIDAD]] -> 0.045877748 | V100: =LISTPROD3[[#This Row],[PRECIO DE VENTA2]]*LISTPROD3[[#This Row],[% GANANCIA2]] -> 321.14423 | W100: =LISTPROD3[[#This Row],[PRECIO DE VENTA2]]-LISTPROD3[[#This Row],[PRECIO VENTA POR RECETA]] -> -3651.1818 | X100: 7000 | Y100: =(LISTPROD3[[#This Row],[PRECIO DE VENTA 3]]-LISTPROD3[[#This Row],[COSTO TOTAL UNIDAD]])/LISTPROD3[[#This Row],[COSTO TOTAL UNIDAD]] -> 0.045877748 | Z100: =LISTPROD3[[#This Row],[% GANANCIA3]]*LISTPROD3[[#This Row],[COSTO TOTAL UNIDAD]] -> 307.05714 | AC100: 9500 | AD100: 7000 | AE100: 7000 | AF100: 7000 | AG100: nuevos productos 28/03/2025 | AH100: OK
...

Sheet Recetas x Prod
A1: NOTA:TODO LO QUE SEA LITRO SE MANEJA EL PROMEDIO DE LA PAPA
A8: CODIGO | B8: 7T01 | G8: CODIGO | H8: AM01 | L8: CODIGO | M8: CA01 | R8: CODIGO | S8: AV01 | V8: CODIGO | W8: DZ01 | Z8: CODIGO | AA8: GM01 | AD8: CODIGO | AE8: PS01 | AH8: CODIGO | AI8: VC01 | AL8: CODIGO | AR8: CODIGO | AT8: RE01 | AY8: CODIGO | BA8: SS01 | BE8: CODIGO | BG8: CA02
A9: PRODUCTO | B9: =VLOOKUP(B8,LISTPROD[],2,FALSE) -> 7 TOROS | G9: PRODUCTO | H9: =VLOOKUP(H8,LISTPROD[],2,FALSE) -> ALICITRIM LT | L9: PRODUCTO | M9: =VLOOKUP(M8,LISTPROD[],2,FALSE) -> CATUAMA (Capsulas) | R9: PRODUCTO | S9: =VLOOKUP(S8,LISTPROD[],2,FALSE) -> ARTERIO VENOSO | V9: PRODUCTO | W9: =VLOOKUP(W8,LISTPROD[],2,FALSE) -> DIABETIZAN | Z9: PRODUCTO | AA9: =VLOOKUP(AA8,LISTPROD[],2,FALSE) -> GREEN MARVIN (Ungüento) | AD9: PRODUCTO | AE9: =VLOOKUP(AE8,LISTPROD[],2,FALSE) -> PAPA SILVESTRE POLVO (500 gr) | AH9: PRODUCTO | AI9: =VLOOKUP(AI8,LISTPROD[],2,FALSE) -> VINO CEREBRAL | AL9: PRODUCTO | AM9: =VLOOKUP(AM8,LISTPROD[],2,FALSE) -> #N/A | AR9: PRODUCTO | AT9: =VLOOKUP(AT8,LISTPROD[],2,FALSE) -> RESCATE (Gotas) | AY9: PRODUCTO | BA9: =VLOOKUP(BA8,LISTPROD[],2,FALSE) -> STRESS (Gotas) | BE9: PRODUCTO | BG9: =VLOOKUP(BG8,LISTPROD[],2,FALSE) -> CALENDULA (Capsulas)
A10: ALMACEN | B10: =VLOOKUP(B8,LISTPROD[],3,FALSE) -> 7TRS | G10: ALMACEN | H10: =VLOOKUP(H8,LISTPROD[],3,FALSE) -> ALICITRIN CIRCULATORIO | L10: ALMACEN | M10: =VLOOKUP(M8,LISTPROD[],3,FALSE) -> CATUAMA | R10: ALMACEN | S10: =VLOOKUP(S8,LISTPROD[],3,FALSE) -> ARTERIO VENOSO | V10: ALMACEN | W10: =VLOOKUP(W8,LISTPROD[],3,FALSE) -> DIABETIZAN | Z10: ALMACEN | AA10: =VLOOKUP(AA8,LISTPROD[],3,FALSE) -> GREEN MARVIN (Ungüento) | AD10: ALMACEN | AE10: =VLOOKUP(AE8,LISTPROD[],3,FALSE) -> PAPA SILVESTRE POLVO (500 gr) | AH10: ALMACEN | AI10: =VLOOKUP(AI8,LISTPROD[],3,FALSE) -> VINO CEREBRAL | AL10: ALMACEN | AM10: =VLOOKUP(AM8,LISTPROD[],3,FALSE) -> #N/A | AR10: ALMACEN | AT10: =VLOOKUP(AT8,LISTPROD[],3,FALSE) -> RESCATE Gotas Orales | AY10: ALMACEN | BA10: =VLOOKUP(BA8,LISTPROD[],3,FALSE) -> STRESS Gotas Orales | BE10: ALMACEN | BG10: =VLOOKUP(BG8,LISTPROD[],3,FALSE) -> CALENDULA
A11: Total Cantidad Envasada | B11: 390 | G11: Total Cantidad Envasada | L11: Total Cantidad Envasada | R11: Total Cantidad Envasada | V11: Total Cantidad Envasada | Z11: Total Cantidad Envasada | AD11: Total Cantidad Envasada | AH11: Total Cantidad Envasada | AL11: Total Cantidad Envasada | AR11: Total Cantidad Envasada | AT11: 158 | AY11: Total Cantidad Envasada | BE11: Total Cantidad Envasada | BG11: 140
A12: Cantidad Unitaria | G12: Cantidad Unitaria | L12: Cantidad Unitaria | R12: Cantidad Unitaria | V12: Cantidad Unitaria | Z12: Cantidad Unitaria | AD12: Cantidad Unitaria | AH12: Cantidad Unitaria | AL12: Cantidad Unitaria | AR12: Cantidad Unitaria | AY12: Cantidad Unitaria | BE12: Cantidad Unitaria
A13: Presentación | B13: 500 ml | G13: Presentación | L13: Presentación | R13: Presentación | V13: Presentación | Z13: Presentación | AD13: Presentación | AH13: Presentación | AL13: Presentación | AR13: Presentación | AY13: Presentación | BE13: Presentación
A14: INGREDIENTES | B14: CANT | C14: GRAMOs/mL | G14: INGREDIENTES | H14: CANT | I14: GRAMOs/mL | L14: INGREDIENTES | M14: CANT | N14: GRAMOs/mL | R14: INGREDIENTES | S14: CANT | T14: GRAMOs/mL | V14: INGREDIENTES | W14: CANT | X14: GRAMOs/mL | Z14: INGREDIENTES | AA14: CANT | AB14: GRAMOs/mL | AD14: INGREDIENTES | AE14: CANT | AF14: GRAMOs/mL | AH14: INGREDIENTES | AI14: CANT | AJ14: GRAMOs/mL | AL14: INGREDIENTES | AM14: CANT | AN14: GRAMOs/mL | AR14: INGREDIENTES | AS14: CLASIFICACION | AT14: CANT | AU14: GRAMOs/mL | AV14: Cant x UNID | AY14: INGREDIENTES | AZ14: CLASIFICACION | BA14: CANT | BB14: GRAMOs/mL | BE14: INGREDIENTES | BF14: CLASIFICACION | BG14: CANT | BH14: GRAMOs/mL | BI14: Cant x UNID
A15: SULFATO FERROSO | B15: 1000 | C15: GR | G15: BENZODATO | H15: 600 | I15: GR | R15: BENZODATO | S15: 600 | V15: BENZODATO | W15: 600 | Z15: VASELINA | AA15: 5000 | AH15: BENZODATO | AI15: 600 | AR15: Dilución Floral de Impaciencia | AS15: INSUMO | AT15: ML | AU15: 1.5 | AV15: =AU15/$AT$11 -> 0.0094936709 | AY15: Dilución Floral de Oimo | AZ15: INSUMO | BA15: 1 | BB15: ML | BE15: PASTILLERO 180(38) PE BLANCO | BF15: EMPAQUE | BG15: UND | BH15: 140 | BI15: =BH15/$AT$192 -> 1
A16: BENZODATO | B16: 600 | C16: GR | G16: ACIDO CITRICO | H16: 500 | I16: GR | R16: CITRATO DE SODIO | S16: 200 | V16: CITRATO DE SODIO | W16: 200 | Z16: PARAFINA | AA16: 200 | AH16: CITRATO DE SODIO | AI16: 200 | AR16: Dilución Floral de Estrella de belén | AS16: INSUMO | AT16: ML | AU16: 1.5 | AV16: =AU16/$AT$11 -> 0.0094936709 | AY16: Dilución Floral de Estrella de belén | AZ16: INSUMO | BA16: 1 | BB16: ML | BE16: CALENDULA | BF16: INSUMO | BG16: GR | BH16: 4200 | BI16: =BH16/$AT$192 -> 30
A17: ACIDO CITRICO | B17: 300 | C17: GR | G17: CITRATO DE SODIO | H17: 200 | I17: GR | R17: ACIDO CITRICO | S17: 1000 | V17: ACIDO CITRICO | W17: 1000 | Z17: SALICILATO | AA17: 3000 | AH17: SABOR-NARANJA | AI17: 100 | AR17: Dilución Floral de Heliantemo | AS17: INSUMO | AT17: ML | AU17: 1.5 | AV17: =AU17/$AT$11 -> 0.0094936709 | AY17: Dilución Floral de Centaura | AZ17: INSUMO | BA17: 1 | BB17: ML | BE17: CAPSULAS | BF17: INSUMO | BG17: UND | BH17: 8400 | BI17: =BH17/$AT$192 -> 60
A18: COMPONENTE | B18: 150 | C18: GR | G18: GOMA XANTAN | H18: 900 | I18: GR | R18: GOMA XANTAN | S18: 800 | V18: ENDULZANTE | W18: 100 | Z18: MENTOL | AA18: 300 | AH18: SULFATO FERROSO | AI18: 1000 | AR18: Dilución Floral de Cerasifera | AS18: INSUMO | AT18: ML | AU18: 1.5 | AV18: =AU18/$AT$11 -> 0.0094936709 | AY18: Dilución Floral de Castaño blanco | AZ18: INSUMO | BA18: 1 | BB18: ML | BE18: TAPA 38 PD ENSAMBLADA PE VERDE | BF18: EMPAQUE | BG18: UND | BH18: 140 | BI18: =BH18/$AT$192 -> 1
A19: GOMA XANTAN | B19: 700 | C19: GR | G19: SABOR-NARANJA | H19: 100 | I19: GR | R19: SABOR-NARANJA | S19: 100 | V19: COLOR-PARDO | W19: 22 | Z19: COLOR-VERDE GRASA | AA19: 1 | AH19: GOMA XANTAN | AI19: 800 | AR19: Dilución Floral de Clemátide | AS19: INSUMO | AT19: ML | AU19: 1.5 | AV19: =AU19/$AT$11 -> 0.0094936709 | AY19: Dilución Floral de Ceratostigma | AZ19: INSUMO | BA19: 1 | BB19: ML | BE19: LINER DE TROQUEL 38 MM PS | BF19: EMPAQUE | BG19: UND | BH19: 140 | BI19: =BH19/$AT$192 -> 1
A20: COLOR-CARAMELO | B20: 100 | C20: GR | G20: COLOR-PARDO | H20: 20 | I20: GR | R20: SULFATO FERROSO | S20: 300 | V20: SABOR-MANGO | W20: 100 | AH20: ACIDO CITRICO | AI20: 300 | AR20: Alcohol al 96 % | AS20: INSUMO | AT20: ML | AU20: 600 | AV20: =AU20/$AT$11 -> 3.7974684 | AY20: Alcohol al 96 % | AZ20: INSUMO | BA20: 450 | BB20: ML | BE20: ETIQUETA | BF20: EMPAQUE | BG20: UND | BH20: 140 | BI20: =BH20/$AT$192 -> 1
A21: COLOR-PARDO | B21: 60 | C21: GR | G21: KIT DE PLANTAS | R21: COLOR-PARDO | S21: 60 | V21: KIT DE PLANTAS | AH21: COLOR-PARDO | AI21: 60 | AR21: Agua purificada | AS21: INSUMO | AT21: ML | AU21: 3100 | AV21: =AU21/$AT$11 -> 19.620253 | AY21: Agua purificada | AZ21: INSUMO | BA21: 2045 | BB21: ML | BE21: TERMOENCOGIBLE | BF21: EMPAQUE | BG21: UND | BH21: 140 | BI21: =BH21/$AT$192 -> 1
A22: CITRATO DE SODIO | B22: 200 | C22: GR | R22: KIT DE PLANTAS | AH22: ENDULZANTE | AI22: 100 | AR22: Frasco Ámbar 25 mL Boca 18 mm | AS22: EMPAQUE | AT22: UND | AU22: 158 | AY22: Frasco Ámbar 25 mL Boca 18 mm | AZ22: EMPAQUE | BB22: UND
A23: ENDULZANTE | B23: 200 | C23: GR | AH23: KIT DE PLANTAS | AR23: Perilla gotero Negra -Tapa negra con Pipeta dosificadora en vidrio . Boca 18 mm | AS23: EMPAQUE | AT23: UND | AU23: 158 | AY23: Perilla gotero Negra -Tapa negra con Pipeta dosificadora en vidrio . Boca 18 mm | AZ23: EMPAQUE | BB23: UND
A24: SABOR-FRESA | B24: 100 | C24: GR | AR24: Etiqueta | AS24: EMPAQUE | AT24: UND | AU24: 158 | AY24: Etiqueta | AZ24: EMPAQUE | BB24: UND
A25: KIT DE PLANTAS | AR25: Plegadiza | AS25: EMPAQUE | AT25: UND | AU25: 158 | AY25: Plegadiza | AZ25: EMPAQUE | BB25: UND
AR26: Banda de seguridad | AS26: EMPAQUE | AT26: UND | AU26: 158 | AY26: Banda de seguridad | AZ26: EMPAQUE | BB26: UND
A33: CODIGO | B33: AN01 | G33: CODIGO | H33: CO01 | L33: CODIGO | M33: PB01 | R33: CODIGO | S33: A01 | V33: CODIGO | W33: DU01 | Z33: CODIGO | AA33: IM01 | AD33: CODIGO | AE33: PF01 | AH33: CODIGO | AI33: VP01 | AL33: CODIGO | AR33: CODIGO | AT33: VS01 | AY33: CODIGO | BA33: AA01
A34: PRODUCTO | B34: =VLOOKUP(B33,LISTPROD[],2,FALSE) -> ARBRON | G34: PRODUCTO | H34: =VLOOKUP(H33,LISTPROD[],2,FALSE) -> CALCUBANO LT | L34: PRODUCTO | M34: =VLOOKUP(M33,LISTPROD[],2,FALSE) -> PROSTABELL | R34: PRODUCTO | S34: =VLOOKUP(S33,LISTPROD[],2,FALSE) -> ARTRIN | V34: PRODUCTO | W34: =VLOOKUP(W33,LISTPROD[],2,FALSE) -> DOLORAN ULTRA (pastillas) y Spray | Z34: PRODUCTO | AA34: =VLOOKUP(AA33,LISTPROD[],2,FALSE) -> INFAMOL-JARABE 500 ML | AD34: PRODUCTO | AE34: =VLOOKUP(AE33,LISTPROD[],2,FALSE) -> POTENFULL | AH34: PRODUCTO | AI34: =VLOOKUP(AI33,LISTPROD[],2,FALSE) -> VISION PLUS (Gotas) | AL34: PRODUCTO | AM34: =VLOOKUP(AM33,LISTPROD[],2,FALSE) -> #N/A | AR34: PRODUCTO | AT34: =VLOOKUP(AT33,LISTPROD[],2,FALSE) -> VICIOS (Gotas) | AY34: PRODUCTO | BA34: =VLOOKUP(BA33,LISTPROD[],2,FALSE) -> ALCACHOFA (Capsulas)
A35: ALMACEN | B35: =VLOOKUP(B33,LISTPROD[],3,FALSE) -> ARBRON | G35: ALMACEN | H35: =VLOOKUP(H33,LISTPROD[],3,FALSE) -> CALCUBANO | L35: ALMACEN | M35: =VLOOKUP(M33,LISTPROD[],3,FALSE) -> SAW PALMETTO-Esencia FLoral 500 ml | R35: ALMACEN | S35: =VLOOKUP(S33,LISTPROD[],3,FALSE) -> ARTRIN | V35: ALMACEN | W35: =VLOOKUP(W33,LISTPROD[],3,FALSE) -> DOLORAN ULTRA (pastillas) y Spray | Z35: ALMACEN | AA35: =VLOOKUP(AA33,LISTPROD[],3,FALSE) -> INFAMOL-JARABE 500 ML | AD35: ALMACEN | AE35: =VLOOKUP(AE33,LISTPROD[],3,FALSE) -> POTENFULL | AH35: ALMACEN | AI35: =VLOOKUP(AI33,LISTPROD[],3,FALSE) -> VISION PLUS (Gotas) | AL35: ALMACEN | AM35: =VLOOKUP(AM33,LISTPROD[],3,FALSE) -> #N/A | AR35: ALMACEN | AT35: =VLOOKUP(AT33,LISTPROD[],3,FALSE) -> VICIOS Gotas Orales | AY35: ALMACEN | BA35: =VLOOKUP(BA33,LISTPROD[],3,FALSE) -> ALCACHOFA
A36: Total Cantidad Envasada | G36: Total Cantidad Envasada | L36: Total Cantidad Envasada | R36: Total Cantidad Envasada | V36: Total Cantidad Envasada | Z36: Total Cantidad Envasada | AD36: Total Cantidad Envasada | AH36: Total Cantidad Envasada | AL36: Total Cantidad Envasada | AR36: Total Cantidad Envasada | AY36: Total Cantidad Envasada
A37: Cantidad Unitaria | G37: Cantidad Unitaria | L37: Cantidad Unitaria | R37: Cantidad Unitaria | V37: Cantidad Unitaria | Z37: Cantidad Unitaria | AD37: Cantidad Unitaria | AH37: Cantidad Unitaria | AL37: Cantidad Unitaria | AR37: Cantidad Unitaria | AY37: Cantidad Unitaria
A38: Presentación | G38: Presentación | L38: Presentación | R38: Presentación | V38: Presentación | Z38: Presentación | AD38: Presentación | AH38: Presentación | AL38: Presentación | AR38: Presentación | AY38: Presentación
A39: INGREDIENTES | B39: CANT | C39: GRAMOs/mL | G39: INGREDIENTES | H39: CANT | I39: GRAMOs/mL | L39: INGREDIENTES | M39: CANT | N39: GRAMOs/mL | R39: INGREDIENTES | S39: CANT | T39: GRAMOs/mL | V39: INGREDIENTES | W39: CANT | X39: GRAMOs/mL | Z39: INGREDIENTES | AA39: CANT | AB39: GRAMOs/mL | AD39: INGREDIENTES | AE39: CANT | AF39: GRAMOs/mL | AH39: INGREDIENTES | AI39: CANT | AJ39: GRAMOs/mL | AL39: INGREDIENTES | AM39: CANT | AN39: GRAMOs/mL | AR39: INGREDIENTES | AT39: CANT | AU39: GRAMOs/mL | AY39: INGREDIENTES | BA39: CANT | BB39: GRAMOs/mL
A40: BENZODATO | B40: 600 | G40: CLORURO DE MAGNESIO | H40: 7000 | L40: BENZODATO | M40: 600 | R40: PASTA BLANCA | S40: 1100 (TABLETA) | AD40: GOMA XANTAN | AE40: 700 | AH40: AGUA DESTILADA | AR40: Dilución Floral de Cerasifera | AT40: 1 | AU40: ML | AY40: Dilución Floral de Nogal | BA40: 1 | BB40: ML
A41: ACIDO CITRICO | B41: 600 | G41: CITATO DE SODIO | H41: 300 | L41: CITATO DE SODIO | M41: 200 | R41: CAJA ARTRIN | S41: 550 UND | AD41: BENZODATO | AE41: 600 | AH41: CLORURO DE SODIO | AI41: 150
A42: ENDULZANTE | B42: 50 | G42: BENZODATO | H42: 600 | L42: ACIDO CITRICO | M42: 1000 | AD42: ACIDO CITRICO | AE42: 1000 | AH42: CLOR-ROJO | AI42: 1
A43: CITRATO DE SODIO | B43: 200 | G43: SABOR-NARANJA | H43: 200 | L43: ENDULZANTE | M43: 150 | AD43: ENDULZANTE | AE43: 250
A44: SABOR DURAZNO | B44: 100 | G44: GOMA XANTAN | H44: 700 | L44: GOMA XANTAN | M44: 900 | AD44: SABOR-TROPICAL | AE44: 600
A45: COLOR-PARDO | B45: 20 | G45: COLOR-PARDO | H45: 40 | L45: COLOR-PARDO | M45: 20 | AD45: COMPONENTE T | AE45: 150
A46: GOMA XANTAN | B46: 800 | G46: KIT DE PLANTAS | L46: SABOR-NARNAJA | M46: 100 | AD46: EMULSION TROPICAL | AE46: 500
A47: KIT DE PLANTAS | L47: KIT DE PLANTAS | AD47: ENTURBIANTE | AE47: 500
AD48: KIT DE PLANTAS
A62: CODIGO | B62: BP01 | G62: CODIGO | H62: CM01 | L62: CODIGO | M62: PT01 | R62: CODIGO | S62: B01 | V62: CODIGO | W62: E01 | Z62: CODIGO | AD62: CODIGO | AE62: PG01 | AH62: CODIGO | AI62: VCF01 | AL62: CODIGO | AR62: CODIGO | AT62: GG01 | AY62: CODIGO | BA62: IN01
A63: PRODUCTO | B63: =VLOOKUP(B62,LISTPROD[],2,FALSE) -> BIL PRO | G63: PRODUCTO | H63: =VLOOKUP(H62,LISTPROD[],2,FALSE) -> CARDO MARIANO (Capsulas) | L63: PRODUCTO | M63: =VLOOKUP(M62,LISTPROD[],2,FALSE) -> PROX TAP LT | R63: PRODUCTO | S63: =VLOOKUP(S62,LISTPROD[],2,FALSE) -> BIO 44 | V63: PRODUCTO | W63: =VLOOKUP(W62,LISTPROD[],2,FALSE) -> ELIXIR (Gotas) | Z63: PRODUCTO | AA63: INFAMOL SPRAY | AD63: PRODUCTO | AE63: =VLOOKUP(AE62,LISTPROD[],2,FALSE) -> PPG | AH63: PRODUCTO | AI63: =VLOOKUP(AI62,LISTPROD[],2,FALSE) -> VITA CEREBRINA FRANCESA | AL63: PRODUCTO | AM63: =VLOOKUP(AM62,LISTPROD[],2,FALSE) -> #N/A | AR63: PRODUCTO | AT63: =VLOOKUP(AT62,LISTPROD[],2,FALSE) -> GINGOBILOBA (Capsulas) | AY63: PRODUCTO | BA63: =VLOOKUP(BA62,LISTPROD[],2,FALSE) -> INSOMNIO (Gotas)
A64: ALMACEN | B64: =VLOOKUP(B62,LISTPROD[],3,FALSE) -> BRIL-PRO | G64: ALMACEN | H64: =VLOOKUP(H62,LISTPROD[],3,FALSE) -> CARDO MARIANO (Capsulas) | L64: ALMACEN | M64: =VLOOKUP(M62,LISTPROD[],3,FALSE) -> PROX - TAP | R64: ALMACEN | S64: =VLOOKUP(S62,LISTPROD[],3,FALSE) -> BIO 44 | V64: ALMACEN | W64: =VLOOKUP(W62,LISTPROD[],3,FALSE) -> ELIXIR (Gotas) | Z64: ALMACEN | AA64: LUIS-FARMACIA NATIVA | AD64: ALMACEN | AE64: =VLOOKUP(AE62,LISTPROD[],3,FALSE) -> PPG | AH64: ALMACEN | AI64: =VLOOKUP(AI62,LISTPROD[],3,FALSE) -> VITA CEREBRINA FRANCESA | AL64: ALMACEN | AM64: =VLOOKUP(AM62,LISTPROD[],3,FALSE) -> #N/A | AR64: ALMACEN | AT64: =VLOOKUP(AT62,LISTPROD[],3,FALSE) -> GINKGO BILOBA | AY64: ALMACEN | BA64: =VLOOKUP(BA62,LISTPROD[],3,FALSE) -> INSOMNIO Gotas Orales
A65: Total Cantidad Envasada | G65: Total Cantidad Envasada | L65: Total Cantidad Envasada | R65: Total Cantidad Envasada | V65: Total Cantidad Envasada | Z65: Total Cantidad Envasada | AD65: Total Cantidad Envasada | AH65: Total Cantidad Envasada | AL65: Total Cantidad Envasada | AR65: Total Cantidad Envasada | AY65: Total Cantidad Envasada
A66: Cantidad Unitaria | G66: Cantidad Unitaria | L66: Cantidad Unitaria | R66: Cantidad Unitaria | V66: Cantidad Unitaria | Z66: Cantidad Unitaria | AD66: Cantidad Unitaria | AH66: Cantidad Unitaria | AL66: Cantidad Unitaria | AR66: Cantidad Unitaria | AY66: Cantidad Unitaria
A67: Presentación | G67: Presentación | L67: Presentación | R67: Presentación | V67: Presentación | Z67: Presentación | AD67: Presentación | AH67: Presentación | AL67: Presentación | AR67: Presentación | AY67: Presentación
A68: INGREDIENTES | B68: CANT | C68: GRAMOs/mL | G68: INGREDIENTES | H68: CANT | I68: GRAMOs/mL | L68: INGREDIENTES | M68: CANT | N68: GRAMOs/mL | R68: INGREDIENTES | S68: CANT | T68: GRAMOs/mL | V68: INGREDIENTES | W68: CANT | X68: GRAMOs/mL | Z68: INGREDIENTES | AA68: CANT | AB68: GRAMOs/mL | AD68: INGREDIENTES | AE68: CANT | AF68: GRAMOs/mL | AH68: INGREDIENTES | AI68: CANT | AJ68: GRAMOs/mL | AL68: INGREDIENTES | AM68: GRAMOs/mL | AR68: INGREDIENTES | AT68: CANT | AU68: GRAMOs/mL | AY68: INGREDIENTES | AZ68: CLASIFICACION | BA68: CANT | BB68: GRAMOs/mL
A69: CLORURO DE MAGNESIO | B69: 7000 | L69: BENZODATO | M69: 600 | V69: BENZODATO | W69: 90 | Z69: ALCOHOL | AA69: 5000 | AD69: CLORURO DE MAGNESIO | AE69: 4500 | AH69: BENZODATO | AI69: 600 | AY69: Dilución Floral de Nogal | AZ69: INSUMO | BA69: 1.55 | BB69: ML
A70: CITRATO DE SODIO | B70: 756 | L70: CITRATO DE SODIO | M70: 200 | V70: ACIDO CITRICO | W70: 25 | Z70: SALICITLATO | AA70: 1500 | AD70: CITRATO DE SODIO | AE70: 290 | AH70: CITRATO DE SODIO | AI70: 200 | AY70: Dilución Floral de Agrimonia | AZ70: INSUMO | BA70: 1.55 | BB70: ML
A71: BENZODATO | B71: 408 | L71: ACIDO CITRICO | M71: 1000 | V71: CITRATO DE SODIO | W71: 25 | Z71: COLOR-ROJO | AA71: 1 | AD71: BENZODATO | AE71: 300 | AH71: SABOR-NARANJA | AI71: 100 | AY71: Dilución Floral de Centaura | AZ71: INSUMO | BA71: 1.55 | BB71: ML
A72: SABOR-GUANABANA | B72: 116 | L72: ENDULZANTE | M72: 150 | V72: COLOR-PARDO | W72: 12 | AD72: COLOR-AMARILLO | AE72: 50 | AH72: SULFATO FERROSO | AI72: 1000 | AY72: Dilución Floral de Impaciencia | AZ72: INSUMO | BA72: 1.55 | BB72: ML
A73: GOMA XANTAN | B73: 708 | L73: GOMA XANTAN | M73: 900 | V73: SABOR-CARAMELO | W73: 7 | AD73: SABOR DURAZNO | AE73: 84 | AH73: GOMA XANTAN | AI73: 800 | AY73: Alcohol al 96 % | AZ73: INSUMO | BA73: 697.5 | BB73: ML
A74: COLOR-BLANCO | B74: 68 | L74: COLOR-PARDO | M74: 20 | V74: KIT DE PLANTAS | AH74: ENDULZANTE | AI74: 100 | AY74: Agua purificada | AZ74: INSUMO | BA74: 3171.3 | BB74: ML
A75: KIT DE PLANTAS | L75: SABOR-NARANJA | M75: 100 | AH75: ACIDO CITRICO | AI75: 300 | AY75: Frasco Ámbar 25 mL Boca 18 mm | AZ75: EMPAQUE | BB75: UND
L76: KIT DE PLANTAS | AH76: COLOR-PARDO | AI76: 40 | AY76: Perilla gotero Negra -Tapa negra con Pipeta dosificadora en vidrio . Boca 18 mm | AZ76: EMPAQUE | BB76: UND
AH77: COLOR-ROJO | AI77: 20 | AY77: Etiqueta | AZ77: EMPAQUE | BB77: UND
AH78: KIT DE PLANTAS | AY78: Plegadiza | AZ78: EMPAQUE | BB78: UND
AY79: Banda de seguridad | AZ79: EMPAQUE | BB79: UND
Z82: CODIGO | AA82: IP01
Z83: PRODUCTO | AA83: =VLOOKUP(AA82,LISTPROD[],2,FALSE) -> INFAMOL PASTAS (lleva Spray)
A87: CODIGO | B87: CL01 | G87: CODIGO | H87: CV01 | L87: CODIGO | M87: RO01 | R87: CODIGO | S87: BO01 | V87: CODIGO | W87: EDM01 | Z87: ALMACEN | AA87: =VLOOKUP(AA82,LISTPROD[],3,FALSE) -> INFAMOL PASTAS (lleva Spray) | AD87: CODIGO | AE87: PP01 | AH87: CODIGO | AI87: WN01 | AL87: CODIGO | AR87: CODIGO | AT87: EB01 | AY87: CODIGO | BA87: PA01
A88: PRODUCTO | B88: =VLOOKUP(B87,LISTPROD[],2,FALSE) -> CIR LAN (500ml) | G88: PRODUCTO | H88: =VLOOKUP(H87,LISTPROD[],2,FALSE) -> CIRCULAV LT | L88: PRODUCTO | M88: =VLOOKUP(M87,LISTPROD[],2,FALSE) -> REUMAT OFF LT | R88: PRODUCTO | S88: =VLOOKUP(S87,LISTPROD[],2,FALSE) -> BOTANPROS | V88: PRODUCTO | W88: =VLOOKUP(W87,LISTPROD[],2,FALSE) -> ENFERMEDADES DE LA MUJER | Z88: Total Cantidad Envasada | AD88: PRODUCTO | AE88: =VLOOKUP(AE87,LISTPROD[],2,FALSE) -> PROSTA PHARMA | AH88: PRODUCTO | AI88: =VLOOKUP(AI87,LISTPROD[],2,FALSE) -> WILTRON | AL88: PRODUCTO | AM88: =VLOOKUP(AM87,LISTPROD[],2,FALSE) -> #N/A | AR88: PRODUCTO | AT88: =VLOOKUP(AT87,LISTPROD[],2,FALSE) -> ESTRELLA DE BELEN (Gotas) | AY88: PRODUCTO | BA88: =VLOOKUP(BA87,LISTPROD[],2,FALSE) -> PASSIFLORA (Gotas)
A89: ALMACEN | B89: =VLOOKUP(B87,LISTPROD[],3,FALSE) -> CIR/LAN | G89: ALMACEN | H89: =VLOOKUP(H87,LISTPROD[],3,FALSE) -> CIRCULAV PLUS | L89: ALMACEN | M89: =VLOOKUP(M87,LISTPROD[],3,FALSE) -> REUMAT - OFF | R89: ALMACEN | S89: =VLOOKUP(S87,LISTPROD[],3,FALSE) -> BOTANPROS | V89: ALMACEN | W89: =VLOOKUP(W87,LISTPROD[],3,FALSE) -> ENFERMEDADES DE LA MUJER | Z89: Cantidad Unitaria | AD89: ALMACEN | AE89: =VLOOKUP(AE87,LISTPROD[],3,FALSE) -> PROSTA PHARMA | AH89: ALMACEN | AI89: =VLOOKUP(AI87,LISTPROD[],3,FALSE) -> WILTRON | AL89: ALMACEN | AM89: =VLOOKUP(AM87,LISTPROD[],3,FALSE) -> #N/A | AR89: ALMACEN | AT89: =VLOOKUP(AT87,LISTPROD[],3,FALSE) -> ESTRELLA DE BELEN Gotas Orales | AY89: ALMACEN | BA89: =VLOOKUP(BA87,LISTPROD[],3,FALSE) -> PASSIFLORA Gotas Orales
A90: Total Cantidad Envasada | G90: Total Cantidad Envasada | L90: Total Cantidad Envasada | R90: Total Cantidad Envasada | V90: Total Cantidad Envasada | Z90: Presentación | AD90: Total Cantidad Envasada | AH90: Total Cantidad Envasada | AL90: Total Cantidad Envasada | AR90: Total Cantidad Envasada | AY90: Total Cantidad Envasada
A91: Cantidad Unitaria | G91: Cantidad Unitaria | L91: Cantidad Unitaria | R91: Cantidad Unitaria | V91: Cantidad Unitaria | Z91: INGREDIENTES | AA91: CANT | AB91: GRAMOs/mL | AD91: Cantidad Unitaria | AH91: Cantidad Unitaria | AL91: Cantidad Unitaria | AR91: Cantidad Unitaria | AY91: Cantidad Unitaria
A92: Presentación | G92: Presentación | L92: Presentación | R92: Presentación | V92: Presentación | AD92: Presentación | AH92: Presentación | AL92: Presentación | AR92: Presentación | AY92: Presentación
A93: INGREDIENTES | B93: CANT | C93: GRAMOs/mL | G93: INGREDIENTES | H93: CANT | I93: GRAMOs/mL | L93: INGREDIENTES | M93: CANT | N93: GRAMOs/mL | R93: INGREDIENTES | S93: CANT | T93: GRAMOs/mL | V93: INGREDIENTES | W93: CANT | X93: GRAMOs/mL | AD93: INGREDIENTES | AE93: CANT | AF93: GRAMOs/mL | AH93: INGREDIENTES | AI93: CANT | AJ93: GRAMOs/mL | AL93: INGREDIENTES | AM93: GRAMOs/mL | AR93: INGREDIENTES | AT93: CANT | AU93: GRAMOs/mL | AY93: INGREDIENTES | BA93: CANT | BB93: GRAMOs/mL
A94: BENZODATO | B94: 600 | G94: BENZODATO | H94: 600 | L94: CLORURO DE MAGNESIO | M94: 7000 | R94: BENZODATO | S94: 600 | V94: BENZODATO | W94: 600 | AD94: BENZODATO | AE94: 600 | AH94: BENZODATO | AI94: 600
A95: ACIDO CITRICO | B95: 500 | G95: ACIDO CITRICO | H95: 550 | L95: CITRATO DE SODIO | M95: 300 | R95: ACIDO CITRICO | S95: 500 | V95: CITRATO DE SODIO | W95: 200 | AD95: CITRATO DE SODIO | AE95: 200 | AH95: CITRATO DE SODIO | AI95: 200
A96: CITRATO DE SODIO | B96: 200 | G96: CITRATO DE SODIO | H96: 200 | L96: BENZODATO | M96: 400 | R96: CITRATO DE SODIO | S96: 200 | V96: ACIDO CITRICO | W96: 300 | AD96: ACIDO CITRICO | AE96: 1000 | AH96: ACIDO CITRICO | AI96: 1000
A97: SABOR-LIMON | B97: 200 | G97: GOMA XANTAN | H97: 900 | L97: SABOR-NARANJA | M97: 200 | R97: GOMA XANTAN | S97: 900 | V97: ENDULZANTE | W97: 150 | AD97: ENDULZANTE | AE97: 150 | AH97: SULFATO FERROSO | AI97: 1000
A98: COLOR-PARDO | B98: 38 | G98: SABOR-NARANJA | H98: 100 | L98: GOMA XANTAN | M98: 700 | R98: SABOR-DURAZNO | S98: 100 | V98: GOMA XANTAN | W98: 900 | AD98: GOMA XANTAN | AE98: 900 | AH98: GOMA XANTAN | AI98: 800
A99: GOMA XANTAN | B99: 800 | G99: COLOR-PARDO | H99: 25 | L99: COLOR-PARDO | M99: 68 | R99: COLOR-PARDO | S99: 20 | V99: COLOR-ROJO | W99: 20 | AD99: COLOR-PARDO | AE99: 20 | AH99: SABOR-NARANJA | AI99: 100
A100: KIT PLANTAS | L100: KIT PLANTAS | R100: KIT DE PLANTAS | V100: SABOR-FRESA | W100: 400 | AD100: SABOR-NARANJA | AE100: 100 | AH100: SABOR-FRESA | AI100: 300
V101: KIT DE PLANTAS | AD101: KIT DE PLANTAS | AH101: COLOR-PARDO | AI101: 60
AH102: KIT DE PLANTAS
Z105: CODIGO | AA105: LC01
A111: CODIGO | B111: KN01 | G111: CODIGO | H111: CPC01 | L111: CODIGO | M111: SP01 | R111: CODIGO | S111: CT01 | V111: CODIGO | W111: EMX01 | Z111: PRODUCTO | AA111: =VLOOKUP(AA105,LISTPROD[],2,FALSE) -> LIMPIEZA CHINA | AD111: CODIGO | AE111: RP01 | AH111: CODIGO | AI111: FN01 | AL111: CODIGO | AR111: CODIGO | AT111: FA01 | AY111: CODIGO | BA111: MN01
A112: PRODUCTO | B112: =VLOOKUP(B111,LISTPROD[],2,FALSE) -> KOLOSAN | G112: PRODUCTO | H112: =VLOOKUP(H111,LISTPROD[],2,FALSE) -> CONCENTRADO DE PLANTAS CUBANA | L112: PRODUCTO | M112: =VLOOKUP(M111,LISTPROD[],2,FALSE) -> SAW PALMETO (Capsulas) | R112: PRODUCTO | S112: =VLOOKUP(S111,LISTPROD[],2,FALSE) -> CARTILAGO DE TIBURON | V112: PRODUCTO | W112: =VLOOKUP(W111,LISTPROD[],2,FALSE) -> ERECMAX | Z112: ALMACEN | AA112: =VLOOKUP(AA105,LISTPROD[],3,FALSE) -> LIMPIEZA CHINA | AD112: PRODUCTO | AE112: =VLOOKUP(AE111,LISTPROD[],2,FALSE) -> RENAL PLUS | AH112: PRODUCTO | AI112: =VLOOKUP(AI111,LISTPROD[],2,FALSE) -> ZARZAPARILLA | AL112: PRODUCTO | AM112: =VLOOKUP(AM111,LISTPROD[],2,FALSE) -> #N/A | AR112: PRODUCTO | AT112: =VLOOKUP(AT111,LISTPROD[],2,FALSE) -> FUMARIA (Gotas) | AY112: PRODUCTO | BA112: =VLOOKUP(BA111,LISTPROD[],2,FALSE) -> MELENA DE LEON (Gotas)
A113: ALMACEN | B113: =VLOOKUP(B111,LISTPROD[],3,FALSE) -> KOLOSAN | G113: ALMACEN | H113: =VLOOKUP(H111,LISTPROD[],3,FALSE) -> GINSENG-Esencia FLoral 500 ml | L113: ALMACEN | M113: =VLOOKUP(M111,LISTPROD[],3,FALSE) -> SAW PALMETTO | R113: ALMACEN | S113: =VLOOKUP(S111,LISTPROD[],3,FALSE) -> CARTILAGO DE TIBURON | V113: ALMACEN | W113: =VLOOKUP(W111,LISTPROD[],3,FALSE) -> ERECMAX | Z113: Total Cantidad Envasada | AD113: ALMACEN | AE113: =VLOOKUP(AE111,LISTPROD[],3,FALSE) -> RENAL PLUS | AH113: ALMACEN | AI113: =VLOOKUP(AI111,LISTPROD[],3,FALSE) -> ZARZAPARILLA | AL113: ALMACEN | AM113: =VLOOKUP(AM111,LISTPROD[],3,FALSE) -> #N/A | AR113: ALMACEN | AT113: =VLOOKUP(AT111,LISTPROD[],3,FALSE) -> FUMARIA Gotas Orales | AY113: ALMACEN | BA113: =VLOOKUP(BA111,LISTPROD[],3,FALSE) -> MELENA DE LEON Gotas Orales
A114: Total Cantidad Envasada | G114: Total Cantidad Envasada | L114: Total Cantidad Envasada | R114: Total Cantidad Envasada | V114: Total Cantidad Envasada | Z114: Cantidad Unitaria | AD114: Total Cantidad Envasada | AH114: Total Cantidad Envasada | AL114: Total Cantidad Envasada | AR114: Total Cantidad Envasada | AY114: Total Cantidad Envasada
A115: Cantidad Unitaria | G115: Cantidad Unitaria | L115: Cantidad Unitaria | R115: Cantidad Unitaria | V115: Cantidad Unitaria | Z115: Presentación | AD115: Cantidad Unitaria | AH115: Cantidad Unitaria | AL115: Cantidad Unitaria | AR115: Cantidad Unitaria | AY115: Cantidad Unitaria
A116: Presentación | G116: Presentación | L116: Presentación | R116: Presentación | V116: Presentación | Z116: INGREDIENTES | AA116: CANT | AB116: GRAMOs/mL | AD116: Presentación | AH116: Presentación | AL116: Presentación | AR116: Presentación | AY116: Presentación
A117: INGREDIENTES | B117: CANT | C117: GRAMOs/mL | G117: INGREDIENTES | H117: CANT | I117: GRAMOs/mL | L117: INGREDIENTES | M117: CANT | N117: GRAMOs/mL | R117: INGREDIENTES | S117: CANT | T117: GRAMOs/mL | V117: INGREDIENTES | W117: CANT | X117: GRAMOs/mL | Z117: BENZODATO | AA117: 600 | AD117: INGREDIENTES | AE117: CANT | AF117: GRAMOs/mL | AH117: INGREDIENTES | AI117: CANT | AJ117: GRAMOs/mL | AL117: INGREDIENTES | AM117: GRAMOs/mL | AR117: INGREDIENTES | AT117: CANT | AU117: GRAMOs/mL | AY117: INGREDIENTES | BA117: CANT | BB117: GRAMOs/mL
G118: BENZODATO | H118: 600 | R118: CLORURO DE MAGNESIO | S118: 7000 | Z118: ACIDO CITRICO | AA118: 550 | AD118: BENZODATO | AE118: 600
G119: ACIDO CITRICO | H119: 500 | R119: CITRATO DE SODIO | S119: 300 | Z119: CITRATO DE SODIO | AA119: 200 | AD119: CITRATO DE SODIO | AE119: 200
G120: CITRATO DE SODIO | H120: 200 | R120: BENZODATO | S120: 408 | Z120: GOMA XANTAN | AA120: 900 | AD120: ACIDO CITRICO | AE120: 1000
G121: GOMA XANTAN | H121: 900 | R121: SABOR-GUANABANA | S121: 116 | Z121: SABOR-DURAZNO | AA121: 100 | AD121: ENDULZANTE | AE121: 150
G122: SABOR-DURAZNO | H122: 100 | R122: GOMA XANTAN | S122: 708 | Z122: COLOR-PARDO | AA122: 30 | AD122: GOMA XANTAN | AE122: 900
G123: COLOR-PARDO | H123: 20 | R123: COLOR-BLANCO | S123: 68 | Z123: KIT DE PLANTAS | AD123: COLOR-PARDO | AE123: 20
G124: KIT DE PLANTAS | R124: KIT DE PLANTAS | AD124: SABOR-NARNAJA | AE124: 100
AD125: KIT DE PLANTAS
Z127: CODIGO | AA127: MS01
A135: CODIGO | B135: PJL01 | G135: CODIGO | H135: FO01 | L135: CODIGO | M135: SC01 | R135: CODIGO | S135: CHP01 | V135: CODIGO | W135: FL01 | Z135: PRODUCTO | AA135: =VLOOKUP(AA127,LISTPROD[],2,FALSE) -> MATRI SEX | AD135: CODIGO | AE135: RC01 | AH135: CODIGO | AI135: ULD01 | AL135: CODIGO | AR135: CODIGO | AT135: MA01 | AY135: CODIGO | BA135: CDP01
A136: PRODUCTO | B136: =VLOOKUP(B135,LISTPROD[],2,FALSE) -> PAP BRAZ JARABE LITRO | G136: PRODUCTO | H136: =VLOOKUP(H135,LISTPROD[],2,FALSE) -> FENOGRECO (Capsulas) | L136: PRODUCTO | M136: =VLOOKUP(M135,LISTPROD[],2,FALSE) -> SUPER CALCIO | R136: PRODUCTO | S136: =VLOOKUP(S135,LISTPROD[],2,FALSE) -> CHANCA PIEDRA JARABE | V136: PRODUCTO | W136: =VLOOKUP(W135,LISTPROD[],2,FALSE) -> FLEXDOL | Z136: ALMACEN | AA136: =VLOOKUP(AA127,LISTPROD[],3,FALSE) -> MATRI SEX | AD136: PRODUCTO | AE136: =VLOOKUP(AE135,LISTPROD[],2,FALSE) -> ROMPE CALCULOS | AH136: PRODUCTO | AI136: =VLOOKUP(AI135,LISTPROD[],2,FALSE) -> ULTRA DOLOR | AL136: PRODUCTO | AM136: =VLOOKUP(AM135,LISTPROD[],2,FALSE) -> #N/A | AR136: PRODUCTO | AT136: =VLOOKUP(AT135,LISTPROD[],2,FALSE) -> MORINGA (Capsulas) | AY136: PRODUCTO | BA136: =VLOOKUP(BA135,LISTPROD[],2,FALSE) -> CITRATO DE POTASIO (Capsulas)
A137: ALMACEN | B137: =VLOOKUP(B135,LISTPROD[],3,FALSE) -> PAP BRAZ JARABE LITRO | G137: ALMACEN | H137: =VLOOKUP(H135,LISTPROD[],3,FALSE) -> FENOGRECO | L137: ALMACEN | M137: =VLOOKUP(M135,LISTPROD[],3,FALSE) -> COLA DE CABALLO-Esencia FLoral 500 ml | R137: ALMACEN | S137: =VLOOKUP(S135,LISTPROD[],3,FALSE) -> CHANCA PIEDRA JARABE | V137: ALMACEN | W137: =VLOOKUP(W135,LISTPROD[],3,FALSE) -> FLEXDOL | Z137: Total Cantidad Envasada | AD137: ALMACEN | AE137: =VLOOKUP(AE135,LISTPROD[],3,FALSE) -> ROMPE CALCULOS | AH137: ALMACEN | AI137: =VLOOKUP(AI135,LISTPROD[],3,FALSE) -> ULTRA DOLOR | AL137: ALMACEN | AM137: =VLOOKUP(AM135,LISTPROD[],3,FALSE) -> #N/A | AR137: ALMACEN | AT137: =VLOOKUP(AT135,LISTPROD[],3,FALSE) -> MORINGA | AY137: ALMACEN | BA137: =VLOOKUP(BA135,LISTPROD[],3,FALSE) -> CITRATO DE POTASIO
A138: Total Cantidad Envasada | B138: 195 | G138: Total Cantidad Envasada | L138: Total Cantidad Envasada | R138: Total Cantidad Envasada | V138: Total Cantidad Envasada | Z138: Cantidad Unitaria | AD138: Total Cantidad Envasada | AH138: Total Cantidad Envasada | AL138: Total Cantidad Envasada | AR138: Total Cantidad Envasada | AY138: Total Cantidad Envasada
A139: Cantidad Unitaria | G139: Cantidad Unitaria | L139: Cantidad Unitaria | R139: Cantidad Unitaria | V139: Cantidad Unitaria | Z139: Presentación | AD139: Cantidad Unitaria | AH139: Cantidad Unitaria | AL139: Cantidad Unitaria | AR139: Cantidad Unitaria | AY139: Cantidad Unitaria
A140: Presentación | B140: 1000 ml | G140: Presentación | L140: Presentación | R140: Presentación | V140: Presentación | Z140: INGREDIENTES | AA140: CANT | AB140: GRAMOs/mL | AD140: Presentación | AH140: Presentación | AL140: Presentación | AR140: Presentación | AY140: Presentación
A141: INGREDIENTES | B141: CANT | C141: GRAMOs/mL | G141: INGREDIENTES | H141: CANT | I141: GRAMOs/mL | L141: INGREDIENTES | M141: CANT | N141: GRAMOs/mL | R141: INGREDIENTES | S141: CANT | T141: GRAMOs/mL | V141: INGREDIENTES | W141: CANT | X141: GRAMOs/mL | AD141: INGREDIENTES | AE141: CANT | AF141: GRAMOs/mL | AH141: INGREDIENTES | AI141: CANT | AJ141: GRAMOs/mL | AL141: INGREDIENTES | AM141: GRAMOs/mL | AR141: INGREDIENTES | AT141: CANT | AU141: GRAMOs/mL | AY141: INGREDIENTES | BA141: CANT | BB141: GRAMOs/mL
A142: BENZODATO | B142: 600 | L142: CLORURO DE MAGNESIO | M142: 7000 | R142: COLOR-PARDO | S142: 30 | AD142: BENZODATO | AE142: 600
A143: ACIDO CITRICO | B143: 550 | L143: CITRATO DE SODIO | M143: 256 | R143: BENZODATO | S143: 600 | AD143: CITRATO DE SODIO | AE143: 200
A144: CITRATO DE SODIO | B144: 200 | L144: BENZODATO | M144: 408 | R144: GOMA XANTAN | S144: 900 | AD144: ACIDO CITRICO | AE144: 1000
A145: GOMA XANTAN | B145: 900 | L145: SABOR-GUANABANA | M145: 116 | R145: CITRATO DE SODIO | S145: 200 | AD145: ENDULZANTE | AE145: 180
...

Sheet RECETAS
A1: COMPRA | B1: GR | C1: KILO
A2: COMPRA | B2: ML | C2: LITROS
B4: OJO RECETA AJUSTADA PARA UNA SOLA UNIDAD
A9: NOMBRE | B9: potenfull | D9: NOMBRE | E9: emperador | G9: NOMBRE | H9: papa liquida | J9: NOMBRE | K9: wiltron | M9: NOMBRE | N9: enfermedades de la mujer
A10: INGREDIENTES | B10: GRAMOs/mL | D10: INGREDIENTES | E10: GRAMOs/mL | G10: INGREDIENTES | H10: GRAMOs/mL | J10: INGREDIENTES | K10: GRAMOs/mL | M10: INGREDIENTES | N10: GRAMOs/mL
A11: goma xanthan | B11: 700 | D11: goma xanthan | E11: 700 | G11: goma xanthan | H11: 700 | J11: goma xanthan | K11: 700 | M11: goma xanthan | N11: 900
A12: benzohato de sodio | B12: 600 | D12: benzohato de sodio | E12: 600 | G12: benzohato de sodio | H12: 600 | J12: benzohato de sodio | K12: 600 | M12: benzohato de sodio | N12: 600
A13: acido citrico | B13: 1000 | D13: acido citrico | E13: 1000 | G13: acido citrico | H13: 200 | J13: acido citrico | K13: 1000 | M13: acido citrico | N13: 300
A14: endulzante | B14: 250 | D14: endulzante | E14: 250 | G14: endulzante | H14: 200 | J14: sabor fresa | K14: 300 | M14: endulzante | N14: 150
A15: enturbiante | B15: 500 | D15: enturbiante | E15: 500 | G15: enturbiante | H15: 500 | J15: enturbiante | K15: 500 | M15: enturbiante | N15: 300
A16: sabor tropical | B16: 500 | D16: sabor tropical | E16: 500 | G16: sabor avena | H16: 100 | J16: sabor naranja | K16: 100 | M16: sabor frssa | N16: 100
A17: emulcion tropical | B17: 500 | D17: emulcion tropical | E17: 500 | G17: citrato de sodio | H17: 200 | J17: citrato de sodio | K17: 200 | M17: citrato de sodio | N17: 200
A18: componente T | B18: 150 | D18: componente T | E18: 150 | G18: plantas | H18: 1000 | J18: plantas | K18: 1000 | M18: plantas | N18: 1000
G19: color pardo | H19: 30 | J19: color pardo | K19: 60 | M19: color pardo | N19: 40
J20: sulfato ferroso | K20: 1000 | M20: color rojo | N20: 20
A21: NOMBRE | B21: limpiador arterio venoso | D21: NOMBRE | E21: factor d7 | G21: NOMBRE | H21: rompe quistes | J21: NOMBRE | K21: rompe quistes
A22: INGREDIENTES | B22: GRAMOs/mL | D22: INGREDIENTES | E22: GRAMOs/mL | G22: INGREDIENTES | H22: GRAMOs/mL | J22: INGREDIENTES | K22: GRAMOs/mL | M22: NOMBRE | N22: vitacerebrina
A23: goma xanthan | B23: 800 | D23: goma xanthan | E23: 800 | G23: goma xanthan | H23: 900 | J23: goma xanthan | K23: 900 | M23: INGREDIENTES | N23: GRAMOs/mL
A24: benzohato de sodio | B24: 600 | D24: benzohato de sodio | E24: 600 | G24: benzohato de sodio | H24: 600 | J24: benzohato de sodio | K24: 600 | M24: goma xanthan | N24: 900
A25: acido citrico | B25: 200 | D25: acido citrico | E25: 300 | G25: acido citrico | H25: 300 | J25: acido citrico | K25: 300 | M25: benzohato de sodio | N25: 600
A26: endulzante | B26: 100 | D26: endulzante | E26: 100 | G26: endulzante | H26: 150 | J26: endulzante | K26: 150 | M26: acido citrico | N26: 300
A27: enturbiante | B27: 500 | D27: enturbiante | E27: 500 | G27: enturbiante | H27: 500 | J27: enturbiante | K27: 500 | M27: endulzante | N27: 150
A28: sabor a naranja | B28: 100 | D28: sabor a naranja | E28: 100 | G28: sabor frssa | H28: 100 | J28: sabor frssa | K28: 100 | M28: enturbiante | N28: 500
A29: citrato de sodio | B29: 200 | D29: citrato de sodio | E29: 200 | G29: citrato de sodio | H29: 200 | J29: citrato de sodio | K29: 200 | M29: sabor a naranja | N29: 100
A30: plantas | B30: 1000 | D30: plantas | E30: 1000 | G30: plantas | H30: 1000 | J30: plantas | K30: 1000 | M30: citrato de sodio | N30: 200
A31: color pardo | B31: 60 | D31: color pardo | E31: 60 | G31: color pardo | H31: 40 | J31: color pardo | K31: 40 | M31: plantas | N31: 1000
A32: sulfato ferroso | B32: 300 | D32: sulfato ferroso | E32: 1000 | G32: sulfato ferroso | H32: 1000 | J32: sulfato ferroso | K32: 1000 | M32: color pardo | N32: 40
G33: color rojo | H33: 20 | J33: color rojo | K33: 20 | M33: sulfato ferroso | N33: 1000
M34: color rojo | N34: 20
A35: NOMBRE | B35: gran tamakura | D35: NOMBRE | E35: salto del tigre | G35: NOMBRE | H35: salto del tigre | J35: NOMBRE | K35: copa del indio | M35: NOMBRE | N35: ortiga
A36: INGREDIENTES | B36: GRAMOs/mL | D36: INGREDIENTES | E36: GRAMOs/mL | G36: INGREDIENTES | H36: GRAMOs/mL | J36: INGREDIENTES | K36: GRAMOs/mL | M36: INGREDIENTES | N36: GRAMOs/mL
A37: goma xanthan | B37: 800 | D37: goma xanthan | E37: 800 | G37: goma xanthan | H37: 900 | J37: goma xanthan | K37: 900 | M37: goma xanthan | N37: 900
A38: benzohato de sodio | B38: 600 | D38: benzohato de sodio | E38: 600 | G38: benzohato de sodio | H38: 600 | J38: benzohato de sodio | K38: 600 | M38: benzohato de sodio | N38: 600
A39: acido citrico | B39: 1000 | D39: acido citrico | E39: 1000 | G39: acido citrico | H39: 500 | J39: acido citrico | K39: 500 | M39: acido citrico | N39: 500
A40: endulzante | B40: 250 | D40: endulzante | E40: 250 | G40: endulzante | H40: 250 | J40: endulzante | K40: 250 | M40: endulzante | N40: 100
A41: sabor tropical | B41: 500 | D41: sabor tropical | E41: 500 | G41: sabor durazno | H41: 500 | J41: sabor durazno | K41: 500 | M41: sabor durazno | N41: 500
A42: emulcion tropical | B42: 500 | D42: emulcion tropical | E42: 500 | G42: color pardo | H42: 30 | J42: color pardo | K42: 30 | M42: color pardo | N42: 30
A43: componente T | B43: 300 | D43: componente T | E43: 300 | G43: citrato de sodio | H43: 200 | J43: citrato de sodio | K43: 200 | M43: citrato de sodio | N43: 200
G44: plantas | H44: 300 | J44: plantas | K44: 300 | M44: plantas | N44: 300
A46: NOMBRE | B46: gran tamakura | D46: NOMBRE | E46: moringa | G46: NOMBRE | H46: colon clenser | J46: NOMBRE | K46: 7 toros | M46: NOMBRE | N46: arbron
A47: INGREDIENTES | B47: GRAMOs/mL | D47: INGREDIENTES | E47: GRAMOs/mL | G47: INGREDIENTES | H47: GRAMOs/mL | J47: INGREDIENTES | K47: GRAMOs/mL | M47: INGREDIENTES | N47: GRAMOs/mL
A48: goma xanthan | B48: 800 | D48: goma xanthan | E48: 900 | G48: goma xanthan | H48: 900 | J48: goma xanthan | K48: 900 | M48: goma xanthan | N48: 900
A49: benzohato de sodio | B49: 600 | D49: benzohato de sodio | E49: 600 | G49: benzohato de sodio | H49: 600 | J49: benzohato de sodio | K49: 600 | M49: benzohato de sodio | N49: 600
A50: citrato de sodio | B50: 256 | D50: acido citrico | E50: 500 | G50: acido citrico | H50: 1000 | J50: acido citrico | K50: 300 | M50: acido citrico | N50: 600
A51: endulzante | B51: 250 | D51: endulzante | E51: 100 | G51: endulzante | H51: 300 | J51: endulzante | K51: 100 | M51: endulzante | N51: 100
A52: sabor uva | B52: 116 | D52: sabor durazno | E52: 500 | G52: sabor mango | H52: 500 | J52: enturbiante | K52: 500 | M52: sabor durazno | N52: 100
A53: color blanco | B53: 68 | D53: color pardo | E53: 30 | G53: color pardo | H53: 30 | J53: sabor durazno | K53: 100 | M53: color pardo | N53: 30
A54: cloruro de magnecio | B54: 7000 | D54: citrato de sodio | E54: 200 | G54: citrato de sodio | H54: 200 | J54: citrato de sodio | K54: 200 | M54: citrato de sodio | N54: 200
D55: plantas | E55: 300 | G55: plantas | H55: 300 | J55: plantas | K55: 1000 | M55: plantas | N55: 300
J56: color caramelo | K56: 100
J57: sulfato ferroso | K57: 1000
J58: color rojo | K58: 20
J59: componente T | K59: 150
A63: NOMBRE | B63: totumo y pulmonaria | D63: NOMBRE | E63: limpieza china | G63: NOMBRE | H63: cir-land | J63: NOMBRE | K63: oxtmax | M63: NOMBRE | N63: gastrobell
A64: INGREDIENTES | B64: GRAMOs/mL | D64: INGREDIENTES | E64: GRAMOs/mL | G64: INGREDIENTES | H64: GRAMOs/mL | J64: INGREDIENTES | K64: GRAMOs/mL | M64: INGREDIENTES | N64: GRAMOs/mL
A65: goma xanthan | B65: 700 | D65: goma xanthan | E65: 900 | G65: goma xanthan | H65: 900 | J65: goma xanthan | K65: 900 | M65: goma xanthan | N65: 900
A66: benzohato de sodio | B66: 600 | D66: benzohato de sodio | E66: 600 | G66: benzohato de sodio | H66: 600 | J66: benzohato de sodio | K66: 600 | M66: benzohato de sodio | N66: 600
A67: acido citrico | B67: 200 | D67: acido citrico | E67: 600 | G67: acido citrico | H67: 600 | J67: cloruro de magnecio | K67: 5000 | M67: acido citrico | N67: 1000
A68: endulzante | B68: 100 | D68: endulzante | E68: 100 | G68: endulzante | H68: 100 | J68: endulzante | K68: 50 | M68: endulzante | N68: 300
A69: sabor menta | B69: 10 | D69: sabor durazno | E69: 100 | G69: sabor limon | H69: 200 | J69: sabor limon | K69: 200 | M69: sabor mango | N69: 150
A70: color amarillo | B70: 70 | D70: color pardo | E70: 30 | G70: color pardo | H70: 40 | J70: color blanco | K70: 70 | M70: color pardo | N70: 20
A71: citrato de sodio | B71: 200 | D71: citrato de sodio | E71: 200 | G71: citrato de sodio | H71: 200 | J71: citrato de sodio | K71: 200 | M71: citrato de sodio | N71: 200
A72: plantas | B72: 300 | D72: plantas | E72: 300 | G72: plantas | H72: 300 | M72: plantas | N72: 300
A73: sabor a naranja | B73: 80
A78: NOMBRE | B78: gastrobell | D78: NOMBRE | E78: meromacho
A79: INGREDIENTES | B79: GRAMOs/mL | D79: INGREDIENTES | E79: GRAMOs/mL
A80: goma xanthan | B80: 900 | D80: goma xanthan | E80: 900
A81: benzohato de sodio | B81: 600 | D81: benzohato de sodio | E81: 600
A82: acido citrico | B82: 1000 | D82: acido citrico | E82: 300
A83: endulzante | B83: 300 | D83: endulzante | E83: 500
A84: sabor mango | B84: 150 | D84: enturbiante | E84: 500
A85: color pardo | B85: 20 | D85: sabor uva | E85: 200
A86: citrato de sodio | B86: 200 | D86: alcohol | E86: 4000
A87: plantas | B87: 300 | D87: plantas | E87: 1000
A88: sabor menta | B88: 10 | D88: color caramelo | E88: 100
D89: sulfato ferroso | E89: 1000
D90: color rojo | E90: 20
D91: componente x | E91: 150

Sheet PRECIO COMPR
Q1: 1KG | R1: 1.000 GR
B4: CODIGO | C4: RE01 | I4: CODIGO | J4: CA02 | P4: CODIGO | Q4: CA02
B5: PRODUCTO | C5: =VLOOKUP(C4,LISTPROD[],2,FALSE) -> RESCATE (Gotas) | I5: PRODUCTO | J5: =VLOOKUP(J4,LISTPROD[],2,FALSE) -> CALENDULA (Capsulas) | P5: PRODUCTO | Q5: =VLOOKUP(Q4,LISTPROD[],2,FALSE) -> CALENDULA (Capsulas)
B6: ALMACEN | C6: =VLOOKUP(C4,LISTPROD[],3,FALSE) -> RESCATE Gotas Orales | I6: ALMACEN | J6: =VLOOKUP(J4,LISTPROD[],3,FALSE) -> CALENDULA | P6: ALMACEN | Q6: =VLOOKUP(Q4,LISTPROD[],3,FALSE) -> CALENDULA
B7: Total Cantidad Envasada | C7: 158 | I7: Total Cantidad Envasada | J7: 140 | K7: CADA ENVASE TIENE 60 CAPSULAR | P7: Total Cantidad Envasada | Q7: 1
B8: Cantidad Unitaria | I8: Cantidad Unitaria | P8: Cantidad Unitaria | Q8: 1
B9: Presentación | I9: Presentación | J9: 60 | K9: CADA ENVASE TIENE 60 CAPSULAR | P9: Presentación | Q9: 60 | R9: CADA ENVASE TIENE 60 CAPSULAR
I10: PESO X UND | J10: 0.5 | K10: =J10*J9 -> 30 | P10: PESO X UND | Q10: 0.5 | R10: =Q10*Q9 -> 30
I11: PRODUCCION | P11: VALOR COMPRA | U11: FORMULA
B12: INGREDIENTES | C12: CLASIFICACION | D12: CANT | E12: CANT COMPRA | F12: PRECIO COMPRA | I12: INGREDIENTES | J12: CLASIFICACION | K12: CANT | L12: Und de Medida | M12: Cant x Und Envasadas | P12: CANT COMPRA | Q12: PRECIO COMPRA | R12: IVA | S12: PRECIO COMPRA | T12: CONVERSION COSTO x UNID/GR | U12: Cant x Und Envasadas | V12: Und de Medida
B13: Dilución Floral de Impaciencia | C13: INSUMO | I13: PASTILLERO 180(38) PE BLANCO | J13: EMPAQUE | K13: UND | L13: 140 | M13: =L13/$J$7 -> 1 | P13: UND | Q13: 547 | R13: =Q13*19% -> 103.93 | S13: =+R13+Q13 -> 650.93 | T13: =S13 -> 650.93 | U13: 1 | V13: UND
B14: Dilución Floral de Estrella de belén | C14: INSUMO | I14: CALENDULA | J14: INSUMO | K14: GR | L14: 4200 | M14: =L14/$J$7 -> 30 | P14: KG | Q14: 25000 | R14: =Q14*19% -> 4750 | S14: =+R14+Q14 -> 29750 | T14: =S14/1000*Q10*Q9 -> 892.5 | U14: 30 | V14: GR
B15: Dilución Floral de Heliantemo | C15: INSUMO | I15: CAPSULAS | J15: INSUMO | K15: UND | L15: 8400 | M15: =L15/$J$7 -> 60 | P15: UND | Q15: 17 | R15: 0 | S15: =+R15+Q15 -> 17 | T15: =Q9*S15 -> 1020 | U15: 60 | V15: UND
B16: Dilución Floral de Cerasifera | C16: INSUMO | I16: TAPA 38 PD ENSAMBLADA PE VERDE | J16: EMPAQUE | K16: UND | L16: 140 | M16: =L16/$J$7 -> 1 | P16: UND | Q16: 252 | R16: =Q16*19% -> 47.88 | S16: =+R16+Q16 -> 299.88 | T16: =S16 -> 299.88 | U16: 1 | V16: UND
B17: Dilución Floral de Clemátide | C17: INSUMO | I17: LINER DE TROQUEL 38 MM PS | J17: EMPAQUE | K17: UND | L17: 140 | M17: =L17/$J$7 -> 1 | P17: UND | Q17: 81 | R17: =Q17*19% -> 15.39 | S17: =+R17+Q17 -> 96.39 | T17: =S17 -> 96.39 | U17: 1 | V17: UND
B18: Alcohol al 96 % | C18: INSUMO | I18: ETIQUETA METALIZADA | J18: EMPAQUE | K18: UND | L18: 140 | M18: =L18/$J$7 -> 1 | P18: UND | Q18: 150 | R18: 0 | S18: =+R18+Q18 -> 150 | T18: =S18 -> 150 | U18: 1 | V18: UND
B19: Agua purificada | C19: INSUMO | I19: TERMOENCOGIBLE | J19: EMPAQUE | K19: UND | L19: 140 | M19: =L19/$J$7 -> 1 | P19: UND | Q19: 120 | R19: 0 | S19: =+R19+Q19 -> 120 | T19: =S19 -> 120 | U19: 1 | V19: UND
B20: Frasco Ámbar 25 mL Boca 18 mm | C20: EMPAQUE | D20: UND | P20: GASTOS VARIOS | S20: 2735.7143 | T20: =S20 -> 2735.7143
B21: Perilla gotero Negra -Tapa negra con Pipeta dosificadora en vidrio . Boca 18 mm | C21: EMPAQUE | D21: UND
B22: Etiqueta | C22: EMPAQUE | D22: UND
B23: Plegadiza | C23: EMPAQUE | D23: UND
B24: Banda de seguridad | C24: EMPAQUE | D24: UND
N25: =SUM(N13:N24) -> 0 | S25: =SUM(S13:S24) -> 33819.914 | T25: =SUM(T13:T24) -> 5965.4143 | U25: COSTO TOTAL UNIDAD
T26: =T25*51% -> 3042.3613 | U26: UTILIDAD 51%
T27: =T25+T26 -> 9007.7756 | U27: PRECIO DE VENTA

Sheet Preci Comp Prod
D1: 1 GALON | E1: 3785 GR
D2: 1 KG | E2: 1000GR
C6: INGREDIENTES | D6: UNIDA MEDIDA COMPRA | E6: PRECIO | F6: IVA | G6: TOTAL | L6: EMPAQUE | M6: UNIDA MEDIDA COMPRA | N6: PRECIO | O6: IVA | P6: TOTAL | Q6: ALMACEN | U6: EMPAQUE | V6: UNIDA MEDIDA COMPRA | W6: PRECIO
C7: ACIDO CITRICO | D7: KG | E7: 5400 | F7: =E7*19% -> 1026 | G7: =+F7+E7 -> 6426 | U7: TAPA 38 PD ENSAMBLADA PE VERDE
L8: BOTELLA MERO MACHO LARGO | M8: UND | N8: 700 | O8: 0 | P8: =+O8+N8 -> 700 | R8: SE USA EN: PONTEFULL FLOR DE CENTELLA NUEVA TAMAKURA GLDEN PUL FACTOR D7 EMPERADOR IFAMOL JARABE | U8: LINER DE TROQUEL 38 MM PS
C9: AGUA DESTILADA | U9: ETIQUETA
C10: ALCOHOL | D10: LT | E10: 7200 | G10: =+E10 -> 7200 | L10: CAJAS | M10: UND | N10: 800 | O10: 0 | P10: =+O10+N10 -> 800 | U10: Frasco Ámbar 25 mL Boca 18 mm
C11: BENZODATO DE SODIO | D11: KG | E11: 7900 | F11: =E11*19% -> 1501 | G11: =+F11+E11 -> 9401 | L11: ETIQUETAS | M11: UND | N11: 100 | O11: 0 | P11: =+O11+N11 -> 100 | U11: Perilla gotero Negra -Tapa negra con Pipeta dosificadora en vidrio . Boca 18 mm
L12: CAJA ARTRIN | M12: UND | N12: 450 | O12: 0 | P12: =+O12+N12 -> 450 | Q12: LUIS-FARMACIA NATIVA | R12: CAJA ARTRIN ULTRADOLOR | U12: Etiqueta
C13: CITRATO DE SODIO | D13: KG | E13: 4700 | F13: =E13*19% -> 893 | G13: =+F13+E13 -> 5593 | L13: CAJA ULTRADOLOR | M13: UND | N13: 650 | O13: 0 | P13: =+O13+N13 -> 650 | Q13: LUIS-FARMACIA NATIVA | U13: Plegadiza
C14: CITRATO DE MAGNESIO | D14: KG | E14: 12000 | F14: =E14*19% -> 2280 | G14: =+F14+E14 -> 14280 | L14: ANTIESPUMANTE | M14: GALON | N14: 84000 | O14: =N14*19% -> 15960 | P14: =+O14+N14 -> 99960 | U14: Banda de seguridad
C15: CLORURO DE MAGNESIO | D15: KG | E15: 18000 | F15: =E15*19% -> 3420 | G15: =+F15+E15 -> 21420 | L15: POTE 180 Y TAPA 53 | M15: UND | N15: =538+306 -> 844 | O15: =N15*19% -> 160.36 | P15: =+O15+N15 -> 1004.36 | U15: Caja 25ml
C16: CLORURO DE SODIO | D16: KG | E16: 14000 | F16: =E16*19% -> 2660 | G16: =+F16+E16 -> 16660 | L16: CAJA UNGÜENTO | M16: UND | N16: 550 | O16: 0 | P16: =+O16+N16 -> 550 | Q16: LUIS-FARMACIA NATIVA | U16: TERMOENCOGIBLE
C17: CLORURO DE POTASIO | D17: KG | E17: 9500 | F17: 0 | G17: =+E17 -> 9500 | L17: ETIQUETA UNGÜENTO | M17: UND | N17: 100 | O17: 0 | P17: =+O17+N17 -> 100 | Q17: LUIS-FARMACIA NATIVA
C18: ANTIESPUMANTE | D18: GR | E18: =N14/3785 -> 22.192867 | F18: =E18*19% -> 4.2166446 | G18: =+F18+E18 -> 26.409511 | L18: CAJA Y ETIQUETA FLEXDOL | M18: UND | N18: 420 | O18: 0 | P18: =+O18+N18 -> 420 | Q18: LUIS-FARMACIA NATIVA
C19: PASTA BLANCA | D19: UND | E19: 1000 | F19: 0 | G19: =+F19+E19 -> 1000 | L19: BOTELLA FLEXDOL | M19: UND | N19: 500 | O19: 0 | P19: =+O19+N19 -> 500 | Q19: LUIS-FARMACIA NATIVA
C20: PASTA NARANJA | D20: UND | E20: 750 | F20: 0 | G20: =+F20+E20 -> 750 | L20: BOTELLA PHARMA | M20: UND | N20: 650 | O20: 0 | P20: =+O20+N20 -> 650 | R20: SE USA: PARA TODO PHARMA
C21: COLOR-AMARILLO | D21: KG | L21: BOTELLA CUBANOS | M21: UND | N21: 650 | O21: 0 | P21: =+O21+N21 -> 650 | R21: SE USA: CUBANOS
C22: COLOR-BLANCO | D22: KG | E22: 210084.03 | F22: =E22*19% -> 39915.966 | G22: =+F22+E22 -> 250000
C23: COLOR-CARAMELO | D23: KG | E23: 20882 | F23: =E23*19% -> 3967.58 | G23: =+F23+E23 -> 24849.58 | L23: COPA | M23: UND | N23: 250 | O23: 0 | P23: =+O23+N23 -> 250 | R23: SE USA PARA TODOS LOS PRODUCTOS MENOS DE LITRO
C24: COLOR-PARDO | D24: KG | E24: 80268 | F24: =E24*19% -> 15250.92 | G24: =+F24+E24 -> 95518.92 | L24: BOTELLA DE LT (Con copa y Tapa) | M24: UND | N24: 1500 | O24: 0 | P24: =+O24+N24 -> 1500 | R24: SE USA: Parta todos los productos de Litro y PAP BRAZ
C25: COLOR-ROJO | D25: KG | L25: BOTELLA LAMPARA | M25: UND | N25: 650 | O25: 0 | P25: =+O25+N25 -> 650 | R25: PROD DE MARIA JOSE
C26: COLOR-CAFÉ | D26: KG | L26: COPA PARA LAMPARA | M26: UND | N26: 250 | O26: 0 | P26: =+O26+N26 -> 250 | R26: PROD DE MARIA JOSE
C27: COLOR-CAFÉ PARDO | D27: KG | L27: TAPA #28 blanca | M27: UND | N27: 70 | O27: 0 | P27: =+O27+N27 -> 70 | R27: PROD DE MARIA JOSE
C28: COLOR-VERDE GRASA | D28: KG | E28: 140000 | F28: =E28*19% -> 26600 | G28: =+F28+E28 -> 166600 | L28: BOTELLA 240ml AMBAR | M28: UND | N28: 350 | O28: 0 | P28: =+O28+N28 -> 350 | R28: SE USA PARA TODOS LOS PRODUCTOS MENOS DE LITRO
C29: COMPONENTE X | D29: KG | E29: 750000 | G29: =+E29 -> 750000
C30: COMPONENTE T | D30: KG | E30: 2000000 | F30: =E30*19% -> 380000 | G30: =+F30+E30 -> 2380000
C31: COMPONENTE S | D31: KG | E31: 600000 | F31: =E31*19% -> 114000 | G31: =+F31+E31 -> 714000
C32: EMULSION TROPICAL | D32: KG | E32: 120000 | F32: =E32*19% -> 22800 | G32: =+F32+E32 -> 142800
C33: ENDULZANTE | D33: KG | E33: 46330 | F33: =E33*19% -> 8802.7 | G33: =+F33+E33 -> 55132.7
C34: ANTI ENTURBIANTE | D34: KG | E34: 120000 | F34: =E34*19% -> 22800 | G34: =+F34+E34 -> 142800 | L34: CAJA PRESENTACION 500ML | M34: UND | N34: 650 | O34: 0 | P34: =+O34+N34 -> 650 | R34: PHARMA
C35: GOMA XANTAN | D35: KG | E35: 18900 | F35: =E35*19% -> 3591 | G35: =+F35+E35 -> 22491 | L35: CAJA PRESENTACION 1000ML | M35: UND | N35: 750 | O35: 0 | P35: =+O35+N35 -> 750 | R35: CUBANOS
C36: KIT DE PLANTAS | E36: 30000 | F36: 0 | G36: =+F36+E36 -> 30000 | H36: DIVIDR EN LA CANT DE PRODUCT | L36: CAJA DE EMPAQUE DE 60 UNIDADE DE 500ML | M36: UND | N36: 4500 | O36: 0 | P36: =+O36+N36 -> 4500
C37: MENTOL | D37: KG | E37: 120000 | F37: =E37*19% -> 22800 | G37: =+F37+E37 -> 142800 | L37: CAJA DE EMPAQUE DE 30 UNIDADE DE 1000ML | M37: UND | N37: 4500 | O37: 0 | P37: =+O37+N37 -> 4500
C38: SABOR DURAZNO | D38: KG | E38: 53393 | F38: =E38*19% -> 10144.67 | G38: =+F38+E38 -> 63537.67 | L38: Banda de seguridad(Termoencogible)
C39: SABOR-AVENA | D39: KG | L39: TERMOENCOGIBLE 7 TOROS
C40: SABOR-CARAMELO | D40: KG | L40: CAJA INFAMOL
C41: SABOR-FRESA | D41: KG | E41: 49240 | F41: =E41*19% -> 9355.6 | G41: =+F41+E41 -> 58595.6 | L41: ETIQUETA INFAMOL SPRAY
C42: SABOR-GUANABANA | D42: KG
C43: SABOR-LIMON | D43: KG | E43: 70000 | F43: =E43*19% -> 13300 | G43: =+F43+E43 -> 83300
C44: SABOR-LIMON G LHD1338 | D44: KG | E44: 46867 | F44: =E44*19% -> 8904.73 | G44: =+F44+E44 -> 55771.73 | L44: GOTEROS
C45: SABOR-MAGO | D45: KG | L45: Frasco Ámbar 25 mL Boca 18 mm | N45: 1050 | P45: =+N45 -> 1050
C46: SABOR-MANGO MADURO | D46: KG | E46: 64575 | F46: =E46*19% -> 12269.25 | G46: =+F46+E46 -> 76844.25 | L46: Perilla gotero Negra -Tapa negra con Pipeta dosificadora en vidrio . Boca 18 mm
C47: SABOR-FRUTOS ROJOS | D47: KG | E47: 48647 | F47: =E47*19% -> 9242.93 | G47: =+F47+E47 -> 57889.93 | L47: Etiqueta | N47: 200 | P47: =+N47 -> 200
C48: SABOR-MENTA | D48: KG | L48: Plegadiza (Caja) | N48: 350 | P48: =+N48 -> 350
C49: SABOR-NARANJA | D49: KG | E49: 51533 | F49: =E49*19% -> 9791.27 | G49: =+F49+E49 -> 61324.27 | L49: Banda de seguridad(Termoencogible) | N49: 200 | P49: =+N49 -> 200
C50: SABOR-ORIENTAL
C51: SABOR-RON
C52: SABR EUCALIPTO | D52: KG | E52: 71947 | F52: =E52*19% -> 13669.93 | G52: =+F52+E52 -> 85616.93
C53: SABOR-TROPICAL | D53: KG | E53: 66465 | F53: =E53*19% -> 12628.35 | G53: =+F53+E53 -> 79093.35
C54: SABOR-UVA | D54: KG | E54: 64485 | F54: =E54*19% -> 12252.15 | G54: =+F54+E54 -> 76737.15
C55: SABOR-VAINILLA
C56: SABOR-VAINILLA LACTEA | D56: KG | E56: 49061 | F56: =E56*19% -> 9321.59 | G56: =+F56+E56 -> 58382.59
C57: SABOR-HONEY | D57: KG | E57: 69826 | F57: =E57*19% -> 13266.94 | G57: =+F57+E57 -> 83092.94
C58: SALICILIATO DE METILO | D58: LT | E58: 38000 | F58: 0 | G58: =+F58+E58 -> 38000
C59: SORBITOL
C60: SULFATO FERROSO | D60: KG | E60: 20000 | F60: 0 | G60: =+F60+E60 -> 20000
C61: VASELINA BLANCO USP | D61: KG | E61: 10086 | F61: =E61*19% -> 1916.34 | G61: =+F61+E61 -> 12002.34
C62: PARAFINA | D62: KG | E62: 15000 | F62: =E62*19% -> 2850 | G62: =+F62+E62 -> 17850
C63: TAURINA | D63: KG | E63: 35000 | F63: =E63*19% -> 6650 | G63: =+F63+E63 -> 41650
C64: SINDENAFIL | D64: KG | E64: 750000 | F64: =E64*19% -> 142500 | G64: =+F64+E64 -> 892500
C65: GLUCOSAMINA SULFATO | D65: KG | E65: 42000 | F65: 0 | G65: =+E65 -> 42000
C66: TADAFILO | D66: KG
C68: Alcohol al 96 % | D68: LT | E68: 7200 | F68: 0 | G68: =+F68+E68 -> 7200
C69: Agua purificada | D69: LT | E69: 300 | F69: 0 | G69: =+F69+E69 -> 300
C70: Dilución Floral de Agrimonia | D70: ML | E70: 50000 | F70: =E70*19% -> 9500 | G70: =+F70+E70 -> 59500
C71: Dilución Floral de Centaura | D71: ML | E71: 50000 | F71: =E71*19% -> 9500 | G71: =+F71+E71 -> 59500
C72: Dilución Floral de Impaciencia | D72: ML | E72: 50000 | F72: =E72*19% -> 9500 | G72: =+F72+E72 -> 59500
C73: Cepa Homeopática-Tintura en Glicerina (Manzanilla) | F73: =E73*19% -> 0 | G73: =+F73+E73 -> 0
C74: Miel | F74: =E74*19% -> 0 | G74: =+F74+E74 -> 0
C75: Solución Salina Esteríl 0,9%
C76: Cloruro de Benzalconio
H140: QUE ES
H141: CANTIDAD DEL TARRO ?
H142: QUE ES
H143: QUE ES
H148: QUE ES
H153: QUE ES
H154: QUE ES
H191: QUE ES

Sheet GRUPOS SAI OPEN
B1: BODEGA
B2: 01-PRINCIPAL
B3: 02-JUNIN
G11: LINEA | H11: 01 | I11: HOMEOPATICOS | K11: LINEA | L11: 02 | M11: MATERIA PRIMA | O11: LINEA | P11: 03 | Q11: MATERIAL DE EMPAQUE
G12: GRUPO | H12: 0101 | I12: JARABES | K12: GRUPO | L12: 0201 | M12: INGREDIENTES | O12: GRUPO | P12: 0301 | Q12: ENVASES
G13: SUBGRUPO | H13: 010101 | I13: JARABE 500 ML | K13: SUBGRUPO | L13: 020101 | M13: INGREDIENTES | O13: SUBGRUPO | P13: 030101 | Q13: BOTELLA FITO BLANCO- MERO MACHO LARGO
H14: 010102 | I14: JARABE 1000 ML | P14: 030102 | Q14: BOTELLA MERO MACHO CORTO
H15: 010103 | I15: JARABE 240 ML | P15: 030103 | Q15: BOTELLA FLEXDOL
H16: 010104 | I16: JARABE 740 ML | P16: 030104 | Q16: BOTELLA PHARMA
P17: 030105 | Q17: BOTELLA CUBANOS
G18: GRUPO | H18: 0102 | I18: CAPSULAS | K18: GRUPO | L18: 0202 | M18: COLORANTES | P18: 030106 | Q18: BOTELLA DE LT (Con copa y Tapa)
G19: SUBGRUPO | H19: 010201 | I19: 30 CAPSULAS | K19: SUBGRUPO | L19: 020201 | M19: COLORANTES | P19: 030107 | Q19: BOTELLA LAMPARA
H20: 010202 | I20: 60 CAPSULAS | P20: 030108 | Q20: BOTELLA 240ml AMBAR
P21: 030109 | Q21: BOTELLA PET AMBAR
P22: 030110 | Q22: BOTELLA DE VIDRIO VINO PPG
G23: GRUPO | H23: 0103 | I23: GOTAS | K23: GRUPO | L23: 0203 | M23: SABORES | P23: 030111 | Q23: BOTELLA (BALA) BLANCA 500ML
G24: SUBGRUPO | H24: 010301 | I24: GOTAS 25 ML | K24: SUBGRUPO | L24: 020201 | M24: SABORES | P24: 030112 | Q24: Frasco Ámbar 25 mL Boca 18 mm
P25: 030113 | Q25: Perilla gotero Negra -Tapa negra con Pipeta dosificadora en vidrio . Boca 18 mm
G26: GRUPO | H26: 0104 | I26: UNGUENTOS | P26: 030114 | Q26: POTE 180 Y TAPA 53
G27: SUBGRUPO | H27: 010401 | I27: UNGUENTOS | P27: 030115 | Q27: PASTILLERO 180(38) PE BLANCO
P28: 030116 | Q28: CAPSULAS
O31: GRUPO | P31: 0302 | Q31: COPAS
O32: SUBGRUPO | P32: 030201 | Q32: COPA VARIOS
P33: 030202 | Q33: COPA PARA LAMPARA
O37: GRUPO | P37: 0303 | Q37: ETIQUETAS
O38: SUBGRUPO | P38: 030301 | Q38: ETIQUETAS
P39: 030302 | Q39: ETIQUETA UNGÜENTO
P40: 030303 | Q40: ETIQUETA PAPA SILVESTRE JARABE 240ml
P41: 030304 | Q41: ETIQUETA WILTRON
P42: 030305 | Q42: ETIQUETA METALIZADA
P43: 030306 | Q43: ETIQUETA INFAMOL SPRAY
P44: 030307 | Q44: ETIQUETA GOTAS
O47: GRUPO | P47: 0304 | Q47: TAPAS
O48: SUBGRUPO | P48: 30401 | Q48: TAPA #28 blanca
P49: 30402 | Q49: TAPA #28 Roja (viene marcada)
P50: 30403 | Q50: TAPA VERDE
P51: 30404 | Q51: TAPA AMARILLA
P52: 30405 | Q52: TAPA 38 PD ENSAMBLADA PE VERDE
O57: GRUPO | P57: 0305 | Q57: TERMOENCOGIBLE
O58: SUBGRUPO | P58: 030501 | Q58: TERMOENCOGIBLE VARIOS
P59: 030502 | Q59: LINER DE TROQUEL 38 MM PS
P60: 030503 | Q60: Banda de seguridad(Termoencogible) por Metros
O64: GRUPO | P64: 0306 | Q64: STICKER
O65: SUBGRUPO | P65: 030601 | Q65: STICKER PHARMA
P66: 030602 | Q66: STICKER MANANTIAL DE VIDA
O71: GRUPO | P71: 0307 | Q71: CAJAS PRODUCTOS
O72: SUBGRUPO | P72: 030701 | Q72: CAJAS VARIOS
P73: 030702 | Q73: CAJA ARTRIN
P74: 030703 | Q74: CAJA ULTRADOLOR
P75: 030704 | Q75: CAJA UNGÜENTO
P76: 030705 | Q76: CAJA Y ETIQUETA FLEXDOL
P77: 030706 | Q77: CAJA WILTROL
P78: 030707 | Q78: CAJA INFAMOL
P79: 030708 | Q79: CAJA ARTERIO VENOSO
P80: 030709 | Q80: PLEGADIZA (CAJA)
O86: GRUPO | P86: 0308 | Q86: CAJAS EMPAQUE
O87: SUBGRUPO | P87: 030801 | Q87: CAJA PRESENTACION 500ML
P88: 030802 | Q88: CAJA PRESENTACION 1000ML
P89: 030803 | Q89: CAJA DE EMPAQUE DE 60 UNIDADE DE 500ML
P90: 030804 | Q90: CAJA DE EMPAQUE DE 30 UNIDADE DE 1000ML

Sheet DETALLE PRODUCTOSxPrecio
E1: HOMEOPATICOS; capsu, goteros y lt | O1: VALIDAR PRECIO
A2: PRODUCTOS ACTUALIZADO MAYO 2025 | O2: FALTA PRECIO PROD
O3: FALTA PRECIO PROD Y VALIDAR RECETA
O4: FALTA RECETA | U4: #1 ELAINE | Y4: #2 CALICHE | AC4: #3 VICTOR
E5: SAI OPEN | J5: No incluir | U5: INF PARA SAI OPEN | Y5: INF PARA SAI OPEN | AC5: INF PARA SAI OPEN | AH5: VALORES ACTUALES
AH6: A-0001 | AI6: B-0001 | AJ6: C-0001
A7: CODIGO | B7: PRODUCTO | C7: NOMBRE EN ETIQUETA | D7: PRESENTACION | E7: LINEA | F7: LINEA. | G7: GRUPO | H7: SUB GRUPO | I7: SUB GRUPO2 | J7: MARCA | K7: CAMARAS DE COMERCIO DE DISTRIBUIDORES | L7: ELABORADO POR | M7: COMERCIALIZADO POR | N7: LUGAR DE ALMACENAMIENTO | O7: PRECIO DE PRODUCCIÓN POR UND | P7: TOTAL GASTOS VARIOS | Q7: COSTO TOTAL UNIDAD | R7: COSTO UTILIDAD | S7: UTILIDAD | T7: PRECIO VENTA POR RECETA | U7: PRECIO DE VENTA 1 | V7: % GANANCIA | W7: VALOR UTILIDAD | X7: DIF EN PRECIO | Y7: PRECIO DE VENTA2 | Z7: % GANANCIA2 | AA7: VALOR UTILIDAD2 | AB7: DIF EN PRECIO5 | AC7: PRECIO DE VENTA 3 | AD7: % GANANCIA3 | AE7: VALOR UTILIDAD22 | AF7: DIF EN PRECIO55 | AG7: OBSERVACIONES | AH7: ELAINE GARZON | AI7: CALICHE-MANZ | AJ7: VICTOR-CALI | AK7: VARIOS | AL7: OBSERVACION | AM7: SEDE | AN7: ESTADO DE RECETAS
A8: 7T01 | B8: 7 TOROS | C8: 7TRS | D8: 500 ML-Jarabe | E8: HOMEOPATICOS | F8: 01 | G8: JARABES | H8: 010101 | I8: 500 ML | J8: NATURAL PALAGAR | L8: LABORATOIO IMPERIO NATURAL | M8: NATURAL PALAGAR S.A.S | N8: MARIA-IMPERIO NATURAL | O8: ='RECETAS JARABES'!G68 -> 2046.4421 | P8: ='Gtos Varios'!$B$22 -> 3070.5429 | Q8: =+LISTPROD[[#This Row],[PRECIO DE PRODUCCIÓN POR UND]]+LISTPROD[[#This Row],[TOTAL GASTOS VARIOS]] -> 5116.985 | R8: ='RECETAS JARABES'!G73 -> 3088.4609 | S8: ='RECETAS JARABES'!H73 -> 0.54 | T8: ='RECETAS JARABES'!G74 -> 8807.8331 | U8: 8000 | V8: =(LISTPROD[[#This Row],[PRECIO DE VENTA 1]]-LISTPROD[[#This Row],[COSTO TOTAL UNIDAD]])/LISTPROD[[#This Row],[COSTO TOTAL UNIDAD]] -> 0.56342066 | W8: =LISTPROD[[#This Row],[% GANANCIA]]*LISTPROD[[#This Row],[COSTO TOTAL UNIDAD]] -> 2883.015 | X8: =+LISTPROD[[#This Row],[PRECIO DE VENTA 1]]-LISTPROD[[#This Row],[PRECIO VENTA POR RECETA]] -> -807.83305 | AC8: 0 | AH8: 8000 | AI8: 0 | AJ8: 0 | AK8: 0 | AM8: JUNIN | AN8: OK
A9: AM01 | B9: ALICITRIM LT | C9: ALICITRIN CIRCULATORIO | D9: 1000 ML-Jarabe | E9: HOMEOPATICOS | F9: 01 | G9: JARABES | H9: 010102 | I9: 1000 ML | J9: CUBANO | L9: LABORATORIO HOMEOPATICO CUBANO | M9: LABORATORIO HOMEOPATICO CUBANO | N9: ANGIE-LHC | O9: ='RECETAS JARABES'!G98 -> 2074.0653 | P9: ='Gtos Varios'!$B$22 -> 3070.5429 | Q9: =+LISTPROD[[#This Row],[PRECIO DE PRODUCCIÓN POR UND]]+LISTPROD[[#This Row],[TOTAL GASTOS VARIOS]] -> 5144.6082 | R9: ='RECETAS JARABES'!G103 -> 3390.7272 | S9: ='RECETAS JARABES'!$H$103 -> 0.59 | T9: ='RECETAS JARABES'!$G$104 -> 9137.7226 | U9: 7500 | V9: =(LISTPROD[[#This Row],[PRECIO DE VENTA 1]]-LISTPROD[[#This Row],[COSTO TOTAL UNIDAD]])/LISTPROD[[#This Row],[COSTO TOTAL UNIDAD]] -> 0.45783697 | W9: =LISTPROD[[#This Row],[% GANANCIA]]*LISTPROD[[#This Row],[COSTO TOTAL UNIDAD]] -> 2355.3918 | X9: =+LISTPROD[[#This Row],[PRECIO DE VENTA 1]]-LISTPROD[[#This Row],[PRECIO VENTA POR RECETA]] -> -1637.7226 | AC9: 0 | AH9: 7500 | AI9: 0 | AJ9: 0 | AK9: 0 | AN9: PREGUNTAR A LUIS POR PRECIOS Y FORMULA | AR9: CLIENTES
A10: AN01 | B10: ARBRON | C10: ARBRON | D10: 500 ML-Jarabe | E10: HOMEOPATICOS | F10: 01 | G10: JARABES | H10: 010101 | I10: 500 ML | J10: NATURAL PALAGAR | L10: LABORATOIO IMPERIO NATURAL | M10: NATURAL PALAGAR S.A.S | N10: MARIA-IMPERIO NATURAL | O10: ='RECETAS JARABES'!G132 -> 1088.0283 | P10: ='Gtos Varios'!$B$22 -> 3070.5429 | Q10: =+LISTPROD[[#This Row],[PRECIO DE PRODUCCIÓN POR UND]]+LISTPROD[[#This Row],[TOTAL GASTOS VARIOS]] -> 4158.5711 | R10: ='RECETAS JARABES'!G137 -> 3475.4995 | S10: ='RECETAS JARABES'!$H$137 -> 0.73 | T10: ='RECETAS JARABES'!$G$138 -> 8236.4578 | U10: 7000 | V10: =(LISTPROD[[#This Row],[PRECIO DE VENTA 1]]-LISTPROD[[#This Row],[COSTO TOTAL UNIDAD]])/LISTPROD[[#This Row],[COSTO TOTAL UNIDAD]] -> 0.68327047 | W10: =LISTPROD[[#This Row],[% GANANCIA]]*LISTPROD[[#This Row],[COSTO TOTAL UNIDAD]] -> 2841.4289 | X10: =+LISTPROD[[#This Row],[PRECIO DE VENTA 1]]-LISTPROD[[#This Row],[PRECIO VENTA POR RECETA]] -> -1236.4578 | AC10: 0 | AH10: 7000 | AI10: 0 | AJ10: 0 | AK10: 0 | AN10: OK | AR10: PRECIO 1
A11: AV01 | B11: ARTERIO VENOSO | C11: ARTERIO VENOSO | D11: 500 ML-Jarabe | E11: HOMEOPATICOS | G11: JARABES | I11: 500 ML | J11: PHARMA | N11: LUIS-FARMACIA NATIVA | O11: ='RECETAS JARABES'!G167 -> 2134.0639 | P11: ='Gtos Varios'!$B$22 -> 3070.5429 | Q11: =+LISTPROD[[#This Row],[PRECIO DE PRODUCCIÓN POR UND]]+LISTPROD[[#This Row],[TOTAL GASTOS VARIOS]] -> 5204.6067 | R11: ='RECETAS JARABES'!G172 -> 3368.0565 | S11: ='RECETAS JARABES'!$H$172 -> 0.58 | T11: ='RECETAS JARABES'!$G$173 -> 9175.0503 | U11: 6000 | V11: =(LISTPROD[[#This Row],[PRECIO DE VENTA 1]]-LISTPROD[[#This Row],[COSTO TOTAL UNIDAD]])/LISTPROD[[#This Row],[COSTO TOTAL UNIDAD]] -> 0.15282485 | W11: =LISTPROD[[#This Row],[% GANANCIA]]*LISTPROD[[#This Row],[COSTO TOTAL UNIDAD]] -> 795.39326 | X11: =+LISTPROD[[#This Row],[PRECIO DE VENTA 1]]-LISTPROD[[#This Row],[PRECIO VENTA POR RECETA]] -> -3175.0503 | Y11: 5000 | Z11: =(LISTPROD[[#This Row],[PRECIO DE VENTA2]]-LISTPROD[[#This Row],[COSTO TOTAL UNIDAD]])/LISTPROD[[#This Row],[COSTO TOTAL UNIDAD]] -> -0.039312622 | AA11: =+LISTPROD[[#This Row],[% GANANCIA2]]*LISTPROD[[#This Row],[COSTO TOTAL UNIDAD]] -> -204.60674 | AB11: =LISTPROD[[#This Row],[PRECIO DE VENTA2]]-LISTPROD[[#This Row],[PRECIO VENTA POR RECETA]] -> -4175.0503 | AC11: 5000 | AD11: =(LISTPROD[[#This Row],[PRECIO DE VENTA 3]]-LISTPROD[[#This Row],[COSTO TOTAL UNIDAD]])/LISTPROD[[#This Row],[COSTO TOTAL UNIDAD]] -> -0.039312622 | AE11: =LISTPROD[[#This Row],[% GANANCIA3]]*LISTPROD[[#This Row],[COSTO TOTAL UNIDAD]] -> -204.60674 | AH11: 6000 | AI11: 5000 | AJ11: 5000 | AK11: 5000 | AN11: OK | AR11: PRECIO 2-MANZ
A12: A01 | B12: ARTRIN | C12: ARTRIN | D12: PASTILLAS 30 | E12: HOMEOPATICOS | G12: PASTILLAS | I12: PASTILLAS DE 30 UND | N12: LUIS-FARMACIA NATIVA | O12: ='RECETAS PASTILLAS'!G16 -> 2450 | P12: ='Gtos Varios'!$B$22 -> 3070.5429 | Q12: =+LISTPROD[[#This Row],[TOTAL GASTOS VARIOS]]+LISTPROD[[#This Row],[PRECIO DE PRODUCCIÓN POR UND]] -> 5520.5429 | R12: ='RECETAS PASTILLAS'!G21 -> 3367.6115 | S12: ='RECETAS PASTILLAS'!H21 -> 0.55 | T12: ='RECETAS PASTILLAS'!G22 -> 9490.5415 | U12: 3200 | V12: =(LISTPROD[[#This Row],[PRECIO DE VENTA 1]]-LISTPROD[[#This Row],[COSTO TOTAL UNIDAD]])/LISTPROD[[#This Row],[COSTO TOTAL UNIDAD]] -> -0.42034686 | W12: =LISTPROD[[#This Row],[% GANANCIA]]*LISTPROD[[#This Row],[COSTO TOTAL UNIDAD]] -> -2320.5429 | Y12: 3200 | Z12: =(LISTPROD[[#This Row],[PRECIO DE VENTA2]]-LISTPROD[[#This Row],[COSTO TOTAL UNIDAD]])/LISTPROD[[#This Row],[COSTO TOTAL UNIDAD]] -> -0.42034686 | AA12: =LISTPROD[[#This Row],[PRECIO DE VENTA2]]*LISTPROD[[#This Row],[% GANANCIA2]] -> -1345.11 | AC12: 3200 | AD12: =(LISTPROD[[#This Row],[PRECIO DE VENTA 3]]-LISTPROD[[#This Row],[COSTO TOTAL UNIDAD]])/LISTPROD[[#This Row],[COSTO TOTAL UNIDAD]] -> -0.42034686 | AE12: =+LISTPROD[[#This Row],[PRECIO DE VENTA 3]]*LISTPROD[[#This Row],[% GANANCIA3]] -> -1345.11 | AG12: Se toma solo el costo de produccion no margen de utilidad | AH12: 3200 | AI12: 3200 | AJ12: 3200 | AK12: 3200 | AN12: OK-26/3/2025 | AR12: PRECIO 3-Victor
A13: BP01 | B13: BIL PRO | C13: BRIL-PRO | D13: 500 ML-Jarabe | E13: HOMEOPATICOS | F13: 01 | G13: JARABES | H13: 010101 | I13: 500 ML | J13: NATURAL PALAGAR | L13: LABORATOIO IMPERIO NATURAL | M13: NATURAL PALAGAR S.A.S | N13: MARIA-IMPERIO NATURAL | O13: ='RECETAS JARABES'!G200 -> 949.4736 | P13: ='Gtos Varios'!$B$22 -> 3070.5429 | Q13: =+LISTPROD[[#This Row],[PRECIO DE PRODUCCIÓN POR UND]]+LISTPROD[[#This Row],[TOTAL GASTOS VARIOS]] -> 4020.0165 | R13: ='RECETAS JARABES'!G205 -> 3374.3546 | S13: ='RECETAS JARABES'!H205 -> 0.73 | T13: ='RECETAS JARABES'!G206 -> 7996.7582 | U13: 7000 | V13: =(LISTPROD[[#This Row],[PRECIO DE VENTA 1]]-LISTPROD[[#This Row],[COSTO TOTAL UNIDAD]])/LISTPROD[[#This Row],[COSTO TOTAL UNIDAD]] -> 0.7412864 | W13: =LISTPROD[[#This Row],[% GANANCIA]]*LISTPROD[[#This Row],[COSTO TOTAL UNIDAD]] -> 2979.9835 | X13: =+LISTPROD[[#This Row],[PRECIO DE VENTA 1]]-LISTPROD[[#This Row],[PRECIO VENTA POR RECETA]] -> -996.75823 | AH13: 7000 | AI13: 0 | AJ13: 0 | AK13: 0 | AM13: JUNIN | AN13: OK
A14: B01 | B14: BIO 44 | C14: BIO 44 | D14: 500 ML-Jarabe | E14: HOMEOPATICOS | G14: JARABES | I14: 500 ML | J14: PHARMA | N14: LUIS-FARMACIA NATIVA | O14: ='RECETAS JARABES'!G232 -> 2388.8636 | P14: ='Gtos Varios'!$B$22 -> 3070.5429 | Q14: =+LISTPROD[[#This Row],[PRECIO DE PRODUCCIÓN POR UND]]+LISTPROD[[#This Row],[TOTAL GASTOS VARIOS]] -> 5459.4064 | R14: ='RECETAS JARABES'!G237 -> 3333.9865 | S14: ='RECETAS JARABES'!H237 -> 0.55 | T14: ='RECETAS JARABES'!G238 -> 9395.78 | U14: 6000 | V14: =(LISTPROD[[#This Row],[PRECIO DE VENTA 1]]-LISTPROD[[#This Row],[COSTO TOTAL UNIDAD]])/LISTPROD[[#This Row],[COSTO TOTAL UNIDAD]] -> 0.099020578 | W14: =LISTPROD[[#This Row],[% GANANCIA]]*LISTPROD[[#This Row],[COSTO TOTAL UNIDAD]] -> 540.59358 | X14: =+LISTPROD[[#This Row],[PRECIO DE VENTA 1]]-LISTPROD[[#This Row],[PRECIO VENTA POR RECETA]] -> -3395.78 | Y14: 5000 | Z14: =(LISTPROD[[#This Row],[PRECIO DE VENTA2]]-LISTPROD[[#This Row],[COSTO TOTAL UNIDAD]])/LISTPROD[[#This Row],[COSTO TOTAL UNIDAD]] -> -0.084149518 | AA14: =+LISTPROD[[#This Row],[% GANANCIA2]]*LISTPROD[[#This Row],[COSTO TOTAL UNIDAD]] -> -459.40642 | AB14: =LISTPROD[[#This Row],[PRECIO DE VENTA2]]-LISTPROD[[#This Row],[PRECIO VENTA POR RECETA]] -> -4395.78 | AC14: 5000 | AD14: =(LISTPROD[[#This Row],[PRECIO DE VENTA 3]]-LISTPROD[[#This Row],[COSTO TOTAL UNIDAD]])/LISTPROD[[#This Row],[COSTO TOTAL UNIDAD]] -> -0.084149518 | AE14: =LISTPROD[[#This Row],[% GANANCIA3]]*LISTPROD[[#This Row],[COSTO TOTAL UNIDAD]] -> -459.40642 | AH14: 6000 | AI14: 5000 | AJ14: 5000 | AK14: 5000 | AN14: FALTA
A15: BO01 | B15: BOTANPROS | C15: BOTANPROS | D15: 500 ML-Jarabe | E15: HOMEOPATICOS | G15: JARABES | I15: 500 ML | J15: N/A | N15: LUIS-FARMACIA NATIVA | O15: ='RECETAS JARABES'!G264 -> 984.66726 | P15: ='Gtos Varios'!$B$22 -> 3070.5429 | Q15: =+LISTPROD[[#This Row],[PRECIO DE PRODUCCIÓN POR UND]]+LISTPROD[[#This Row],[TOTAL GASTOS VARIOS]] -> 4055.2101 | R15: ='RECETAS JARABES'!G269 -> 3353.47 | S15: ='RECETAS JARABES'!H269 -> 0.72 | T15: ='RECETAS JARABES'!G270 -> 8011.0673 | U15: 7000 | V15: =(LISTPROD[[#This Row],[PRECIO DE VENTA 1]]-LISTPROD[[#This Row],[COSTO TOTAL UNIDAD]])/LISTPROD[[#This Row],[COSTO TOTAL UNIDAD]] -> 0.72617443 | W15: =LISTPROD[[#This Row],[% GANANCIA]]*LISTPROD[[#This Row],[COSTO TOTAL UNIDAD]] -> 2944.7899 | X15: =+LISTPROD[[#This Row],[PRECIO DE VENTA 1]]-LISTPROD[[#This Row],[PRECIO VENTA POR RECETA]] -> -1011.0673 | Y15: 5000 | Z15: =(LISTPROD[[#This Row],[PRECIO DE VENTA2]]-LISTPROD[[#This Row],[COSTO TOTAL UNIDAD]])/LISTPROD[[#This Row],[COSTO TOTAL UNIDAD]] -> 0.23298173 | AA15: =+LISTPROD[[#This Row],[% GANANCIA2]]*LISTPROD[[#This Row],[COSTO TOTAL UNIDAD]] -> 944.78989 | AB15: =LISTPROD[[#This Row],[PRECIO DE VENTA2]]-LISTPROD[[#This Row],[PRECIO VENTA POR RECETA]] -> -3011.0673 | AC15: 5000 | AD15: =(LISTPROD[[#This Row],[PRECIO DE VENTA 3]]-LISTPROD[[#This Row],[COSTO TOTAL UNIDAD]])/LISTPROD[[#This Row],[COSTO TOTAL UNIDAD]] -> 0.23298173 | AE15: =LISTPROD[[#This Row],[% GANANCIA3]]*LISTPROD[[#This Row],[COSTO TOTAL UNIDAD]] -> 944.78989 | AH15: 7000 | AI15: 5000 | AJ15: 5000 | AK15: 5000 | AN15: OK
A16: CO01 | B16: CALCUBANO LT | C16: CALCUBANO | D16: 1000 ML-Jarabe | E16: HOMEOPATICOS | F16: 01 | G16: JARABES | H16: 010102 | I16: 1000 ML | J16: CUBANO | L16: LABORATORIO HOMEOPATICO CUBANO | M16: LABORATORIO HOMEOPATICO CUBANO | N16: ANGIE-LHC | O16: ='RECETAS JARABES'!G295 -> 2745.6159 | P16: ='Gtos Varios'!$B$22 -> 3070.5429 | Q16: =+LISTPROD[[#This Row],[PRECIO DE PRODUCCIÓN POR UND]]+LISTPROD[[#This Row],[TOTAL GASTOS VARIOS]] -> 5816.1587 | R16: ='RECETAS JARABES'!$G$300 -> 3337.6439 | S16: ='RECETAS JARABES'!H300 -> 0.52 | T16: ='RECETAS JARABES'!G301 -> 9756.1897 | U16: 7500 | V16: =(LISTPROD[[#This Row],[PRECIO DE VENTA 1]]-LISTPROD[[#This Row],[COSTO TOTAL UNIDAD]])/LISTPROD[[#This Row],[COSTO TOTAL UNIDAD]] -> 0.28951089 | W16: =LISTPROD[[#This Row],[% GANANCIA]]*LISTPROD[[#This Row],[COSTO TOTAL UNIDAD]] -> 1683.8413 | X16: =+LISTPROD[[#This Row],[PRECIO DE VENTA 1]]-LISTPROD[[#This Row],[PRECIO VENTA POR RECETA]] -> -2256.1897 | Y16: 0 | AA16: =+LISTPROD[[#This Row],[% GANANCIA2]]*LISTPROD[[#This Row],[COSTO TOTAL UNIDAD]] -> 0 | AB16: =LISTPROD[[#This Row],[PRECIO DE VENTA2]]-LISTPROD[[#This Row],[PRECIO VENTA POR RECETA]] -> -9756.1897 | AH16: 7500 | AI16: 0 | AJ16: 0 | AK16: 0 | AN16: OK
A17: CM01 | B17: CARDO MARIANO (Capsulas) | C17: CARDO MARIANO (Capsulas) | D17: ENVASE TIENE 60 CAPSULAS | E17: HOMEOPATICOS | F17: 01 | G17: CAPSULAS | H17: 010202 | I17: CAPSULAS 60 UND | N17: ANGIE-LHC | O17: ='RECETAS CAPS'!U19 -> 3943.7 | P17: ='Gtos Varios'!$B$22 -> 3070.5429 | Q17: =+LISTPROD[[#This Row],[TOTAL GASTOS VARIOS]]+LISTPROD[[#This Row],[PRECIO DE PRODUCCIÓN POR UND]] -> 7014.2429 | R17: ='RECETAS CAPS'!U25 -> 3351.3172 | S17: ='RECETAS CAPS'!V25 -> 0.44 | T17: ='RECETAS CAPS'!U26 -> 10967.947 | U17: 10968 | V17: =(LISTPROD[[#This Row],[PRECIO DE VENTA 1]]-LISTPROD[[#This Row],[COSTO TOTAL UNIDAD]])/LISTPROD[[#This Row],[COSTO TOTAL UNIDAD]] -> 0.56367554 | W17: =LISTPROD[[#This Row],[% GANANCIA]]*LISTPROD[[#This Row],[COSTO TOTAL UNIDAD]] -> 3953.7571 | AH17: 9600 | AI17: 0 | AJ17: 0 | AK17: 0 | AM17: JUNIN | AN17: OK
A18: CT01 | B18: CARTILAGO DE TIBURON | C18: CARTILAGO DE TIBURON | D18: 500 ML-Jarabe | E18: HOMEOPATICOS | G18: JARABES | I18: 500 ML | J18: PHARMA | N18: LUIS-FARMACIA NATIVA | O18: ='RECETAS JARABES'!G327 -> 2482.1171 | P18: ='Gtos Varios'!$B$22 -> 3070.5429 | Q18: =+LISTPROD[[#This Row],[PRECIO DE PRODUCCIÓN POR UND]]+LISTPROD[[#This Row],[TOTAL GASTOS VARIOS]] -> 5552.6599 | R18: ='RECETAS JARABES'!$G$332 -> 3323.7254 | S18: ='RECETAS JARABES'!$H$332 -> 0.54 | T18: ='RECETAS JARABES'!$G$333 -> 9478.7725 | U18: 6000 | V18: =(LISTPROD[[#This Row],[PRECIO DE VENTA 1]]-LISTPROD[[#This Row],[COSTO TOTAL UNIDAD]])/LISTPROD[[#This Row],[COSTO TOTAL UNIDAD]] -> 0.080563205 | W18: =LISTPROD[[#This Row],[% GANANCIA]]*LISTPROD[[#This Row],[COSTO TOTAL UNIDAD]] -> 447.34008 | X18: =+LISTPROD[[#This Row],[PRECIO DE VENTA 1]]-LISTPROD[[#This Row],[PRECIO VENTA POR RECETA]] -> -3478.7725 | Y18: 5000 | Z18: =(LISTPROD[[#This Row],[PRECIO DE VENTA2]]-LISTPROD[[#This Row],[COSTO TOTAL UNIDAD]])/LISTPROD[[#This Row],[COSTO TOTAL UNIDAD]] -> -0.099530663 | AA18: =+LISTPROD[[#This Row],[% GANANCIA2]]*LISTPROD[[#This Row],[COSTO TOTAL UNIDAD]] -> -552.65992 | AB18: =LISTPROD[[#This Row],[PRECIO DE VENTA2]]-LISTPROD[[#This Row],[PRECIO VENTA POR RECETA]] -> -4478.7725 | AC18: 5000 | AD18: =(LISTPROD[[#This Row],[PRECIO DE VENTA 3]]-LISTPROD[[#This Row],[COSTO TOTAL UNIDAD]])/LISTPROD[[#This Row],[COSTO TOTAL UNIDAD]] -> -0.099530663 | AE18: =LISTPROD[[#This Row],[% GANANCIA3]]*LISTPROD[[#This Row],[COSTO TOTAL UNIDAD]] -> -552.65992 | AH18: 6000 | AI18: 5000 | AJ18: 5000 | AK18: 5000 | AN18: OK
A19: CHP01 | B19: CHANCA PIEDRA JARABE | C19: CHANCA PIEDRA JARABE | D19: 500 ML-Jarabe | E19: HOMEOPATICOS | G19: JARABES | I19: 500 ML | J19: PHARMA | N19: LUIS-FARMACIA NATIVA | O19: ='RECETAS JARABES'!G364 -> 2112.0478 | P19: ='Gtos Varios'!$B$22 -> 3070.5429 | Q19: =+LISTPROD[[#This Row],[PRECIO DE PRODUCCIÓN POR UND]]+LISTPROD[[#This Row],[TOTAL GASTOS VARIOS]] -> 5182.5907 | R19: ='RECETAS JARABES'!$G$369 -> 3355.2871 | S19: ='RECETAS JARABES'!H369 -> 0.58 | T19: ='RECETAS JARABES'!G370 -> 9140.265 | U19: 6000 | V19: =(LISTPROD[[#This Row],[PRECIO DE VENTA 1]]-LISTPROD[[#This Row],[COSTO TOTAL UNIDAD]])/LISTPROD[[#This Row],[COSTO TOTAL UNIDAD]] -> 0.15772215 | W19: =LISTPROD[[#This Row],[% GANANCIA]]*LISTPROD[[#This Row],[COSTO TOTAL UNIDAD]] -> 817.40932 | X19: =+LISTPROD[[#This Row],[PRECIO DE VENTA 1]]-LISTPROD[[#This Row],[PRECIO VENTA POR RECETA]] -> -3140.265 | Y19: 5000 | Z19: =(LISTPROD[[#This Row],[PRECIO DE VENTA2]]-LISTPROD[[#This Row],[COSTO TOTAL UNIDAD]])/LISTPROD[[#This Row],[COSTO TOTAL UNIDAD]] -> -0.035231546 | AA19: =+LISTPROD[[#This Row],[% GANANCIA2]]*LISTPROD[[#This Row],[COSTO TOTAL UNIDAD]] -> -182.59068 | AB19: =LISTPROD[[#This Row],[PRECIO DE VENTA2]]-LISTPROD[[#This Row],[PRECIO VENTA POR RECETA]] -> -4140.265 | AC19: 5000 | AD19: =(LISTPROD[[#This Row],[PRECIO DE VENTA 3]]-LISTPROD[[#This Row],[COSTO TOTAL UNIDAD]])/LISTPROD[[#This Row],[COSTO TOTAL UNIDAD]] -> -0.035231546 | AE19: =LISTPROD[[#This Row],[% GANANCIA3]]*LISTPROD[[#This Row],[COSTO TOTAL UNIDAD]] -> -182.59068 | AH19: 6000 | AI19: 5000 | AJ19: 5000 | AK19: 5000 | AN19: OK
A20: CL01 | B20: CIR LAN (500ml) | C20: CIR/LAN | D20: 500 ML-Jarabe | E20: HOMEOPATICOS | F20: 01 | G20: JARABES | H20: 010101 | I20: 500 ML | J20: NATURAL PALAGAR | L20: LABORATOIO IMPERIO NATURAL | M20: NATURAL PALAGAR S.A.S | N20: MARIA-IMPERIO NATURAL | O20: ='RECETAS JARABES'!G396 -> 1054.3662 | P20: ='Gtos Varios'!$B$22 -> 3070.5429 | Q20: =+LISTPROD[[#This Row],[PRECIO DE PRODUCCIÓN POR UND]]+LISTPROD[[#This Row],[TOTAL GASTOS VARIOS]] -> 4124.9091 | R20: ='RECETAS JARABES'!G401 -> 3450.9262 | S20: ='RECETAS JARABES'!H401 -> 0.73 | T20: ='RECETAS JARABES'!G402 -> 8178.2224 | U20: 7000 | V20: =(LISTPROD[[#This Row],[PRECIO DE VENTA 1]]-LISTPROD[[#This Row],[COSTO TOTAL UNIDAD]])/LISTPROD[[#This Row],[COSTO TOTAL UNIDAD]] -> 0.69700711 | W20: =LISTPROD[[#This Row],[% GANANCIA]]*LISTPROD[[#This Row],[COSTO TOTAL UNIDAD]] -> 2875.0909 | X20: =+LISTPROD[[#This Row],[PRECIO DE VENTA 1]]-LISTPROD[[#This Row],[PRECIO VENTA POR RECETA]] -> -1178.2224 | AH20: 7000 | AI20: 0 | AJ20: 0 | AK20: 0 | AM20: JUNIN | AN20: OK
A21: CV01 | B21: CIRCULAV LT | C21: CIRCULAV PLUS | D21: 1000 ML-Jarabe | E21: HOMEOPATICOS | F21: 01 | G21: JARABES | H21: 010102 | I21: 1000 ML | J21: CUBANO | L21: LABORATORIO HOMEOPATICO CUBANO | M21: LABORATORIO HOMEOPATICO CUBANO | N21: ANGIE-LHC | O21: ='RECETAS JARABES'!G426 -> 2060.4127 | P21: ='Gtos Varios'!$B$22 -> 3070.5429 | Q21: =+LISTPROD[[#This Row],[PRECIO DE PRODUCCIÓN POR UND]]+LISTPROD[[#This Row],[TOTAL GASTOS VARIOS]] -> 5130.9555 | R21: ='RECETAS JARABES'!G431 -> 3210.6719 | S21: ='RECETAS JARABES'!H431 -> 0.56 | T21: ='RECETAS JARABES'!G432 -> 8944.0146 | U21: 7500 | V21: =(LISTPROD[[#This Row],[PRECIO DE VENTA 1]]-LISTPROD[[#This Row],[COSTO TOTAL UNIDAD]])/LISTPROD[[#This Row],[COSTO TOTAL UNIDAD]] -> 0.46171604 | W21: =LISTPROD[[#This Row],[% GANANCIA]]*LISTPROD[[#This Row],[COSTO TOTAL UNIDAD]] -> 2369.0445 | X21: =+LISTPROD[[#This Row],[PRECIO DE VENTA 1]]-LISTPROD[[#This Row],[PRECIO VENTA POR RECETA]] -> -1444.0146 | AH21: 7500 | AI21: 0 | AJ21: 0 | AK21: 0 | AN21: PREGUNTAR A LUIS POR PRECIOS Y FORMULA
A22: CG01 | B22: COLAGENO | C22: COLAGENO | D22: 500 ML-Jarabe | E22: HOMEOPATICOS | G22: JARABES | I22: 500 ML | J22: PHARMA | N22: LUIS-FARMACIA NATIVA | O22: ='RECETAS JARABES'!G460 -> 2662.4346 | P22: ='Gtos Varios'!$B$22 -> 3070.5429 | Q22: =+LISTPROD[[#This Row],[PRECIO DE PRODUCCIÓN POR UND]]+LISTPROD[[#This Row],[TOTAL GASTOS VARIOS]] -> 5732.9774 | R22: ='RECETAS JARABES'!G465 -> 3357.7432 | S22: ='RECETAS JARABES'!H465 -> 0.53 | T22: ='RECETAS JARABES'!G466 -> 9693.1078 | U22: 6000 | V22: =(LISTPROD[[#This Row],[PRECIO DE VENTA 1]]-LISTPROD[[#This Row],[COSTO TOTAL UNIDAD]])/LISTPROD[[#This Row],[COSTO TOTAL UNIDAD]] -> 0.046576599 | W22: =LISTPROD[[#This Row],[% GANANCIA]]*LISTPROD[[#This Row],[COSTO TOTAL UNIDAD]] -> 267.02259 | X22: =+LISTPROD[[#This Row],[PRECIO DE VENTA 1]]-LISTPROD[[#This Row],[PRECIO VENTA POR RECETA]] -> -3693.1078 | Y22: 5000 | Z22: =(LISTPROD[[#This Row],[PRECIO DE VENTA2]]-LISTPROD[[#This Row],[COSTO TOTAL UNIDAD]])/LISTPROD[[#This Row],[COSTO TOTAL UNIDAD]] -> -0.12785283 | AA22: =+LISTPROD[[#This Row],[% GANANCIA2]]*LISTPROD[[#This Row],[COSTO TOTAL UNIDAD]] -> -732.97741 | AB22: =LISTPROD[[#This Row],[PRECIO DE VENTA2]]-LISTPROD[[#This Row],[PRECIO VENTA POR RECETA]] -> -4693.1078 | AC22: 5000 | AD22: =(LISTPROD[[#This Row],[PRECIO DE VENTA 3]]-LISTPROD[[#This Row],[COSTO TOTAL UNIDAD]])/LISTPROD[[#This Row],[COSTO TOTAL UNIDAD]] -> -0.12785283 | AE22: =LISTPROD[[#This Row],[% GANANCIA3]]*LISTPROD[[#This Row],[COSTO TOTAL UNIDAD]] -> -732.97741 | AH22: 6000 | AI22: 5000 | AJ22: 5000 | AK22: 5000 | AN22: OK
A23: CC01 | B23: COLIRIO CUBANO (Gotas) | C23: COLIRIO CUBANO (Gotas) | D23: Gotas 25 ML | E23: HOMEOPATICOS | G23: GOTAS | I23: 25 ML | N23: LUIS-FARMACIA NATIVA | O23: ='RECETAS GOTAS'!$K$151 -> 1796.5759 | P23: ='Gtos Varios'!B$22 -> 3070.5429 | Q23: =+LISTPROD[[#This Row],[TOTAL GASTOS VARIOS]]+LISTPROD[[#This Row],[PRECIO DE PRODUCCIÓN POR UND]] -> 4867.1188 | R23: ='RECETAS GOTAS'!$K$156 -> 3391.0937 | S23: ='RECETAS GOTAS'!L156 -> 0.62 | T23: ='RECETAS GOTAS'!$K$157 -> 8860.5996 | U23: 3500 | V23: =(LISTPROD[[#This Row],[PRECIO DE VENTA 1]]-LISTPROD[[#This Row],[COSTO TOTAL UNIDAD]])/LISTPROD[[#This Row],[COSTO TOTAL UNIDAD]] -> -0.28088872 | W23: =LISTPROD[[#This Row],[% GANANCIA]]*LISTPROD[[#This Row],[COSTO TOTAL UNIDAD]] -> -1367.1188 | AC23: 0 | AH23: 3500 | AI23: 0 | AJ23: 0 | AK23: 0 | AN23: PREGUNTAR A LUIS POR PRECIOS Y FORMULA
